Workbook

Sheet Menkul Kıymet
A1: Tarih | B1: Hisse Senedi Stok | C1: DİBS STOK | D1: Repo Stok | E1: ÖSBA STOK | I1: Hisse Senedi Flow | J1: DIBS Flow | K1: REPO Flow | L1: OSBA Flow | O1: Eurobond | P1: Hazine Eurobond Stok | Q1: Hazine Eurobond Flow | S1: Şirket Eurobond Stok | T1: Şirket Eurobond Flow
A2: 04-05-2018 | B2: TP.PYUK1 | C2: TP.PYUK2 | D2: TP.PYUK21 | E2: TP.PYUK22 | I2: TP.PYUK3 | J2: TP.PYUK4 | K2: TP.PYUK5 | L2: TP.PYUK5 | P2: TP.BS07.CARI | Q2: TP.BS07.NOMINAL | S2: TP.HDBSC.K7 | T2: TP.HDBSN.K7
A3: 11-05-2018 | B3: 40832.5 | C3: 27101.3 | D3: 1941.1 | E3: 876.9 | I3: 28.8 | J3: -230.9 | K3: -24.8 | L3: -5.8 | P3: 44522.5 | Q3: 45876.1 | S3: TP.HDBSC.K18 | T3: TP.HDBSN.K18
A4: 18-05-2018 | B4: 39586.5 | C4: 24693.6 | D4: 1820.7 | E4: 835.5 | I4: -72 | J4: -637.9 | K4: -26.2 | L4: -41.5 | P4: 43152.1 | Q4: 45743.6 | S4: TP.HDBSC.K29 | T4: TP.HDBSN.K29
A5: 25-05-2018 | B5: 37480 | C5: 23252.9 | D5: 1718.4 | E5: 789.6 | I5: -9.4 | J5: -144.3 | K5: -4.8 | L5: -45.9 | P5: 44093 | Q5: 45811.5 | S5: 45791.36 | T5: 0
A6: 01-06-2018 | B6: 38096.5 | C6: 24828.5 | D6: 1780.2 | E6: 767.1 | I6: 15 | J6: 29.4 | K6: -31.3 | L6: -22.5 | P6: 43224.7 | Q6: 45445.6 | S6: 45712.58 | T6: 0
A7: 08-06-2018 | B7: 36210.3 | C7: 23662.5 | D7: 2594 | E7: 779.1 | I7: -218.6 | J7: -170.9 | K7: 843.7 | L7: 12 | P7: 43829.5 | Q7: 46004.6 | S7: 45775.17 | T7: 0
A8: 15-06-2018 | B8: 34839 | C8: 22298.3 | D8: 1717.2 | E8: 753.7 | I8: 289.1 | J8: -459.5 | K8: -815.5 | L8: -25.4 | P8: 42984.8 | Q8: 45680.8 | S8: 44862.32 | T8: 48064.27
A9: 22-06-2018 | B9: 34921.4 | C9: 21695.5 | D9: 1622.1 | E9: 756.3 | I9: 225.4 | J9: 131.5 | K9: -54 | L9: 2.6 | P9: 43469.7 | Q9: 45781.9 | S9: 44733.92 | T9: 47752.94
A10: 29-06-2018 | B10: 36121.6 | C10: 22403 | D10: 1672.2 | E10: 781.6 | I10: -179.8 | J10: 83.2 | K10: -10.1 | L10: 25.3 | P10: 43398.1 | Q10: 45750.3 | S10: 44756.86 | T10: 47730.59
A11: 06-07-2018 | B11: 36279.8 | C11: 22280.8 | D11: 1663.3 | E11: 766.6 | I11: -80.8 | J11: 397.4 | K11: 0.7 | L11: -15 | P11: 43877.6 | Q11: 45863.4 | S11: 44899.8 | T11: 47793.82
A12: 13-07-2018 | B12: 32781.1 | C12: 20552.3 | D12: 1598.3 | E12: 727.9 | I12: -213.8 | J12: 49.4 | K12: -0.2 | L12: -38.8 | P12: 42442.1 | Q12: 45510.8 | S12: 43791.26 | T12: 47657.21
A13: 20-07-2018 | B13: 31192.5 | C13: 20500 | D13: 1593.4 | E13: 773.6 | I13: -222.2 | J13: -256.4 | K13: -0.3 | L13: 45.7 | P13: 43293.4 | Q13: 45765.8 | S13: 44007.76 | T13: 47563.58
A14: 27-07-2018 | B14: 32564.2 | C14: 20376.5 | D14: 1593.4 | E14: 769.4 | I14: 28.3 | J14: -18.2 | K14: 0.6 | L14: -4.2 | P14: 43048.5 | Q14: 45758.7 | S14: 44016.37 | T14: 47595.61
A15: 03-08-2018 | B15: 31645.1 | C15: 18622.3 | D15: 1517 | E15: 715.9 | I15: 77.6 | J15: -182.1 | K15: 4.4 | L15: -53.5 | P15: 42466.2 | Q15: 45691.9 | S15: 42623.31 | T15: 47083.78
A16: 10-08-2018 | B16: 29363.1 | C16: 17078.8 | D16: 1445.5 | E16: 671.4 | I16: 45.8 | J16: -196.5 | K16: 21.4 | L16: -44.5 | P16: 40298.9 | Q16: 45725.8 | S16: 40046.7 | T16: 46763.08
... A133: 06-11-2020 | B133: 19728.6 | C133: 4960.2 | D133: 131.4 | E133: 212.2 | I133: -22 | J133: -4.5 | K133: 5.1 | L133: -9.1 | P133: 43703.7 | Q133: 46402 | S133: 36129.01 | T133: 37391.31
A134: 13-11-2020 | B134: 23507.6 | C134: 5803.8 | D134: 166.9 | E134: 232 | I134: 614.4 | J134: 293.9 | K134: 22.9 | L134: 19.8 | P134: 46119.8 | Q134: 46415 | S134: 36951.64 | T134: 37662.08 | V134: 6 Kasım Sonrası Flow
A135: 20-11-2020 | B135: 25306.8 | C135: 6151.8 | D135: 234.4 | E135: 239.2 | I135: 389.6 | J135: 175.5 | K135: 64.1 | L135: 7.2 | P135: 46319.6 | Q135: 46274.7 | S135: 37173.91 | T135: 37597.57 | V135: Hisse Flow
A136: 27-11-2020 | B136: 25059.6 | C136: 6114.1 | D136: 172.3 | E136: 230.6 | I136: 231.7 | J136: 147.2 | K136: -55.9 | L136: -8.6 | P136: 46235.2 | Q136: 46363.1 | S136: 37081.01 | T136: 37449.3 | V136: =SUM(I133:I152) -> 701.8
A137: 04-12-2020 | B137: 25043.3 | C137: 6195 | D137: 134.3 | E137: 228.1 | I137: -23.3 | J137: 91.4 | K137: -39.1 | L137: -2.4 | P137: 48847.2 | Q137: 48487.9 | S137: 37334.06 | T137: 37571.4 | V137: DIBS Flow
A138: 11-12-2020 | B138: 25317.1 | C138: 6248.6 | D138: 138.7 | E138: 223.6 | I138: 41 | J138: 99 | K138: 4 | L138: -4.5 | P138: 48420.3 | Q138: 48515.4 | S138: 38182.92 | T138: 38358.69 | V138: =SUM(J133:J152) -> 4428.6
A139: 18-12-2020 | B139: 26540.1 | C139: 8028.3 | D139: 1733.1 | E139: 219 | I139: 244 | J139: 1661.8 | K139: 1591.5 | L139: -4.6 | P139: 49628.3 | Q139: 48717.8 | S139: 38115.65 | T139: 38207.08 | V139: Repo Flow
A140: 25-12-2020 | B140: 27275 | C140: 8270.8 | D140: 1717.6 | E140: 224 | I140: -18.8 | J140: 106.7 | K140: -30.9 | L140: 5 | P140: 49594.7 | Q140: 48726.9 | S140: 38306.63 | T140: 38397.31 | V140: =SUM(K133:K152) -> 1732.2
A141: 01-01-2021 | B141: 29168.1 | C141: 8597.5 | D141: 1850.3 | E141: 224.8 | I141: 90.7 | J141: 35.1 | K141: 94.7 | L141: 0.8 | P141: 49910.2 | Q141: 48640.7 | S141: 38459.17 | T141: 38388.19 | V141: OSBA Flow
A142: 08-01-2021 | B142: 30874.4 | C142: 9159 | D142: 1817.2 | E142: 222.3 | I142: 287.7 | J142: 491.1 | K142: -44.5 | L142: -2.5 | P142: 49897.9 | Q142: 48821.7 | S142: 38445.64 | T142: 38397.69 | V142: =SUM(L133:L152) -> 60.8
A143: 15-01-2021 | B143: 30534.5 | C143: 8981.2 | D143: 1886 | E143: 222.5 | I143: 31.4 | J143: -17.7 | K143: 93.8 | L143: 0.2 | P143: 49481 | Q143: 48932.7 | S143: 38956.51 | T143: 38746.47 | V143: TR Eurobond Flow
A144: 22-01-2021 | B144: 30429.7 | C144: 9062 | D144: 1875.3 | E144: 248.9 | I144: -117.7 | J144: 33.4 | K144: -10.8 | L144: 26.3 | P144: 49407.9 | Q144: 48758.9 | S144: 38960.06 | T144: 38720.16 | V144: =Q152-Q133 -> 3645
A145: 29-01-2021 | B145: 28920 | C145: 9523.2 | D145: 1875.6 | E145: 239.1 | I145: -493.7 | J145: 418.7 | K145: 4.5 | L145: -9.8 | P145: 52961.3 | Q145: 51896.8 | S145: 39583.37 | T145: 39277.1 | V145: Şirket Eurobond Flow
A146: 05-02-2021 | B146: 30814.9 | C146: 9961.5 | D146: 1923.7 | E146: 272.9 | I146: -183.2 | J146: 140.5 | K146: 21.6 | L146: 33.8 | P146: 53500 | Q146: 52029.5 | S146: 40359.61 | T146: 39883.7 | V146: =T152-T133 -> 1406.19
A147: 12-02-2021 | B147: 31019.6 | C147: 10249.9 | D147: 1964.6 | E147: 281.4 | I147: -62.3 | J147: 128.2 | K147: 15.7 | L147: 8.5 | P147: 53750.8 | Q147: 52320.7 | S147: 39821.75 | T147: 39228.5 | V147: Swap
A148: 19-02-2021 | B148: 31378 | C148: 10474.5 | D148: 1969.2 | E148: 289.2 | I148: -122.8 | J148: 194.5 | K148: -4.6 | L148: 7.8 | P148: 53468.3 | Q148: 52213.8 | S148: 39952.43 | T148: 39278.9 | V148: =Swap!G12 -> 14903
A149: 26-02-2021 | B149: 28563.1 | C149: 10254.2 | D149: 1962 | E149: 267.6 | I149: -117.6 | J149: 83.2 | K149: 17.4 | L149: -21.6 | P149: 52314.5 | Q149: 52057.2 | S149: 39698.58 | T149: 39160.2 | V149: Total Giriş-
A150: 05-03-2021 | B150: 28969.9 | C150: 9853.1 | D150: 1932.5 | E150: 263.5 | I150: -10.1 | J150: 49.8 | K150: 22.9 | L150: -4.2 | P150: 51513.5 | Q150: 51868.2 | S150: 39648.66 | T150: 39163.8 | V150: =SUM(V135:V148) -> 26877.59
A151: 12-03-2021 | B151: 29154 | C151: 9604.2 | D151: 1904.5 | E151: 282.3 | I151: -117.6 | J151: -126.4 | K151: 3.1 | L151: 18.9 | P151: 51302.3 | Q151: 51472.4 | S151: 39142.54 | T151: 38731.3
A152: 19-03-2021 | B152: 28946.4 | C152: 9956.7 | D152: 1858 | E152: 282.1 | I152: 60.4 | J152: 427.2 | K152: -43.3 | L152: -0.2 | P152: 50127 | Q152: 50047 | S152: 39281.78 | T152: 38797.5
A153: 44281 | B153: 23782.3 | C153: 7670.5 | D153: 1724.1 | E153: 265.3 | I153: -813.9 | J153: -1104.8 | K153: -11.7 | L153: -16.8 | P153: 46628.5 | Q153: 49460.8 | S153: 38186.32 | T153: 38653.8
A154: 44288 | B154: 23405.5 | C154: 7370.4 | D154: 1718.6 | E154: 261.2 | I154: -364.4 | J154: -140.4 | K154: 13.1 | L154: -4.1 | P154: 46148.2 | Q154: 48481.4 | S154: 39516.66 | T154: 38814.4
A155: 44295 | B155: 22776.3 | C155: 7464 | D155: 1724.2 | E155: 264.7 | I155: -46 | J155: 77.9 | K155: -6 | L155: 3.4 | P155: 46116.6 | Q155: 48143.1 | S155: 38533.3 | T155: 38755.2
A156: 44302 | B156: 23176.5 | C156: 7786.5 | D156: 1921.1 | E156: 282.7 | I156: 0 | J156: 164.9 | K156: 172 | L156: 18 | P156: 46686.5 | Q156: 47959.1 | S156: 38992.42 | T156: 38912.5
A157: 44308 | B157: 21755.5 | C157: 7473.5 | D157: 1593.6 | E157: 260.6 | I157: 104.5 | J157: -252.6 | K157: -323.8 | L157: -22.1 | P157: 46437.4 | Q157: 47912.8 | S157: 38650.69 | T157: 38426.2
A158: 44316 | B158: 22002.3 | C158: 7481.6 | D158: 1727.2 | E158: 267 | I158: 31.5 | J158: 33 | K158: 129.6 | L158: 6.5 | P158: 46213.8 | Q158: 47822.9 | S158: 38704.68 | T158: 38419.7
A159: 44323 | B159: 22182.2 | C159: 7440.1 | D159: 1697.1 | E159: 269.5 | I159: 87.7 | J159: 23.7 | K159: -12.4 | L159: 2.4 | P159: 46627.7 | Q159: 47567.8 | S159: 38256.9 | T159: 37857.9
A160: 44330 | B160: 22386.9 | C160: 7591 | D160: 1737.6 | E160: 271.6 | I160: 51.7 | J160: 118.5 | K160: 27.5 | L160: 2.1 | P160: 46405.3 | Q160: 47538.3 | S160: 38332.12 | T160: 37862.4
A161: 44337 | B161: 22366.7 | C161: 7707.8 | D161: 1780.1 | E161: 291.3 | I161: 51 | J161: 174.8 | K161: 47.8 | L161: 19.7 | P161: 46650.7 | Q161: 47583 | S161: 38542 | T161: 38009
A162: 44344 | B162: 21624 | C162: 7671.9 | D162: 2040.8 | E162: 264.2 | I162: 6.8 | J162: 69.2 | K162: 267.7 | L162: -27.1 | P162: 46381.9 | Q162: 47321.9 | S162: 39120 | T162: 38528
A163: 44351 | B163: 21303.1 | C163: 7447.6 | D163: 2009.3 | E163: 234.5 | I163: -97.7 | J163: -64.1 | K163: -13 | L163: -29.7 | P163: 46217.1 | Q163: 47163.6 | S163: 39328 | T163: 38738
A164: 44358 | B164: 21982.5 | C164: 7630.4 | D164: 1908.9 | E164: 251 | I164: 33.5 | J164: 80.3 | K164: -112.1 | L164: 16.5 | P164: 46527.6 | Q164: 46524.6 | S164: 39524.95 | T164: 38808.95
... A172: 44414 | B172: 22047.5 | C172: 8570.7 | D172: 1778.1 | E172: 224.2 | I172: 168 | J172: 113.8 | K172: -15.5 | L172: -3.2 | P172: 47528.9 | Q172: 47979.2 | S172: 41498.59 | T172: 40671.8
A173: 44421

Sheet DTH
A1: Her Perşembe | B1: date | C1: bireylerin döviz hesapları | D1: tuzellerin döviz hesapları | E1: birey - tüzel spreadi | F1: Birey / Tüzel Rasyosu | G1: Toplam | H1: birey | I1: 13w Birey kümülatif | J1: tuzel | K1: 13w Tüzel kümülatif | L1: Toplam | M1: 13w toplam kümülatif
A2: EVDS -> YABANCI PARA MEVDUAT | B2: 41263 | C2: 67883 | D2: 43637 | G2: =C2+D2 -> 111520
B3: 41264 | C3: 68103 | D3: 44074 | E3: =C3-D3 -> 24029 | F3: =C3/D3 -> 1.5451967 | G3: =C3+D3 -> 112177 | H3: =C3-C2 -> 220 | J3: =D3-D2 -> 437 | L3: =H3+J3 -> 657
B4: 41271 | C4: 77793.038 | D4: 45253.757 | E4: =C4-D4 -> 32539.281 | F4: =C4/D4 -> 1.7190404 | G4: =C4+D4 -> 123046.79 | H4: =C4-C3 -> 9690.0378 | J4: =D4-D3 -> 1179.7567 | L4: =H4+J4 -> 10869.794
B5: 41278 | C5: 77858.058 | D5: 43850.298 | E5: =C5-D5 -> 34007.761 | F5: =C5/D5 -> 1.7755423 | G5: =C5+D5 -> 121708.36 | H5: =C5-C4 -> 65.020601 | J5: =D5-D4 -> -1403.4588 | L5: =H5+J5 -> -1338.4382
B6: 41285 | C6: 78964.258 | D6: 46448.785 | E6: =C6-D6 -> 32515.473 | F6: =C6/D6 -> 1.7000285 | G6: =C6+D6 -> 125413.04 | H6: =C6-C5 -> 1106.1995 | J6: =D6-D5 -> 2598.487 | L6: =H6+J6 -> 3704.6865
B7: 41292 | C7: 79634.204 | D7: 46944.187 | E7: =C7-D7 -> 32690.016 | F7: =C7/D7 -> 1.6963592 | G7: =C7+D7 -> 126578.39 | H7: =C7-C6 -> 669.94582 | J7: =D7-D6 -> 495.4026 | L7: =H7+J7 -> 1165.3484
B8: 41299 | C8: 79853.274 | D8: 47154.437 | E8: =C8-D8 -> 32698.837 | F8: =C8/D8 -> 1.6934413 | G8: =C8+D8 -> 127007.71 | H8: =C8-C7 -> 219.07024 | J8: =D8-D7 -> 210.2498 | L8: =H8+J8 -> 429.32004
B9: 41306 | C9: 80655.624 | D9: 46678.861 | E9: =C9-D9 -> 33976.763 | F9: =C9/D9 -> 1.7278833 | G9: =C9+D9 -> 127334.48 | H9: =C9-C8 -> 802.34972 | J9: =D9-D8 -> -475.57671 | L9: =H9+J9 -> 326.773
B10: 41313 | C10: 80351.913 | D10: 46014.276 | E10: =C10-D10 -> 34337.638 | F10: =C10/D10 -> 1.7462388 | G10: =C10+D10 -> 126366.19 | H10: =C10-C9 -> -303.71043 | J10: =D10-D9 -> -664.58496 | L10: =H10+J10 -> -968.29539
B11: 41320 | C11: 80156.365 | D11: 44957.208 | E11: =C11-D11 -> 35199.158 | F11: =C11/D11 -> 1.782948 | G11: =C11+D11 -> 125113.57 | H11: =C11-C10 -> -195.54805 | J11: =D11-D10 -> -1057.068 | L11: =H11+J11 -> -1252.6161
B12: 41327 | C12: 79307.744 | D12: 44005.48 | E12: =C12-D12 -> 35302.264 | F12: =C12/D12 -> 1.8022243 | G12: =C12+D12 -> 123313.22 | H12: =C12-C11 -> -848.62087 | J12: =D12-D11 -> -951.72766 | L12: =H12+J12 -> -1800.3485
B13: 41334 | C13: 78598.018 | D13: 43992.928 | E13: =C13-D13 -> 34605.09 | F13: =C13/D13 -> 1.7866058 | G13: =C13+D13 -> 122590.95 | H13: =C13-C12 -> -709.72626 | J13: =D13-D12 -> -12.552379 | L13: =H13+J13 -> -722.27864
B14: 41341 | C14: 78504.977 | D14: 44519.366 | E14: =C14-D14 -> 33985.611 | F14: =C14/D14 -> 1.7633894 | G14: =C14+D14 -> 123024.34 | H14: =C14-C13 -> -93.040993 | J14: =D14-D13 -> 526.43833 | L14: =H14+J14 -> 433.39734
B15: 41348 | C15: 78093.298 | D15: 44954.751 | E15: =C15-D15 -> 33138.548 | F15: =C15/D15 -> 1.7371534 | G15: =C15+D15 -> 123048.05 | H15: =C15-C14 -> -411.67851 | I15: =SUM(H3:H15) -> 10210.298 | J15: =D15-D14 -> 435.38504 | K15: =SUM(J3:J15) -> 1317.7509 | L15: =H15+J15 -> 23.706524 | M15: =SUM(L3:L15) -> 11528.049
B16: 41355 | C16: 77324.736 | D16: 44966.802 | E16: =C16-D16 -> 32357.934 | F16: =C16/D16 -> 1.7195961 | G16: =C16+D16 -> 122291.54 | H16: =C16-C15 -> -768.56225 | I16: =SUM(H4:H16) -> 9221.7362 | J16: =D16-D15 -> 12.051466 | K16: =SUM(J4:J16) -> 892.80239 | L16: =H16+J16 -> -756.51078 | M16: =SUM(L4:L16) -> 10114.539
B17: 41362 | C17: 77133.158 | D17: 45462.069 | E17: =C17-D17 -> 31671.09 | F17: =C17/D17 -> 1.6966487 | G17: =C17+D17 -> 122595.23 | H17: =C17-C16 -> -191.57781 | I17: =SUM(H5:H17) -> -659.87935 | J17: =D17-D16 -> 495.26644 | K17: =SUM(J5:J17) -> 208.31216 | L17: =H17+J17 -> 303.68863 | M17: =SUM(L5:L17) -> -451.56719
B18: 41369 | C18: 77818.122 | D18: 46570.177 | E18: =C18-D18 -> 31247.945 | F18: =C18/D18 -> 1.6709862 | G18: =C18+D18 -> 124388.3 | H18: =C18-C17 -> 684.96315 | I18: =SUM(H6:H18) -> -39.936799 | J18: =D18-D17 -> 1108.1077 | K18: =SUM(J6:J18) -> 2719.8787 | L18: =H18+J18 -> 1793.0709 | M18: =SUM(L6:L18) -> 2679.9419
B19: 41376 | C19: 78921.064 | D19: 47632.586 | E19: =C19-D19 -> 31288.479 | F19: =C19/D19 -> 1.6568713 | G19: =C19+D19 -> 126553.65 | H19: =C19-C18 -> 1102.9427 | I19: =SUM(H7:H19) -> -43.19351 | J19: =D19-D18 -> 1062.4091 | K19: =SUM(J7:J19) -> 1183.8008 | L19: =H19+J19 -> 2165.3518 | M19: =SUM(L7:L19) -> 1140.6073
B20: 41383 | C20: 78917.109 | D20: 47705.429 | E20: =C20-D20 -> 31211.679 | F20: =C20/D20 -> 1.6542584 | G20: =C20+D20 -> 126622.54 | H20: =C20-C19 -> -3.955445 | I20: =SUM(H8:H20) -> -717.09477 | J20: =D20-D19 -> 72.843858 | K20: =SUM(J8:J20) -> 761.24202 | L20: =H20+J20 -> 68.888413 | M20: =SUM(L8:L20) -> 44.147242
B21: 41390 | C21: 79235.552 | D21: 47773.344 | E21: =C21-D21 -> 31462.208 | F21: =C21/D21 -> 1.6585725 | G21: =C21+D21 -> 127008.9 | H21: =C21-C20 -> 318.44294 | I21: =SUM(H9:H21) -> -617.72207 | J21: =D21-D20 -> 67.914079 | K21: =SUM(J9:J21) -> 618.90629 | L21: =H21+J21 -> 386.35702 | M21: =SUM(L9:L21) -> 1.184223
B22: 41397 | C22: 79642.018 | D22: 46979.764 | E22: =C22-D22 -> 32662.254 | F22: =C22/D22 -> 1.6952409 | G22: =C22+D22 -> 126621.78 | H22: =C22-C21 -> 406.46595 | I22: =SUM(H10:H22) -> -1013.6058 | J22: =D22-D21 -> -793.57971 | K22: =SUM(J10:J22) -> 300.9033 | L22: =H22+J22 -> -387.11376 | M22: =SUM(L10:L22) -> -712.70254
B23: 41404 | C23: 79126.906 | D23: 46145.09 | E23: =C23-D23 -> 32981.816 | F23: =C23/D23 -> 1.7147416 | G23: =C23+D23 -> 125272 | H23: =C23-C22 -> -515.11157 | I23: =SUM(H11:H23) -> -1225.007 | J23: =D23-D22 -> -834.67339 | K23: =SUM(J11:J23) -> 130.81487 | L23: =H23+J23 -> -1349.785 | M23: =SUM(L11:L23) -> -1094.1921
B24: 41411 | C24: 77559.294 | D24: 44642.075 | E24: =C24-D24 -> 32917.219 | F24: =C24/D24 -> 1.7373586 | G24: =C24+D24 -> 122201.37 | H24: =C24-C23 -> -1567.6125 | I24: =SUM(H12:H24) -> -2597.0714 | J24: =D24-D23 -> -1503.0159 | K24: =SUM(J12:J24) -> -315.13308 | L24: =H24+J24 -> -3070.6285 | M24: =SUM(L12:L24) -> -2912.2045
B25: 41418 | C25: 76570.593 | D25: 45762.26 | E25: =C25-D25 -> 30808.333 | F25: =C25/D25 -> 1.6732258 | G25: =C25+D25 -> 122332.85 | H25: =C25-C24 -> -988.70021 | I25: =SUM(H13:H25) -> -2737.1508 | J25: =D25-D24 -> 1120.1857 | K25: =SUM(J13:J25) -> 1756.7802 | L25: =H25+J25 -> 131.48544 | M25: =SUM(L13:L25) -> -980.37055
B26: 41425 | C26: 75979.828 | D26: 46705.707 | E26: =C26-D26 -> 29274.122 | F26: =C26/D26 -> 1.6267783 | G26: =C26+D26 -> 122685.53 | H26: =C26-C25 -> -590.76504 | I26: =SUM(H14:H26) -> -2618.1896 | J26: =D26-D25 -> 943.44639 | K26: =SUM(J14:J26) -> 2712.779 | L26: =H26+J26 -> 352.68136 | M26: =SUM(L14:L26) -> 94.58945
... B543: 45044 | C543: 111763.42 | D543: 75005.8 | E543: =C543-D543 -> 36757.62 | F543: =C543/D543 -> 1.4900637 | G543: =C543+D543 -> 186769.22 | H543: =C543-C542 -> -354.62 | I543: =SUM(H531:H543) -> -5521.39 | J543: =D543-D542 -> -1676.84 | K543: =SUM(J531:J543) -> -3758.73 | L543: =H543+J543 -> -2031.46 | M543: =SUM(L531:L543) -> -9280.12
B544: 45051 | C544: 112317.59 | D544: 76716.18 | E544: =C544-D544 -> 35601.41 | F544: =C544/D544 -> 1.4640665 | G544: =C544+D544 -> 189033.77 | H544: =C544-C543 -> 554.17 | I544: =SUM(H532:H544) -> -3665.94 | J544: =D544-D543 -> 1710.38 | K544: =SUM(J532:J544) -> -2778.17 | L544: =H544+J544 -> 2264.55 | M544: =SUM(L532:L544) -> -6444.11 | P544: DTH hesaplarında ilginç bir ayrışma var. Seçimden ve KKM'nin ölümünün açıklandığından bu yana Bireyler DTH'larını hiç artırmazken kurumlar son hızda DTH hesaplarını dolduruyorlar. Tıpkı KKM açıklandığında duruma uyanamayan bireylerin DTHlarını azaltmayıp tüzellerin son hızda azaltması gibi. Bireyler mevcut denklemi geç anlıyor gibi.
B545: 45058 | C545: 112016.9 | D545: 73625.45 | E545: =C545-D545 -> 38391.45 | F545: =C545/D545 -> 1.5214427 | G545: =C545+D545 -> 185642.35 | H545: =C545-C544 -> -300.69 | I545: =SUM(H533:H545) -> -2360.1 | J545: =D545-D544 -> -3090.73 | K545: =SUM(J533:J545) -> -5525.68 | L545: =H545+J545 -> -3391.42 | M545: =SUM(L533:L545) -> -7885.78
B546: 45065 | C546: 109658.29 | D546: 73346.76 | E546: =C546-D546 -> 36311.53 | F546: =C546/D546 -> 1.4950666 | G546: =C546+D546 -> 183005.05 | H546: =C546-C545 -> -2358.61 | I546: =SUM(H534:H546) -> -3173.19 | J546: =D546-D545 -> -278.69 | K546: =SUM(J534:J546) -> -4342.28 | L546: =H546+J546 -> -2637.3 | M546: =SUM(L534:L546) -> -7515.47
B547: 45072 | C547: 105747.64 | D547: 70256.17 | E547: =C547-D547 -> 35491.47 | F547: =C547/D547 -> 1.5051723 | G547: =C547+D547 -> 176003.81 | H547: =C547-C546 -> -3910.65 | I547: =SUM(H535:H547) -> -4948.92 | J547: =D547-D546 -> -3090.59 | K547: =SUM(J535:J547) -> -4885.54 | L547: =H547+J547 -> -7001.24 | M547: =SUM(L535:L547) -> -9834.46
B548: 45079 | C548: 105451.38 | D548: 70011.2 | E548: =C548-D548 -> 35440.18 | F548: =C548/D548 -> 1.5062073 | G548: =C548+D548 -> 175462.58 | H548: =C548-C547 -> -296.26 | I548: =SUM(H536:H548) -> -5744.69 | J548: =D548-D547 -> -244.97 | K548: =SUM(J536:J548) -> -5220.59 | L548: =H548+J548 -> -541.23 | M548: =SUM(L536:L548) -> -10965.28
B549: 45086 | C549: 104970.77 | D549: 68703.48 | E549: =C549-D549 -> 36267.29 | F549: =C549/D549 -> 1.5278814 | G549: =C549+D549 -> 173674.25 | H549: =C549-C548 -> -480.61 | I549: =SUM(H537:H549) -> -6116.67 | J549: =D549-D548 -> -1307.72 | K549: =SUM(J537:J549) -> -7767.34 | L549: =H549+J549 -> -1788.33 | M549: =SUM(L537:L549) -> -13884.01
B550: 45093 | C550: 104939 | D550: 71397 | E550: =C550-D550 -> 33542 | F550: =C550/D550 -> 1.4697956 | G550: =C550+D550 -> 176336 | H550: =C550-C549 -> -31.77 | I550: =SUM(H538:H550) -> -6255.94 | J550: =D550-D549 -> 2693.52 | K550: =SUM(J538:J550) -> -3850.17 | L550: =H550+J550 -> 2661.75 | M550: =SUM(L538:L550) -> -10106.11
B551: 45100 | C551: 101947 | D551: 66004 | E551: =C551-D551 -> 35943 | F551: =C551/D551 -> 1.5445579 | G551: =C551+D551 -> 167951 | H551: =C551-C550 -> -2992 | I551: =SUM(H539:H551) -> -9563.54 | J551: =D551-D550 -> -5393 | K551: =SUM(J539:J551) -> -8975.67 | L551: =H551+J551 -> -8385 | M551: =SUM(L539:L551) -> -18539.21
B552: 45107 | C552: 102600 | D552: 65707 | E552: =C552-D552 -> 36893 | F552: =C552/D552 -> 1.5614775 | G552: =C552+D552 -> 168307 | H552: =C552-C551 -> 653 | I552: =SUM(H540:H552) -> -8143.91 | J552: =D552-D551 -> -297 | K552: =SUM(J540:J552) -> -7232.67 | L552: =H552+J552 -> 356 | M552: =SUM(L540:L552) -> -15376.58
B553: 45114 | C553: 102632 | D553: 65997 | E553: =C553-D553 -> 36635 | F553: =C553/D553 -> 1.555101 | G553: =C553+D553 -> 168629 | H553: =C553-C552 -> 32 | I553: =SUM(H541:H553) -> -9358.25 | J553: =D553-D552 -> 290 | K553: =SUM(J541:J553) -> -9659.99 | L553: =H553+J553 -> 322 | M553: =SUM(L541:L553) -> -19018.24
B554: 45121 | C554: 103660 | D554: 67467 | E554: =C554-D554 -> 36193 | F554: =C554/D554 -> 1.5364549 | G554: =C554+D554 -> 171127 | H554: =C554-C553 -> 1028 | I554: =SUM(H542:H554) -> -8421.14 | J554: =D554-D553 -> 1470 | K554: =SUM(J542:J554) -> -8357.25 | L554: =H554+J554 -> 2498 | M554: =SUM(L542:L554) -> -16778.39
B555: 45128 | C555: 103687 | D555: 67129 | E555: =C555-D555 -> 36558 | F555: =C555/D555 -> 1.5445932 | G555: =C555+D555 -> 170816 | H555: =C555-C554 -> 27 | I555: =SUM(H543:H555) -> -8431.04 | J555: =D555-D554 -> -338 | K555: =SUM(J543:J555) -> -9553.64 | L555: =H555+J555 -> -311 | M555: =SUM(L543:L555) -> -17984.68
B556: 45135 | C556: 104543 | D556: 66999 | E556: =C556-D556 -> 37544 | F556: =C556/D556 -> 1.5603666 | G556: =C556+D556 -> 171542 | H556: =C556-C555 -> 856 | I556: =SUM(H544:H556) -> -7220.42 | J556: =D556-D555 -> -130 | K556: =SUM(J544:J556) -> -8006.8 | L556: =H556+J556 -> 726 | M556: =SUM(L544:L556) -> -15227.22
... B682: 46017 | C682: 142716 | D682: 78746 | E682: =C682-D682 -> 63970 | F682: =C682/D682 -> 1.8123587 | G682: =C682+D682 -> 221462 | H682: =C682-C681 -> 4566 | I682: =SUM(H670:H682) -> 16622 | J682: =D682-D681 -> 1627 | K682: =SUM(J670:J682) -> 889 | L682: =H682+J682 -> 6193 | M682: =SUM(L670:L682) -> 17511
B683: 46024
B684: 46031
B685: 46038
B686: 46045
B687: 46052
B688: 46059

Sheet Menkul Kıymet - Güncel
A1: Her Perşembe | C1: Hisse Senedi - Flow | E1: DIBS - Flow | F1: Hisse fark | G1: DIBS fark | H1: 4 week cor | I1: 13 week cor | J1: Total Flow | K1: Toplam Kümülatif-2023 | O1: 13w Sum Hisse Flow | P1: 13w Sum tAHVİL Flow | Q1: 13w hisse flow - dibs flow
A2: TCMB MENK. İST | B2: 11-09-2020 | C2: -30.24 | E2: -10.58 | J2: =C2+E2 -> -40.82
B3: 18-09-2020 | C3: 2.57 | E3: -90.42 | F3: =C3-C2 -> 32.81 | G3: =E3-E2 -> -79.84 | J3: =C3+E3 -> -87.85
B4: 25-09-2020 | C4: -101.89 | E4: 1.7 | F4: =C4-C3 -> -104.46 | G4: =E4-E3 -> 92.12 | J4: =C4+E4 -> -100.19
B5: 02-10-2020 | C5: 131.22 | E5: 407.2 | F5: =C5-C4 -> 233.11 | G5: =E5-E4 -> 405.5 | H5: =CORREL(C2:C5,E2:E5) -> 0.81257493 | J5: =C5+E5 -> 538.42
B6: 09-10-2020 | C6: -91.33 | E6: -174.52 | F6: =C6-C5 -> -222.55 | G6: =E6-E5 -> -581.72 | H6: =CORREL(C3:C6,E3:E6) -> 0.85063951 | J6: =C6+E6 -> -265.85
B7: 16-10-2020 | C7: -28.37 | E7: -38.03 | F7: =C7-C6 -> 62.96 | G7: =E7-E6 -> 136.49 | H7: =CORREL(C4:C7,E4:E7) -> 0.92477044 | J7: =C7+E7 -> -66.4
B8: 23-10-2020 | C8: -10.82 | E8: 20.9 | F8: =C8-C7 -> 17.55 | G8: =E8-E7 -> 58.93 | H8: =CORREL(C5:C8,E5:E8) -> 0.99862015 | J8: =C8+E8 -> 10.08
B9: 30-10-2020 | C9: -116.63 | E9: -32.74 | F9: =C9-C8 -> -105.81 | G9: =E9-E8 -> -53.64 | H9: =CORREL(C6:C9,E6:E9) -> 0.53638465 | J9: =C9+E9 -> -149.37
B10: 06-11-2020 | C10: -21.99 | E10: -17.34 | F10: =C10-C9 -> 94.64 | G10: =E10-E9 -> 15.4 | H10: =CORREL(C7:C10,E7:E10) -> 0.53128496 | J10: =C10+E10 -> -39.33
B11: 13-11-2020 | C11: 614.4 | E11: 211.09 | F11: =C11-C10 -> 636.39 | G11: =E11-E10 -> 228.43 | H11: =CORREL(C8:C11,E8:E11) -> 0.9921364 | J11: =C11+E11 -> 825.49
B12: 20-11-2020 | C12: 389.64 | E12: 201.76 | F12: =C12-C11 -> -224.76 | G12: =E12-E11 -> -9.33 | H12: =CORREL(C9:C12,E9:E12) -> 0.96874449 | J12: =C12+E12 -> 591.4
B13: 27-11-2020 | C13: 231.71 | E13: 194.51 | F13: =C13-C12 -> -157.93 | G13: =E13-E12 -> -7.25 | H13: =CORREL(C10:C13,E10:E13) -> 0.84466666 | J13: =C13+E13 -> 426.22
B14: 04-12-2020 | C14: -23.27 | E14: 133.48 | F14: =C14-C13 -> -254.98 | G14: =E14-E13 -> -61.03 | H14: =CORREL(C11:C14,E11:E14) -> 0.90858674 | I14: =CORREL(C2:C14,E2:E14) -> 0.64646017 | J14: =C14+E14 -> 110.21 | O14: =SUM(C2:C14) -> 945 | P14: =SUM(E2:E14) -> 807.01 | Q14: =O14-P14 -> 137.99
B15: 11-12-2020 | C15: 40.97 | E15: 103.79 | F15: =C15-C14 -> 64.24 | G15: =E15-E14 -> -29.69 | H15: =CORREL(C12:C15,E12:E15) -> 0.88190438 | I15: =CORREL(C3:C15,E3:E15) -> 0.63394776 | J15: =C15+E15 -> 144.76 | O15: =SUM(C3:C15) -> 1016.21 | P15: =SUM(E3:E15) -> 921.38 | Q15: =O15-P15 -> 94.83
B16: 18-12-2020 | C16: 244.04 | E16: 44.88 | F16: =C16-C15 -> 203.07 | G16: =E16-E15 -> -58.91 | H16: =CORREL(C13:C16,E13:E16) -> -0.064804327 | I16: =CORREL(C4:C16,E4:E16) -> 0.60625454 | J16: =C16+E16 -> 288.92 | O16: =SUM(C4:C16) -> 1257.68 | P16: =SUM(E4:E16) -> 1056.68 | Q16: =O16-P16 -> 201
B17: 25-12-2020 | C17: -18.79 | E17: 159.25 | F17: =C17-C16 -> -262.83 | G17: =E17-E16 -> 114.37 | H17: =CORREL(C14:C17,E14:E17) -> -0.95488618 | I17: =CORREL(C5:C17,E5:E17) -> 0.55558158 | J17: =C17+E17 -> 140.46 | O17: =SUM(C5:C17) -> 1340.78 | P17: =SUM(E5:E17) -> 1214.23 | Q17: =O17-P17 -> 126.55
B18: 01-01-2021 | C18: 90.68 | E18: -85.97 | F18: =C18-C17 -> 109.47 | G18: =E18-E17 -> -245.22 | H18: =CORREL(C15:C18,E15:E18) -> -0.43324732 | I18: =CORREL(C6:C18,E6:E18) -> 0.64862394 | J18: =C18+E18 -> 4.71 | O18: =SUM(C6:C18) -> 1300.24 | P18: =SUM(E6:E18) -> 721.06 | Q18: =O18-P18 -> 579.18
B19: 08-01-2021 | C19: 287.71 | E19: 634.85 | F19: =C19-C18 -> 197.03 | G19: =E19-E18 -> 720.82 | H19: =CORREL(C16:C19,E16:E19) -> 0.51988396 | I19: =CORREL(C7:C19,E7:E19) -> 0.52122473 | J19: =C19+E19 -> 922.56 | O19: =SUM(C7:C19) -> 1679.28 | P19: =SUM(E7:E19) -> 1530.43 | Q19: =O19-P19 -> 148.85
B20: 15-01-2021 | C20: 31.41 | E20: -2.57 | F20: =C20-C19 -> -256.3 | G20: =E20-E19 -> -637.42 | H20: =CORREL(C17:C20,E17:E20) -> 0.79207421 | I20: =CORREL(C8:C20,E8:E20) -> 0.50711147 | J20: =C20+E20 -> 28.84 | O20: =SUM(C8:C20) -> 1739.06 | P20: =SUM(E8:E20) -> 1565.89 | Q20: =O20-P20 -> 173.17
B21: 22-01-2021 | C21: -117.71 | E21: 28.6 | F21: =C21-C20 -> -149.12 | G21: =E21-E20 -> 31.17 | H21: =CORREL(C18:C21,E18:E21) -> 0.7766421 | I21: =CORREL(C9:C21,E9:E21) -> 0.50737805 | J21: =C21+E21 -> -89.11 | O21: =SUM(C9:C21) -> 1632.17 | P21: =SUM(E9:E21) -> 1573.59 | Q21: =O21-P21 -> 58.58
B22: 29-01-2021 | C22: -493.75 | E22: 413.98 | F22: =C22-C21 -> -376.04 | G22: =E22-E21 -> 385.38 | H22: =CORREL(C19:C22,E19:E22) -> 0.1762428 | I22: =CORREL(C10:C22,E10:E22) -> 0.05565317 | J22: =C22+E22 -> -79.77 | O22: =SUM(C10:C22) -> 1255.05 | P22: =SUM(E10:E22) -> 2020.31 | Q22: =O22-P22 -> -765.26
B23: 05-02-2021 | C23: -183.22 | E23: 169.96 | F23: =C23-C22 -> 310.53 | G23: =E23-E22 -> -244.02 | H23: =CORREL(C20:C23,E20:E23) -> -0.9741298 | I23: =CORREL(C11:C23,E11:E23) -> 0.020200614 | J23: =C23+E23 -> -13.26 | O23: =SUM(C11:C23) -> 1093.82 | P23: =SUM(E11:E23) -> 2207.61 | Q23: =O23-P23 -> -1113.79
B24: 12-02-2021 | C24: -62.34 | E24: 83.52 | F24: =C24-C23 -> 120.88 | G24: =E24-E23 -> -86.44 | H24: =CORREL(C21:C24,E21:E24) -> -0.96481707 | I24: =CORREL(C12:C24,E12:E24) -> -0.0063254168 | J24: =C24+E24 -> 21.18 | O24: =SUM(C12:C24) -> 417.08 | P24: =SUM(E12:E24) -> 2080.04 | Q24: =O24-P24 -> -1662.96
B25: 19-02-2021 | C25: -122.76 | E25: 169.58 | F25: =C25-C24 -> -60.42 | G25: =E25-E24 -> 86.06 | H25: =CORREL(C22:C25,E22:E25) -> -0.98986252 | I25: =CORREL(C13:C25,E13:E25) -> -0.045062905 | J25: =C25+E25 -> 46.82 | O25: =SUM(C13:C25) -> -95.32 | P25: =SUM(E13:E25) -> 2047.86 | Q25: =O25-P25 -> -2143.18
... B92: 03-06-2022 | C92: 130.13 | E92: -1.63 | F92: =C92-C91 -> 170.99 | G92: =E92-E91 -> 53.36 | H92: =CORREL(C89:C92,E89:E92) -> 0.79809295 | I92: =CORREL(C80:C92,E80:E92) -> 0.69925153 | J92: =C92+E92 -> 128.5 | O92: =SUM(C80:C92) -> -1873.34 | P92: =SUM(E80:E92) -> -683.82 | Q92: =O92-P92 -> -1189.52
B93: 10-06-2022 | C93: -316.07 | E93: -85.02 | F93: =C93-C92 -> -446.2 | G93: =E93-E92 -> -83.39 | H93: =CORREL(C90:C93,E90:E93) -> 0.75486409 | I93: =CORREL(C81:C93,E81:E93) -> 0.69509647 | J93: =C93+E93 -> -401.09 | N93: Son 1 Senede Total Flow | O93: =SUM(C81:C93) -> -1899.98 | P93: =SUM(E81:E93) -> -647.89 | Q93: =O93-P93 -> -1252.09
B94: 17-06-2022 | C94: -192.82 | E94: -144.66 | F94: =C94-C93 -> 123.25 | G94: =E94-E93 -> -59.64 | H94: =CORREL(C91:C94,E91:E94) -> 0.77473065 | I94: =CORREL(C82:C94,E82:E94) -> 0.69314323 | J94: =C94+E94 -> -337.48 | N94: =J93+J94 -> -738.57 | O94: =SUM(C82:C94) -> -1895.7 | P94: =SUM(E82:E94) -> -776.66 | Q94: =O94-P94 -> -1119.04
B95: 24-06-2022 | C95: -98.41 | E95: -57.7 | F95: =C95-C94 -> 94.41 | G95: =E95-E94 -> 86.96 | H95: =CORREL(C92:C95,E92:E95) -> 0.76536367 | I95: =CORREL(C83:C95,E83:E95) -> 0.73474631 | J95: =C95+E95 -> -156.11 | N95: =N94+J95 -> -894.68 | O95: =SUM(C83:C95) -> -2012.9 | P95: =SUM(E83:E95) -> -729.55 | Q95: =O95-P95 -> -1283.35
B96: 01-07-2022 | C96: -59.74 | E96: 22.1 | F96: =C96-C95 -> 38.67 | G96: =E96-E95 -> 79.8 | H96: =CORREL(C93:C96,E93:E96) -> 0.6277995 | I96: =CORREL(C84:C96,E84:E96) -> 0.75419522 | J96: =C96+E96 -> -37.64 | N96: =N95+J96 -> -932.32 | O96: =SUM(C84:C96) -> -2082.79 | P96: =SUM(E84:E96) -> -811.2 | Q96: =O96-P96 -> -1271.59
B97: 08-07-2022 | C97: -62.2 | E97: -54.46 | F97: =C97-C96 -> -2.46 | G97: =E97-E96 -> -76.56 | H97: =CORREL(C94:C97,E94:E97) -> 0.89517436 | I97: =CORREL(C85:C97,E85:E97) -> 0.79737632 | J97: =C97+E97 -> -116.66 | N97: =N96+J97 -> -1048.98 | O97: =SUM(C85:C97) -> -2390.15 | P97: =SUM(E85:E97) -> -826.92 | Q97: =O97-P97 -> -1563.23
B98: 15-07-2022 | C98: -37.42 | E98: -41.94 | F98: =C98-C97 -> 24.78 | G98: =E98-E97 -> 12.52 | H98: =CORREL(C95:C98,E95:E98) -> 0.2857923 | I98: =CORREL(C86:C98,E86:E98) -> 0.7841903 | J98: =C98+E98 -> -79.36 | N98: =N97+J98 -> -1128.34 | O98: =SUM(C86:C98) -> -2454.44 | P98: =SUM(E86:E98) -> -905.62 | Q98: =O98-P98 -> -1548.82
B99: 22-07-2022 | C99: -76.55 | E99: -4.17 | F99: =C99-C98 -> -39.13 | G99: =E99-E98 -> 37.77 | H99: =CORREL(C96:C99,E96:E99) -> -0.39501836 | I99: =CORREL(C87:C99,E87:E99) -> 0.7811258 | J99: =C99+E99 -> -80.72 | N99: =N98+J99 -> -1209.06 | O99: =SUM(C87:C99) -> -2478.24 | P99: =SUM(E87:E99) -> -887.62 | Q99: =O99-P99 -> -1590.62
B100: 29-07-2022 | C100: -26.9 | E100: -21.11 | F100: =C100-C99 -> 49.65 | G100: =E100-E99 -> -16.94 | H100: =CORREL(C97:C100,E97:E100) -> -0.22020487 | I100: =CORREL(C88:C100,E88:E100) -> 0.78645969 | J100: =C100+E100 -> -48.01 | N100: =N99+J100 -> -1257.07 | O100: =SUM(C88:C100) -> -2395.12 | P100: =SUM(E88:E100) -> -884.8 | Q100: =O100-P100 -> -1510.32
B101: 05-08-2022 | C101: 88.02 | E101: 6.81 | F101: =C101-C100 -> 114.92 | G101: =E101-E100 -> 27.92 | H101: =CORREL(C98:C101,E98:E101) -> 0.50005019 | I101: =CORREL(C89:C101,E89:E101) -> 0.80105158 | J101: =C101+E101 -> 94.83 | N101: =N100+J101 -> -1162.24 | O101: =SUM(C89:C101) -> -2062.94 | P101: =SUM(E89:E101) -> -802.2 | Q101: =O101-P101 -> -1260.74
B102: 12-08-2022 | C102: 270.04 | E102: 2.52 | F102: =C102-C101 -> 182.02 | G102: =E102-E101 -> -4.29 | H102: =CORREL(C99:C102,E99:E102) -> 0.56146678 | I102: =CORREL(C90:C102,E90:E102) -> 0.58915624 | J102: =C102+E102 -> 272.56 | N102: =N101+J102 -> -889.68 | O102: =SUM(C90:C102) -> -1026.03 | P102: =SUM(E90:E102) -> -501.57 | Q102: =O102-P102 -> -524.46
B103: 19-08-2022 | C103: 366.2 | E103: -9.54 | F103: =C103-C102 -> 96.16 | G103: =E103-E102 -> -12.06 | H103: =CORREL(C100:C103,E100:E103) -> 0.30985429 | I103: =CORREL(C91:C103,E91:E103) -> 0.6300112 | J103: =C103+E103 -> 356.66 | N103: =N102+J103 -> -533.02 | O103: =SUM(C91:C103) -> -56.58 | P103: =SUM(E91:E103) -> -443.79 | Q103: =O103-P103 -> 387.21
B104: 26-08-2022 | C104: -32 | E104: -5.86 | F104: =C104-C103 -> -398.2 | G104: =E104-E103 -> 3.68 | H104: =CORREL(C101:C104,E101:E104) -> -0.24232091 | I104: =CORREL(C92:C104,E92:E104) -> 0.61248146 | J104: =C104+E104 -> -37.86 | N104: =N103+J104 -> -570.88 | O104: =SUM(C92:C104) -> -47.72 | P104: =SUM(E92:E104) -> -394.66 | Q104: =O104-P104 -> 346.94
B105: 02-09-2022 | C105: 97.95 | E105: -63.47 | F105: =C105-C104 -> 129.95 | G105: =E105-E104 -> -57.61 | H105: =CORREL(C102:C105,E102:E105) -> 0.28555532 | I105: =CORREL(C93:C105,E93:E105) -> 0.5444537 | J105: =C105+E105 -> 34.48 | N105: =N104+J105 -> -536.4 | O105: =SUM(C93:C105) -> -79.9 | P105: =SUM(E93:E105) -> -456.5 | Q105: =O105-P105 -> 376.6
B106: 09-09-2022 | C106: -13.48 | E106: -24.78 | F106: =C106-C105 -> -111.43 | G106: =E106-E105 -> 38.69 | H106: =CORREL(C103:C106,E103:E106) -> 0.11442132 | I106: =CORREL(C94:C106,E94:E106) -> 0.46072595 | J106: =C106+E106 -> -38.26 | N106: =N105+J106 -> -574.66 | O106: =SUM(C94:C106) -> 222.69 | P106: =SUM(E94:E106) -> -396.26 | Q106: =O106-P106 -> 618.95
... B121: 23-12-2022 | C121: -321.61 | E121: -1.41 | F121: =C121-C120 -> -127.72 | G121: =E121-E120 -> 1.7 | H121: =CORREL(C118:C121,E118:E121) -> -0.96607585 | I121: =CORREL(C109:C121,E109:E121) -> -0.24219614 | J121: =C121+E121 -> -323.02 | N121: =N120+J121 -> -1984.12 | O121: =SUM(C109:C121) -> -942.27 | P121: =SUM(E109:E121) -> -198.78 | Q121: =O121-P121 -> -743.49
B122: 30-12-2022 | C122: -53.45 | E122: 53.25 | F122: =C122-C121 -> 268.16 | G122: =E122-E121 -> 54.66 | H122: =CORREL(C119:C122,E119:E122) -> 0.88752471 | I122: =CORREL(C110:C122,E110:E122) -> -0.13687244 | J122: =C122+E122 -> -0.2 | K122: 2023 Başl. Küm. Flow | L122: Hisse Küm. 2023 | M122: DIBS Küm. 2023 | N122: =N121+J122 -> -1984.32 | O122: =SUM(C110:C122) -> -695.42 | P122: =SUM(E110:E122) -> -150.47 | Q122: =O122-P122 -> -544.95
B123: 06-01-2023 | C123: -351.87 | E123: -55.14 | F123: =C123-C122 -> -298.42 | G123: =E123-E122 -> -108.39 | H123: =CORREL(C120:C123,E120:E123) -> 0.8917138 | I123: =CORREL(C111:C123,E111:E123) -> -0.034115294 | J123: =C123+E123 -> -407.01 | K123: =J122+J123 -> -407.21 | L123: =C122+C123 -> -405.32 | M123: =E122+E123 -> -1.89 | N123: =N122+J123 -> -2391.33 | O123: =SUM(C111:C123) -> -910.94 | P123: =SUM(E111:E123) -> -118.8 | Q123: =O123-P123 -> -792.14
B124: 13-01-2023 | C124: 67.6 | E124: 80.07 | F124: =C124-C123 -> 419.47 | G124: =E124-E123 -> 135.21 | H124: =CORREL(C121:C124,E121:E124) -> 0.95019245 | I124: =CORREL(C112:C124,E112:E124) -> 0.089209892 | J124: =C124+E124 -> 147.67 | K124: =K123+J124 -> -259.54 | L124: =L123+C124 -> -337.72 | M124: =M123+E124 -> 78.18 | N124: =N123+J124 -> -2243.66 | O124: =SUM(C112:C124) -> -674.11 | P124: =SUM(E112:E124) -> -21.8 | Q124: =O124-P124 -> -652.31
B125: 20-01-2023 | C125: -334.89 | E125: 2.11 | F125: =C125-C124 -> -402.49 | G125: =E125-E124 -> -77.96 | H125: =CORREL(C122:C125,E122:E125) -> 0.93191521 | I125: =CORREL(C113:C125,E113:E125) -> 0.073542206 | J125: =C125+E125 -> -332.78 | K125: =K124+J125 -> -592.32 | L125: =L124+C125 -> -672.61 | M125: =M124+E125 -> 80.29 | N125: =N124+J125 -> -2576.44 | O125: =SUM(C113:C125) -> -946.4 | P125: =SUM(E113:E125) -> -8.1 | Q125: =O125-P125 -> -938.3
B126: 27-01-2023 | C126: 22.9 | E126: -0.46 | F126: =C126-C125 -> 357.79 | G126: =E126-E125 -> -2.57 | H126: =CORREL(C123:C126,E123:E126) -> 0.74669851 | I126: =CORREL(C114:C126,E114:E126) -> 0.064668734 | J126: =C126+E126 -> 22.44 | K126: =K125+J126 -> -569.88 | L126: =L125+C126 -> -649.71 | M126: =M125+E126 -> 79.83 | N126: =N125+J126 -> -2554 | O126: =SUM(C114:C126) -> -911.85 | P126: =SUM(E114:E126) -> -22.36 | Q126: =O126-P126 -> -889.49
B127: 03-02-2023 | C127: 92.13 | E127: 40.33 | F127: =C127-C126 -> 69.23 | G127: =E127-E126 -> 40.79 | H127: =CORREL(C124:C127,E124:E127) -> 0.57373116 | I127: =CORREL(C115:C127,E115:E127) -> 0.13610565 | J127: =C127+E127 -> 132.46 | K127: =K126+J127 -> -437.42 | L127: =L126+C127 -> -557.58 | M127: =M126+E127 -> 120.16 | N127: =N126+J127 -> -2421.54 | O127: =SUM(C115:C127) -> -857.83 | P127: =SUM(E115:E127) -> 26.15 | Q127: =O127-P127 -> -883.98
B128: 10-02-2023 | C128: 130.53 | E128: 3.62 | F128: =C128-C127 -> 38.4 | G128: =E128-E127 -> -36.71 | H128: =CORREL(C125:C128,E125:E128) -> 0.36275613 | I128: =CORREL(C116:C128,E116:E128) -> 0.20188875 | J128: =C128+E128 -> 134.15 | K128: =K127+J128 -> -303.27 | L128: =L127+C128 -> -427.05 | M128: =M127+E128 -> 123.78 | N128: =N127+J128 -> -2287.39 | O128: =SUM(C116:C128) -> -843.61 | P128: =SUM(E116:E128) -> 58.41 | Q128: =O128-P128 -> -902.02
B129: 17-02-2023 | C129: 9.22 | E129: -38.66 | F129: =C129-C128 -> -121.31 | G129: =E129-E128 -> -42.28 | H129: =CORREL(C126:C129,E126:E129) -> 0.63108694 | I129: =CORREL(C117:C129,E117:E129) -> 0.19371299 | J129: =C129+E129 -> -29.44 | K129: =K128+J129 -> -332.71 | L129: =L128+C129 -> -417.83 | M129: =M128+E129 -> 85.12 | N129: =N128+J129 -> -2316.83 | O129: =SUM(C117:C129) -> -890.87 | P129: =SUM(E117:E129) -> 40.29 | Q129: =O129-P129 -> -931.16
B130: 24-02-2023 | C130: -260.77 | E130: 13.37 | F130: =C130-C129 -> -269.99 | G130: =E130-E129 -> 52.03 | H130: =CORREL(C127:C130,E127:E130) -> 0.027649743 | I130: =CORREL(C118:C130,E118:E130) -> 0.17219305 | J130: =C130+E130 -> -247.4 | K130: =K129+J130 -> -580.11 | L130: =L129+C130 -> -678.6 | M130: =M129+E130 -> 98.49 | N130: =N129+J130 -> -2564.23 | O130: =SUM(C118:C130) -> -1175.87 | P130: =SUM(E118:E130) -> 50.78 | Q130: =O130-P130 -> -1226.65
B131: 03-03-2023 | C131: 136.89 | E131: 69.1 | F131: =C131-C130 -> 397.66 | G131: =E131-E130 -> 55.73 | H131: =CORREL(C128:C131,E128:E131) -> 0.23845467 | I131: =CORREL(C119:C131,E119:E131) -> 0.55415083 | J131: =C131+E131 -> 205.99 | K131: =K130+J131 -> -374.12 | L131: =L130+C131 -> -541.71 | M131: =M130+E131 -> 167.59 | N131: =N130+J131 -> -2358.24 | O131: =SUM(C119:C131) -> -1378.73 | P131: =SUM(E119:E131) -> 156.15 | Q131: =O131-P131 -> -1534.88
B132: 10-03-2023 | C132: -53.52 | E132: -56.21 | F132: =C132-C131 -> -190.41 | G132: =E132-E131 -> -125.31 | H132: =CORREL(C129:C132,E129:E132) -> 0.2881887 | I132: =CORREL(C120:C132,E120:E132) -> 0.46164438 | J132: =C132+E132 -> -109.73 | K132: =K131+J132 -> -483.85 | L132: =L131+C132 -> -595.23 | M132: =M131+E132 -> 111.38 | N132: =N131+J132 -> -2467.97 | O132: =SUM(C120:C132) -> -1110.73 | P132: =SUM(E120:E132) -> 106.86 | Q132: =O132-P132 -> -1217.59
B133: 17-03-2023 | C133: -210.82 | E133: -25.99 | F133: =C133-C132 -> -157.3 | G133: =E133-E132 -> 30.22 | H133: =CORREL(C130:C133,E130:E133) -> 0.49776899 | I133: =CORREL(C121:C133,E121:E133) -> 0.48038629 | J133: =C133+E133 -> -236.81 | K133: =K132+J133 -> -720.66 | L133: =L132+C133 -> -806.05 | M133: =M132+E133 -> 85.39 | N133: =N132+J133 -> -2704.78 | O133: =SUM(C121:C133) -> -1127.66 | P133: =SUM(E121:E133) -> 83.98 | Q133: =O133-P133 -> -1211.64
B134: 24-03-2023 | C134: -113.03 | E134: 25.09 | F134: =C134-C133 -> 97.79 | G134: =E134-E133 -> 51.08 | H134: =CORREL(C131:C134,E131:E134) -> 0.65045903 | I134: =CORREL(C122:C134,E122:E134) -> 0.48574243 | J134: =C134+E134 -> -87.94 | K134: =K133+J134 -> -808.6 | L134: =L133+C134 -> -919.08 | M134: =M133+E134 -> 110.48 | N134: =N133+J134 -> -2792.72 | O134: =SUM(C122:C134) -> -919.08 | P134: =SUM(E122:E134) -> 110.48 | Q134: =O134-P134 -> -1029.56
B135: 31-03-2023 | C135: -60.92 | E135: 15.14 | F135: =C135-C134 -> 52.11 | G135: =E135-E134 -> -9.95 | H135: =CORREL(C132:C135,E132:E135) -> 0.015940601 | I135: =CORREL(C123:C135,E123:E135) -> 0.50007488 | J135: =C135+E135 -> -45.78 | K135: =K134+J135 -> -854.38 | L135: =L134+C135 -> -980 | M135: =M134+E135 -> 125.62 | N135: =N134+J135 -> -2838.5 | O135: =SUM(C123:C135) -> -926.55 | P135: =SUM(E123:E135) -> 72.37 | Q135: =O135-P135 -> -998.92
... B144: 02-06-2023 | C144: -51.98 | E144: 14.98 | F144: =C144-C143 -> 326.5608 | G144: =E144-E143 -> 13.35 | H144: =CORREL(C141:C144,E141:E144) -> 0.0087546849 | I144: =CORREL(C132:C144,E132:E144) -> -0.1216754 | J144: =C144+E144 -> -37 | K144: =K143+J144 -> -1628.2808 | L144: =L143+C144 -> -1654.1308 | M144: =M143+E144 -> 25.85 | N144: =N143+J144 -> -3612.4008 | O144: =SUM(C132:C144) -> -1112.4208 | P144: =SUM(E132:E144) -> -141.74 | Q144: =O144-P144 -> -970.6808
B145: 45086 | C145: 261.8 | E145: 25.2 | F145: =C145-C144 -> 313.78 | G145: =E145-E144 -> 10.22 | H145: =CORREL(C142:C145,E142:E145) -> 0.68843126 | I145: =CORREL(C133:C145,E133:E145) -> 0.11623295 | J145: =C145+E145 -> 287 | K145: =K144+J145 -> -1341.2808 | L145: =L144+C145 -> -1392.3308 | M145: =M144+E145 -> 51.05 | N145: =N144+J145 -> -3325.4008 | O145: =SUM(C133:C145) -> -797.1008 | P145: =SUM(E133:E145) -> -60.33 | Q145: =O145-P145 -> -736.7708
B146: 45093 | C146: 313.4 | E146: -16.2 | F146: =C146-C145 -> 51.6 | G146: =E146-E145 -> -41.4 | H146: =CORREL(C143:C146,E143:E146) -> -0.046646165 | I146: =CORREL(C134:C146,E134:E146) -> -0.02594389 | J146: =C146+E146 -> 297.2 | K146: =K145+J146 -> -1044.0808 | L146: =L145+C146 -> -1078.9308 | M146: =M145+E146 -> 34.85 | N146: =N145+J146 -> -3028.2008 | O146: =SUM(C134:C146) -> -272.8808 | P146: =SUM(E134:E146) -> -50.54 | Q146: =O146-P146 -> -222.3408
B147: 45100 | C147: 398.8 | E147: 14.2 | F147: =C147-C146 -> 85.4 | G147: =E147-E146 -> 30.4 | H147: =CORREL(C144:C147,E144:E147) -> -0.22719486 | I147: =CORREL(C135:C147,E135:E147) -> 0.13182556 | J147: =C147+E147 -> 413 | K147: =K146+J147 -> -631.0808 | L147: =L146+C147 -> -680.1308 | M147: =M146+E147 -> 49.05 | N147: =N146+J147 -> -2615.2008 | O147: =SUM(C135:C147) -> 238.9492 | P147: =SUM(E135:E147) -> -61.43 | Q147: =O147-P147 -> 300.3792
B148: 45107 | C148: 123.6 | E148: 27 | F148: =C148-C147 -> -275.2 | G148: =E148-E147 -> 12.8 | H148: =CORREL(C145:C148,E145:E148) -> -0.47072206 | I148: =CORREL(C136:C148,E136:E148) -> 0.19341201 | J148: =C148+E148 -> 150.6 | K148: =K147+J148 -> -480.4808 | L148: =L147+C148 -> -556.5308 | M148: =M147+E148 -> 76.05 | N148: =N147+J148 -> -2464.6008 | O148: =SUM(C136:C148) -> 423.4692 | P148: =SUM(E136:E148) -> -49.57 | Q148: =O148-P148 -> 473.0392
B149: 45114 | C149: 231.4 | E149: 57 | F149: =C149-C148 -> 107.8 | G149: =E149-E148 -> 30 | H149: =CORREL(C146:C149,E146:E149) -> -0.44589652 | I149: =CORREL(C137:C149,E137:E149) -> 0.3146403 | J149: =C149+E149 -> 288.4 | K149: =K148+J149 -> -192.0808 | L149: =L148+C149 -> -325.1308 | M149: =M148+E149 -> 133.05 | N149: =N148+J149 -> -2176.2008 | O149: =SUM(C137:C149) -> 729.5892 | P149: =SUM(E137:E149) -> -5.85 | Q149: =O149-P149 -> 735.4392
B150: 45121 | C150: 152.5 | E150: -26.5 | F150: =C150-C149 -> -78.9 | G150: =E150-E149 -> -83.5 | H150: =CORREL(C147:C150,E147:E150) -> 0.14833228 | I150: =CORREL(C138:C150,E138:E150) -> 0.28708178 | J150: =C150+E150 -> 126 | K150: =K149+J150 -> -66.0808 | L150: =L149+C150 -> -172.6308 | M150: =M149+E150 -> 106.55 | N150: =N149+J150 -> -2050.2008 | O150: =SUM(C138:C150) -> 703.0792 | P150: =SUM(E138:E150) -> -26.32 | Q150: =O150-P150 -> 729.3992
B151: 45128 | C151: 128.4 | E151: -6.8 | F151: =C151-C150 -> -24.1 | G151: =E151-E150 -> 19.7 | H151: =CORREL(C148:C151,E148:E151) -> 0.64305388 | I151: =CORREL(C139:C151,E139:E151) -> 0.28148519 | J151: =C151+E151 -> 121.6 | K151: =K150+J151 -> 55.5192 | L151: =L150+C151 -> -44.2308 | M151: =M150+E151 -> 99.75 | N151: =N150+J151 -> -1928.6008 | O151: =SUM(C139:C151) -> 794.4192 | P151: =SUM(E139:E151) -> -9.11 | Q151: =O151-P151 -> 803.5292
B152: 45135 | C152: 178.9 | E152: -8.7 | F152: =C152-C151 -> 50.5 | G152: =E152-E151 -> -1.9 | H152: =CORREL(C149:C152,E149:E152) -> 0.8510165 | I152: =CORREL(C140:C152,E140:E152) -> 0.3260649 | J152: =C152+E152 -> 170.2 | K152: =K151+J152 -> 225.7192 | L152: =L151+C152 -> 134.6692 | M152: =M151+E152 -> 91.05 | N152: =N151+J152 -> -1758.4008 | O152: =SUM(C140:C152) -> 1151.7392 | P152: =SUM(E140:E152) -> -28.79 | Q152: =O152-P152 -> 1180.5292
B153: 45142 | C153: 139.7 | E153: 19.9 | F153: =C153-C152 -> -39.2 | G153: =E153-E152 -> 28.6 | H153: =CORREL(C150:C153,E150:E153) -> -0.30377547 | I153: =CORREL(C141:C153,E141:E153) -> 0.27666973 | J153: =C153+E153 -> 159.6 | K153: =K152+J153 -> 385.3192 | L153: =L152+C153 -> 274.3692 | M153: =M152+E153 -> 110.95 | N153: =N152+J153 -> -1598.8008 | O153: =SUM(C141:C153) -> 1335.2892 | P153: =SUM(E141:E153) -> 61.91 | Q153: =O153-P153 -> 1273.3792
B154: 45149 | C154: -101 | E154: 8.8 | F154: =C154-C153 -> -240.7 | G154: =E154-E153 -> -11.1 | H154: =CORREL(C151:C154,E151:E154) -> -0.32550569 | I154: =CORREL(C142:C154,E142:E154) -> 0.1242602 | J154: =C154+E154 -> -92.2 | K154: =K153+J154 -> 293.1192 | L154: =L153+C154 -> 173.3692 | M154: =M153+E154 -> 119.75 | N154: =N153+J154 -> -1691.0008 | O154: =SUM(C142:C154) -> 1369.4092 | P154: =SUM(E142:E154) -> 106.3 | Q154: =O154-P154 -> 1263.1092
B155: 45156 | C155: -75.62 | E155: 1.5 | F155: =C155-C154 -> 25.38 | G155: =E155-E154 -> -7.3 | H155: =CORREL(C152:C155,E152:E155) -> -0.10388755 | I155: =CORREL(C143:C155,E143:E155) -> 0.11589775 | J155: =C155+E155 -> -74.12 | K155: =K154+J155 -> 218.9992 | L155: =L154+C155 -> 97.7492 | M155: =M154+E155 -> 121.25 | N155: =N154+J155 -> -1765.1208 | O155: =SUM(C143:C155) -> 1321.3592 | P155: =SUM(E143:E155) -> 112.01 | Q155: =O155-P155 -> 1209.3492
B156: 45163 | C156: -341.07 | E156: -20.25 | F156: =C156-C155 -> -265.45 | G156: =E156-E155 -> -21.75 | H156: =CORREL(C153:C156,E153:E156) -> 0.96287521 | I156: =CORREL(C144:C156,E144:E156) -> 0.2843542 | J156: =C156+E156 -> -361.32 | K156: =K155+J156 -> -142.3208 | L156: =L155+C156 -> -243.3208 | M156: =M155+E156 -> 101 | N156: =N155+J156 -> -2126.4408 | O156: =SUM(C144:C156) -> 1358.83 | P156: =SUM(E144:E156) -> 90.13 | Q156: =O156-P156 -> 1268.7
... B278: 46017 | C278: 283.78 | E278: -235.96 | F278: =C278-C277 -> -70.69 | G278: =E278-E277 -> -438.73 | H278: =CORREL(C275:C278,E275:E278) -> -0.43263473 | I278: =CORREL(C266:C278,E266:E278) -> 0.017505797 | J278: =C278+E278 -> 47.82 | K278: =K277+J278 -> 22389.819 | L278: =L277+C278 -> 903.9392 | M278: =M277+E278 -> 21485.88 | N278: =N277+J278 -> 20405.699 | O278: =SUM(C266:C278) -> 510.86 | P278: =SUM(E266:E278) -> 2072.66 | Q278: =O278-P278 -> -1561.8
B279: 46024
B280: 46031
B281: 46038
B282: 46045
B283: 46052
B284: 46059
B285: 46066
B286: 46073
B287: 46080
B288: 46087
B289: 46094
B290: 46101
... B315: 46276

Sheet Inflow - Outflow  - Stok
B1: Stok( 30.07.2021) | D1: 6 Kasım-19 Mart inFlow | H1: FLOW | AD1: 19 Mart Sonrası Kümülatif
A2: YABANCI | H2: 44281 | I2: 44288 | J2: 44295 | K2: 44302 | L2: 44308 | M2: 44316 | N2: 44323 | O2: 44330 | P2: 44337 | Q2: 44344 | R2: 44351 | S2: 44358 | T2: 44365 | U2: 44372 | V2: 44379 | W2: 44386 | X2: 44393 | Y2: 44400 | Z2: 44407 | AA2: 44414 | AB2: 44421
A3: Hisse Senedi | B3: ='Menkul Kıymet'!B172 -> 22047.5 | D3: ='Menkul Kıymet'!V136 -> 701.8 | H3: ='Menkul Kıymet'!I153 -> -813.9 | I3: ='Menkul Kıymet'!I154 -> -364.4 | J3: ='Menkul Kıymet'!I155 -> -46 | K3: ='Menkul Kıymet'!I156 -> 0 | L3: ='Menkul Kıymet'!I157 -> 104.5 | M3: ='Menkul Kıymet'!I158 -> 31.5 | N3: ='Menkul Kıymet'!I159 -> 87.7 | O3: ='Menkul Kıymet'!I160 -> 51.7 | P3: ='Menkul Kıymet'!I161 -> 51 | Q3: ='Menkul Kıymet'!I162 -> 6.8 | R3: ='Menkul Kıymet'!I163 -> -97.7 | S3: ='Menkul Kıymet'!I164 -> 33.5 | T3: ='Menkul Kıymet'!I165 -> -3.2 | U3: ='Menkul Kıymet'!I166 -> -3.4 | V3: ='Menkul Kıymet'!I167 -> -38.1 | W3: ='Menkul Kıymet'!I168 -> 54.2 | X3: ='Menkul Kıymet'!I169 -> -62 | Y3: ='Menkul Kıymet'!I170 -> 0 | Z3: ='Menkul Kıymet'!I171 -> -51.8 | AA3: ='Menkul Kıymet'!I172 -> 168 | AD3: =SUM(H3:AA3) -> -891.6
A4: DIBS | B4: ='Menkul Kıymet'!C172 -> 8570.7 | D4: ='Menkul Kıymet'!V138 -> 4428.6 | H4: ='Menkul Kıymet'!J153 -> -1104.8 | I4: ='Menkul Kıymet'!J154 -> -140.4 | J4: ='Menkul Kıymet'!J155 -> 77.9 | K4: ='Menkul Kıymet'!J156 -> 164.9 | L4: ='Menkul Kıymet'!J157 -> -252.6 | M4: ='Menkul Kıymet'!J158 -> 33 | N4: ='Menkul Kıymet'!J159 -> 23.7 | O4: ='Menkul Kıymet'!J160 -> 118.5 | P4: ='Menkul Kıymet'!J161 -> 174.8 | Q4: ='Menkul Kıymet'!J162 -> 69.2 | R4: ='Menkul Kıymet'!J163 -> -64.1 | S4: ='Menkul Kıymet'!J164 -> 80.3 | T4: ='Menkul Kıymet'!J165 -> -3.6 | U4: ='Menkul Kıymet'!J166 -> 172.5 | V4: ='Menkul Kıymet'!J167 -> 83 | W4: ='Menkul Kıymet'!J168 -> 5.9 | X4: ='Menkul Kıymet'!J169 -> 56.5 | Y4: ='Menkul Kıymet'!J170 -> 16.1 | Z4: ='Menkul Kıymet'!J171 -> 300.7 | AA4: ='Menkul Kıymet'!J172 -> 113.8 | AD4: =SUM(H4:AA4) -> -74.7
A5: Repo | B5: ='Menkul Kıymet'!D172 -> 1778.1 | D5: ='Menkul Kıymet'!V140 -> 1732.2 | H5: ='Menkul Kıymet'!K153 -> -11.7 | I5: ='Menkul Kıymet'!K154 -> 13.1 | J5: ='Menkul Kıymet'!K155 -> -6 | K5: ='Menkul Kıymet'!K156 -> 172 | L5: ='Menkul Kıymet'!K157 -> -323.8 | M5: ='Menkul Kıymet'!K158 -> 129.6 | N5: ='Menkul Kıymet'!K159 -> -12.4 | O5: ='Menkul Kıymet'!K160 -> 27.5 | P5: ='Menkul Kıymet'!K161 -> 47.8 | Q5: ='Menkul Kıymet'!K162 -> 267.7 | R5: ='Menkul Kıymet'!K163 -> -13 | S5: ='Menkul Kıymet'!K164 -> -112.1 | T5: ='Menkul Kıymet'!K165 -> -86 | U5: ='Menkul Kıymet'!K166 -> -36.8 | V5: ='Menkul Kıymet'!K167 -> 69.3 | W5: ='Menkul Kıymet'!K168 -> -59.8 | X5: ='Menkul Kıymet'!K169 -> -17.8 | Y5: ='Menkul Kıymet'!K170 -> 14.7 | Z5: ='Menkul Kıymet'!K171 -> 8.5 | AA5: ='Menkul Kıymet'!K172 -> -15.5 | AD5: =SUM(H5:AA5) -> 55.3
A6: OSBA | B6: ='Menkul Kıymet'!E172 -> 224.2 | D6: ='Menkul Kıymet'!V142 -> 60.8 | H6: ='Menkul Kıymet'!L153 -> -16.8 | I6: ='Menkul Kıymet'!L154 -> -4.1 | J6: ='Menkul Kıymet'!L155 -> 3.4 | K6: ='Menkul Kıymet'!L156 -> 18 | L6: ='Menkul Kıymet'!L157 -> -22.1 | M6: ='Menkul Kıymet'!L158 -> 6.5 | N6: ='Menkul Kıymet'!L159 -> 2.4 | O6: ='Menkul Kıymet'!L160 -> 2.1 | P6: ='Menkul Kıymet'!L161 -> 19.7 | Q6: ='Menkul Kıymet'!L162 -> -27.1 | R6: ='Menkul Kıymet'!L163 -> -29.7 | S6: ='Menkul Kıymet'!L164 -> 16.5 | T6: ='Menkul Kıymet'!L165 -> 5.6 | U6: ='Menkul Kıymet'!L166 -> -21.2 | V6: ='Menkul Kıymet'!L167 -> -2.8 | W6: ='Menkul Kıymet'!L168 -> -6.2 | X6: ='Menkul Kıymet'!L169 -> 8.3 | Y6: ='Menkul Kıymet'!L170 -> 2.8 | Z6: ='Menkul Kıymet'!L171 -> -10.2 | AA6: ='Menkul Kıymet'!L172 -> -3.2 | AD6: =SUM(H6:AA6) -> -58.1
A7: TR Eurobond | B7: ='Menkul Kıymet'!P172 -> 47528.9 | D7: ='Menkul Kıymet'!V144 -> 3645 | H7: ='Menkul Kıymet'!Q153-'Menkul Kıymet'!Q152 -> -586.2 | I7: ='Menkul Kıymet'!Q154-'Menkul Kıymet'!Q153 -> -979.4 | J7: ='Menkul Kıymet'!Q155-'Menkul Kıymet'!Q154 -> -338.3 | K7: ='Menkul Kıymet'!Q156-'Menkul Kıymet'!Q155 -> -184 | L7: ='Menkul Kıymet'!Q157-'Menkul Kıymet'!Q156 -> -46.3 | M7: ='Menkul Kıymet'!Q158-'Menkul Kıymet'!Q157 -> -89.9 | N7: ='Menkul Kıymet'!Q159-'Menkul Kıymet'!Q158 -> -255.1 | O7: ='Menkul Kıymet'!Q160-'Menkul Kıymet'!Q159 -> -29.5 | P7: ='Menkul Kıymet'!Q161-'Menkul Kıymet'!Q160 -> 44.7 | Q7: ='Menkul Kıymet'!Q162-'Menkul Kıymet'!Q161 -> -261.1 | R7: ='Menkul Kıymet'!Q163-'Menkul Kıymet'!Q162 -> -158.3 | S7: ='Menkul Kıymet'!Q164-'Menkul Kıymet'!Q163 -> -639 | T7: ='Menkul Kıymet'!Q165-'Menkul Kıymet'!Q164 -> -274.2 | U7: ='Menkul Kıymet'!Q166-'Menkul Kıymet'!Q165 -> 1540.5 | V7: ='Menkul Kıymet'!Q167-'Menkul Kıymet'!Q166 -> -135.5 | W7: ='Menkul Kıymet'!Q168-'Menkul Kıymet'!Q167 -> 1003.5 | X7: ='Menkul Kıymet'!Q169-'Menkul Kıymet'!Q168 -> -174.5 | Y7: ='Menkul Kıymet'!Q170-'Menkul Kıymet'!Q169 -> -75.9 | Z7: ='Menkul Kıymet'!Q171-'Menkul Kıymet'!Q170 -> -215.6 | AA7: ='Menkul Kıymet'!Q172-'Menkul Kıymet'!Q171 -> -213.7 | AD7: =SUM(H7:AA7) -> -2067.8
A8: Şirket Eurobond | B8: ='Menkul Kıymet'!S172 -> 41498.59 | D8: ='Menkul Kıymet'!V146 -> 1406.19 | H8: ='Menkul Kıymet'!T153-'Menkul Kıymet'!T152 -> -143.7 | I8: ='Menkul Kıymet'!T154-'Menkul Kıymet'!T153 -> 160.6 | J8: ='Menkul Kıymet'!T155-'Menkul Kıymet'!T154 -> -59.2 | K8: ='Menkul Kıymet'!T156-'Menkul Kıymet'!T155 -> 157.3 | L8: ='Menkul Kıymet'!T157-'Menkul Kıymet'!T156 -> -486.3 | M8: ='Menkul Kıymet'!T158-'Menkul Kıymet'!T157 -> -6.5 | N8: ='Menkul Kıymet'!T159-'Menkul Kıymet'!T158 -> -561.8 | O8: ='Menkul Kıymet'!T160-'Menkul Kıymet'!T159 -> 4.5 | P8: ='Menkul Kıymet'!T161-'Menkul Kıymet'!T160 -> 146.6 | Q8: ='Menkul Kıymet'!T162-'Menkul Kıymet'!T161 -> 519 | R8: ='Menkul Kıymet'!T163-'Menkul Kıymet'!T162 -> 210 | S8: ='Menkul Kıymet'!T164-'Menkul Kıymet'!T163 -> 70.95 | T8: ='Menkul Kıymet'!T165-'Menkul Kıymet'!T164 -> -36.83 | U8: ='Menkul Kıymet'!T166-'Menkul Kıymet'!T165 -> -33.02 | V8: ='Menkul Kıymet'!T167-'Menkul Kıymet'!T166 -> 1367.14 | W8: ='Menkul Kıymet'!T168-'Menkul Kıymet'!T167 -> -126.54 | X8: ='Menkul Kıymet'!T169-'Menkul Kıymet'!T168 -> 12.5 | Y8: ='Menkul Kıymet'!T170-'Menkul Kıymet'!T169 -> -71.2 | Z8: ='Menkul Kıymet'!T171-'Menkul Kıymet'!T170 -> 73.89 | AA8: ='Menkul Kıymet'!T172-'Menkul Kıymet'!T171 -> 676.91 | AD8: =SUM(H8:AA8) -> 1874.3
A9: Swap | B9: =Swap!E47 -> 12790 | D9: =Swap!G12 -> 14903 | H9: =Swap!D28 -> -6622 | I9: =Swap!D29 -> -1022 | J9: =Swap!D30 -> 280 | K9: =Swap!D31 -> -98 | L9: =Swap!D32 -> -695 | M9: =Swap!D33 -> -1011 | N9: =Swap!D34 -> 466 | O9: =Swap!D35 -> 103 | P9: =Swap!D36 -> -575 | Q9: =Swap!D37 -> -1323 | R9: =Swap!D38 -> -1308 | S9: =Swap!D39 -> 412 | T9: =Swap!D40 -> -1104 | U9: =Swap!D41 -> 219 | V9: =Swap!D42 -> 180 | W9: =Swap!D43 -> 171 | X9: =Swap!D44 -> 381 | Y9: =Swap!D45 -> -130 | Z9: =Swap!D46 -> 885 | AA9: =Swap!D47 -> -374 | AB9: =Swap!D48 -> 222 | AD9: =SUM(H9:AA9) -> -11165
A10: Toplam | B10: =SUM(B3:B9) -> 134437.99 | D10: =SUM(D3:E9) -> 26877.59 | H10: =SUM(H3:H9) -> -9299.1 | I10: =SUM(I3:I9) -> -2336.6 | J10: =SUM(J3:J9) -> -88.2 | K10: =SUM(K3:K9) -> 230.2 | L10: =SUM(L3:L9) -> -1721.6 | M10: =SUM(M3:M9) -> -906.8 | N10: =SUM(N3:N9) -> -249.5 | O10: =SUM(O3:O9) -> 277.8 | ... AA10: =SUM(AA3:AA9) -> 352.31 | AD10: =SUM(H10:AA10) -> -12327.6
A11: YERLİ
A12: DTH( Arındırılmış) | B12: ='Yerleşik DTH - Kamu Bankaları'!D4 -> 232246 | D12: 8267 | H12: -8125 | I12: ='Yerleşik DTH - Kamu Bankaları'!K4 -> -2024 | J12: ='Yerleşik DTH - Kamu Bankaları'!N4 -> 396 | K12: ='Yerleşik DTH - Kamu Bankaları'!Q4 -> 1345 | L12: ='Yerleşik DTH - Kamu Bankaları'!T4 -> -769 | M12: ='Yerleşik DTH - Kamu Bankaları'!W4 -> -201 | N12: ='Yerleşik DTH - Kamu Bankaları'!Z4 -> 537 | O12: ='Yerleşik DTH - Kamu Bankaları'!AC4 -> 451 | P12: ='Yerleşik DTH - Kamu Bankaları'!AF4 -> -937 | Q12: ='Yerleşik DTH - Kamu Bankaları'!AI4 -> 109 | R12: ='Yerleşik DTH - Kamu Bankaları'!AL4 -> -30 | S12: ='Yerleşik DTH - Kamu Bankaları'!AO4 -> 806 | T12: ='Yerleşik DTH - Kamu Bankaları'!AR4 -> 713 | U12: ='Yerleşik DTH - Kamu Bankaları'!AU4 -> 397 | V12: ='Yerleşik DTH - Kamu Bankaları'!AX4 -> 120 | W12: ='Yerleşik DTH - Kamu Bankaları'!BA4 -> 1724 | X12: ='Yerleşik DTH - Kamu Bankaları'!BD4 -> 1727 | Y12: ='Yerleşik DTH - Kamu Bankaları'!BG4 -> 791 | Z12: ='Yerleşik DTH - Kamu Bankaları'!BJ4 -> 352 | AA12: ='Yerleşik DTH - Kamu Bankaları'!BM4 -> 1664 | AB12: ='Yerleşik DTH - Kamu Bankaları'!BP4 -> 861 | AD12: =SUM(H12:AA12) -> -954
A13: Kamu Bankaları FX Poz | B13: ='Yerleşik DTH - Kamu Bankaları'!D12 -> -137 | D13: 5300 | H13: -422 | I13: 391 | J13: ='Yerleşik DTH - Kamu Bankaları'!H12 -> -24 | K13: ='Yerleşik DTH - Kamu Bankaları'!I12 -> 44.6 | L13: ='Yerleşik DTH - Kamu Bankaları'!J12 -> -98 | M13: ='Yerleşik DTH - Kamu Bankaları'!K12 -> 48 | N13: ='Yerleşik DTH - Kamu Bankaları'!L12 -> 5 | O13: ='Yerleşik DTH - Kamu Bankaları'!M12 -> 15 | P13: ='Yerleşik DTH - Kamu Bankaları'!N12 -> 50 | Q13: ='Yerleşik DTH - Kamu Bankaları'!O12 -> -109 | ... AA13: ='Yerleşik DTH - Kamu Bankaları'!Y12 -> -17 | AD13: =SUM(H13:AA13) -> -202.4
H17: DTH Kümülatif
H18: =SUM(H12) -> -8125 | I18: =SUM(H12+I12) -> -10149 | J18: =SUM(H12:J12) -> -9753 | K18: =SUM(H12:K12) -> -8408 | L18: =SUM(H12:L12) -> -9177 | M18: =SUM(H12:M12) -> -9378 | N18: =SUM(H12:N12) -> -8841 | O18: =SUM(H12:O12) -> -8390 | P18: =SUM(H12:P12) -> -9327 | Q18: =SUM(H12:Q12) -> -9218 | R18: =SUM(H12:R12) -> -9248 | S18: =SUM(H12:S12) -> -8442 | T18: =SUM(H12:T12) -> -7729 | U18: =SUM(H12:U12) -> -7332 | V18: =SUM(H12:V12) -> -7212 | W18: =SUM(H12:W12) -> -5488 | X18: =SUM(H12:X12) -> -3761 | Y18: =SUM(H12:Y12) -> -2970 | Z18: =SUM(H12:Z12) -> -2618 | AA18: =SUM(H12:AA12) -> -954 | AB18: =AA18+AB12 -> -93
M19: ='Menkul Kıymet'!I160 -> 51.7 | N19: ='Menkul Kıymet'!I161 -> 51 | O19: ='Menkul Kıymet'!I162 -> 6.8 | P19: ='Menkul Kıymet'!I163 -> -97.7
M20: ='Menkul Kıymet'!J160 -> 118.5 | N20: ='Menkul Kıymet'!J161 -> 174.8 | O20: ='Menkul Kıymet'!J162 -> 69.2 | P20: ='Menkul Kıymet'!J163 -> -64.1
O21: ='Menkul Kıymet'!K162 -> 267.7 | P21: ='Menkul Kıymet'!K163 -> -13
G22: ='Menkul Kıymet'!L154 -> -4.1 | H22: ='Menkul Kıymet'!L155 -> 3.4 | I22: ='Menkul Kıymet'!L156 -> 18 | J22: ='Menkul Kıymet'!L157 -> -22.1 | K22: ='Menkul Kıymet'!L158 -> 6.5 | O22: ='Menkul Kıymet'!L162 -> -27.1 | P22: ='Menkul Kıymet'!L163 -> -29.7
G25: =Swap!D29 -> -1022 | H25: =Swap!D30 -> 280 | I25: =Swap!D31 -> -98 | J25: =Swap!D32 -> -695 | K25: =Swap!D33 -> -1011 | O25: =Swap!D37 -> -1323 | P25: =Swap!D38 -> -1308

Sheet Yerleşik DTH - Kamu Bankaları
F1: KOVULMA SONRASI - Bireysel DTHlar ARINDIRILMIŞ DEĞİŞİM
F2: 44281 | I2: 44288 | L2: 44295 | O2: 44302 | R2: 44308 | U2: 44316 | X2: 44323 | AA2: 44330 | AD2: 44337 | AG2: 44344 | AJ2: 44351 | AM2: 44358 | AP2: 44365 | AS2: 44372 | AV2: 44379 | AY2: 44386 | BB2: 44393 | BE2: 44396 | BH2: 44407 | BK2: 44414 | BN2: 44421
A3: 6 Kasım Sonrası Artış(Arındırılmamış) | C3: Yerleşikler DTH | D3: STOK(13.08.2021) | F3: Birey | G3: Tüzel | H3: Arındırılmış | I3: Birey | J3: Tüzel | K3: Arındırılmış | L3: Birey | M3: Tüzel | N3: Arındırılmış | O3: Birey | P3: Tüzel | Q3: Arındırılmış | R3: Birey | S3: Tüzel | T3: Arındırılmış | U3: Birey | V3: Tüzel | W3: Arındırılmış | X3: Birey | Y3: Tüzel | Z3: Arındırılmış | AA3: Birey | AB3: Tüzel | AC3: Arındırılmış | AD3: Birey | AE3: Tüzel | AF3: Arındırılmış | AG3: Birey | AH3: Tüzel | AI3: Arındırılmış | AJ3: Birey | AK3: Tüzel | AL3: Arındırılmış | AM3: Birey | AN3: Tüzel | AO3: Arındırılmış | AP3: Birey | AQ3: Tüzel | AR3: Arındırılmış | AS3: Birey | AT3: Tüzel | AU3: Arındırılmış | AV3: Birey | AW3: Tüzel | AX3: Arındırılmış | AY3: Birey | AZ3: Tüzel | BA3: Arındırılmış | BB3: Birey | BC3: Tüzel | BD3: Arındırılmış | BE3: Birey | BF3: Tüzel | BG3: Arındırılmış | BH3: Birey | BI3: Tüzel | BJ3: Arındırılmış | BK3: Birey | BL3: Tüzel | BM3: Arındırılmış | BN3: Birey | BO3: Tüzel | BP3: Arındırılmış
A4: 8267 | D4: 232246 | F4: -6740 | G4: -1385 | H4: =F4+G4 -> -8125 | I4: -718 | J4: -1306 | K4: =I4+J4 -> -2024 | L4: -509 | M4: 905 | N4: =L4+M4 -> 396 | O4: 257 | P4: 1088 | Q4: 1345 | R4: -20 | S4: -749 | T4: -769 | U4: 33 | V4: -269 | W4: -201 | X4: -83 | Y4: 620 | Z4: 537 | AA4: 118 | AB4: 334 | AC4: 451 | AD4: -550 | AE4: -387 | AF4: -937 | AG4: 275 | AH4: -166 | AI4: 109 | AJ4: 456 | AK4: -485 | AL4: -30 | AM4: -101 | AN4: 907 | AO4: 806 | AP4: 455 | AQ4: 258 | AR4: 713 | AS4: 340 | AT4: 57 | AU4: 397 | AV4: 340 | AW4: -222 | AX4: 120 | AY4: 288 | AZ4: 1437 | BA4: 1724 | BB4: 732 | BC4: 995 | BD4: =BB4+BC4 -> 1727 | BE4: 494 | BF4: 297 | BG4: =BE4+BF4 -> 791 | BH4: 327 | BI4: 25 | BJ4: 352 | BK4: 701 | BL4: 963 | BM4: 1664 | BN4: 580 | BO4: 281 | BP4: 861
F10: Kamu Bankaları FX Pozisyon Değişimi | O10: KAMU BANKASI FX POZİSYONLARINDAKİ DEĞİŞİM
A11: Kamu Bankaları FX Poz | D11: STOK(13.08.2021) | F11: 44281 | G11: 44288 | H11: 44295 | I11: 44302 | J11: 44308 | K11: 44316 | L11: 44323 | M11: 44330 | N11: 44337 | O11: 44344 | P11: 44351 | Q11: 44358 | R11: 44365 | S11: 44372 | T11: 44379 | U11: 44386 | V11: 44393 | W11: 44396 | X11: 44407 | Y11: 44414 | Z11: 44421
A12: 6 Kasım Sonrası ne kadar aldı ? | D12: -137 | F12: -422 | G12: =328+63 -> 391 | H12: -24 | I12: 44.6 | J12: -98 | K12: 48 | L12: 5 | M12: 15 | N12: 50 | O12: -109 | P12: 9 | Q12: 220 | R12: -20 | S12: -60 | T12: -16 | U12: -92 | V12: -180 | W12: 10 | X12: 43 | Y12: -17 | Z12: -30
A13: =94-(-5206) -> 5300

Sheet Swap
A1: TARİH | B1: Swap Para Alım - TL | C1: Swap Para Satım - TL | D1: Net Para Satım - TL | E1: TCMB Swap | F1: Y.Dışı yerleşikler Swap Stok | G1: Haluk Bürükçekçi Verileri | K1: bddk aylık rapor
A2: 12'2017 | B2: 40991 | C2: 88052 | D2: =C2-B2 -> 47061 | E2: 0 | F2: =D2-E2 -> 47061 | K2: Bilanço dışı İşlemler :USD BAZINDA
A3: 12'2018 | B3: 22565 | C3: 59554 | D3: =C3-B3 -> 36989 | E3: 264 | F3: =D3-E3 -> 36725 | K3: Para Swapları
A4: 12'2019 | B4: 15946 | C4: 60193 | D4: =C4-B4 -> 44247 | E4: 12310 | F4: =D4-E4 -> 31937 | K4: Swap Para Alım
A5: 10'2020 | B5: 7233 | C5: 59116 | D5: =C5-B5 -> 51883 | E5: 49900 | F5: =D5-E5 -> 1983 | K5: Swap Para satım
A6: 11'2020 | B6: 8807 | C6: 67361 | D6: =C6-B6 -> 58554 | E6: 46400 | F6: =D6-E6 -> 12154
A7: 12'2020 | B7: 9458 | C7: 74109 | D7: =C7-B7 -> 64651 | E7: 44300 | F7: =D7-E7 -> 20351
A11: TARİH | B11: TCMB TARAFLI SWAP STOĞU( Günlük ) | C11: BDDK = Bilanço Dışı YP( Haftalık ) | D11: Haftalık Carry Trade poz. Değişimi | E11: Y.Dışı yerleşikler Swap Stok | G11: 6 Kasım Sonrası Giren Carry Poz
A12: Eylül'20 | B12: 45387 | C12: 54439 | E12: =C12-B12 -> 9052 | G12: =SUM(D13:D26) -> 14903
A13: Ekim'20 | B13: 49353 | C13: 58556 | D13: =(C13-C12)-(B13-B12) -> 151 | E13: =C13-B13 -> 9203
A14: Kasım'20 | B14: 45928 | C14: 62252 | D14: =(C14-C13)-(B14-B13) -> 7121 | E14: =C14-B14 -> 16324
A15: Aralık'20 | B15: 44428 | C15: 66852 | D15: =(C15-C14)-(B15-B14) -> 6100 | E15: =C15-B15 -> 22424 | G15: Source
A16: 44204 | B16: 43601 | C16: 65329 | D16: =(C16-C15)-(B16-B15) -> -696 | E16: =C16-B16 -> 21728 | G16: TCMB Taraflı Swap İşlemleri
A17: 44211 | B17: 43447 | C17: 65194 | D17: =(C17-C16)-(B17-B16) -> 19 | E17: =C17-B17 -> 21747 | G17: BDDK = BDYP
A18: 44218 | B18: 42363 | C18: 65453 | D18: =(C18-C17)-(B18-B17) -> 1343 | E18: =C18-B18 -> 23090
A19: 44225 | B19: 41590 | C19: 64835 | D19: =(C19-C18)-(B19-B18) -> 155 | E19: =C19-B19 -> 23245
A20: 44232 | B20: 41176 | C20: 64162 | D20: =(C20-C19)-(B20-B19) -> -259 | E20: =C20-B20 -> 22986 | G20: Önceki Verileri şu şekilde buluyoruz
A21: 44239 | B21: 40160 | C21: 63922 | D21: =(C21-C20)-(B21-B20) -> 776 | E21: =C21-B21 -> 23762 | G21: UA Rezervler tablosu ( Aylık ) ndaki Swaplar - Yabancı MB Swapları | O21: BDYP = Ayın son haftası olarak alınıyor
A22: 44246 | B22: 39899 | C22: 64173 | D22: =(C22-C21)-(B22-B21) -> 512 | E22: =C22-B22 -> 24274
A23: 44253 | B23: 40389 | C23: 63153 | D23: =(C23-C22)-(B23-B22) -> -1510 | E23: =C23-B23 -> 22764 | G23: 2. Yurt içi para karşılığında döviz forward ve future'ların toplam açık ve fazla pozisyon büyüklükleri (para swaplarının gelecekteki bacağını da kapsar) ++++++3. Diğer == SWAPLAR
A24: 44260 | B24: 40305 | C24: 63091 | D24: =(C24-C23)-(B24-B23) -> 22 | E24: =C24-B24 -> 22786 | G24: Yabancı MB Swapları : 17,5B USD
A25: 44267 | B25: 40170 | C25: 62825 | D25: =(C25-C24)-(B25-B24) -> -131 | E25: =C25-B25 -> 22655
A26: 44274 | B26: 44786 | C26: 68741 | D26: =(C26-C25)-(B26-B25) -> 1300 | E26: =C26-B26 -> 23955
A27: N. Ağbal'ın Kovulması
A28: 44281 | B28: 42779 | C28: 60112 | D28: =(C28-C26)-(B28-B26) -> -6622 | E28: =C28-B28 -> 17333
A29: 44288 | B29: 42721 | C29: 59032 | D29: =(C29-C28)-(B29-B28) -> -1022 | E29: =C29-B29 -> 16311
A30: 44295 | B30: 41961 | C30: 58552 | D30: =(C30-C29)-(B30-B29) -> 280 | E30: =C30-B30 -> 16591
A31: 44302 | B31: 42328 | C31: 58821 | D31: =(C31-C30)-(B31-B30) -> -98 | E31: =C31-B31 -> 16493
A32: 44308 | B32: 42432 | C32: 58230 | D32: =(C32-C31)-(B32-B31) -> -695 | E32: =C32-B32 -> 15798
A33: 44316 | B33: 43217 | C33: 58004 | D33: =(C33-C32)-(B33-B32) -> -1011 | E33: =C33-B33 -> 14787
A34: 44323 | B34: 42279 | C34: 57532 | D34: =(C34-C33)-(B34-B33) -> 466 | E34: =C34-B34 -> 15253
A35: 44328 | B35: 42298 | C35: 57654 | D35: =(C35-C34)-(B35-B34) -> 103 | E35: =C35-B35 -> 15356
A36: 44337 | B36: 42514 | C36: 57295 | D36: =(C36-C35)-(B36-B35) -> -575 | E36: =C36-B36 -> 14781
A37: 44344 | B37: 42317 | C37: 55775 | D37: =(C37-C36)-(B37-B36) -> -1323 | E37: =C37-B37 -> 13458
A38: 44351 | B38: 44400 | C38: 56550 | D38: =(C38-C37)-(B38-B37) -> -1308 | E38: =C38-B38 -> 12150
A39: 44358 | B39: 45204 | C39: 57766 | D39: =(C39-C38)-(B39-B38) -> 412 | E39: =C39-B39 -> 12562
A40: 44365 | B40: 45735 | C40: 57193 | D40: =(C40-C39)-(B40-B39) -> -1104 | E40: =C40-B40 -> 11458
... A48: 44421 | B48: 44845 | C48: 57857 | D48: =(C48-C47)-(B48-B47) -> 222 | E48: =C48-B48 -> 13012

Sheet Credit
A1: HER PERŞEMBE | C1: Tüketici Kredileri ve Bireysel Kredi Kartları (3+7) | D1: Ticari ve Diğer Krediler | E1: Bireysel Krediler(USD) | F1: Ticari Krediler(USD) | G1: USDTRY | H1: Krediler / Toplam Krediler (2+10) | I1: Aylık Kredi Flowu(TL) | J1: Haftalık Kredi Flowu ( TL ) | K1: Haftalık Kredi Flowu ( TL )/ TOTAL Kredi Stoğu | L1: Aylık TL Kredi Flowu(USDBazında) | M1: Aylık TL Kredi Flowu(USD Bazında ) + Aylık USD Flowu | N1: YP Flow minus TL Kredi Flow ( USD Eq.) | O1: Aylık Kredi Flowu ( TL )/ TOTAL Kredi Stoğu | P1: Toplam MoM % | Q1: Toplam YoY % | S1: Tüketici Kredileri MoM % | T1: Tüketici YoY % | U1: 13-WEEK GROWTH - Tüketici | V1: Haftalık Tüketici Flowu / Haftalık Toplam Flow | W1: Aylık Tüketici Flowu Aylık Total Flowun Kaçı | X1: Ticari Krediler MoM % | Y1: Ticari YoY % | Z1: 13-WEEK GROWTH - Ticari | AA1: Haftalık Ticari Flowu / Haftalık Toplam Flow | AB1: Haftalık Ticari Flowu Haftalık total Flowun kaçı 13w Avg | AC1: Haftalık Tükecii Flowu Haftalık Total Flowun kaçı 13w Avg | AD1: Aylık ticari Flowu Aylık Total Flowun Kaçı | AE1: 13 Week MA | AF1: 13 W Kredi MoM % | AG1: 13 W Kredi YoY % | AH1: YP KREDİLER (Dolar Bazında) | AI1: Ticari Krediler(TL Ederi) | AJ1: USD Bazlı - Ticari Krediler Aylık Büyüme | AK1: Aylık USD Artış | AL1: Haftalık USD Artış | AM1: Haftalık USD Artış - TL Ederi | AN1: Aylık Artışı TL Ederi | AO1: USD Kredi Total TL Değeri | AP1: TL Kredi Total / FX Kredi
A2: BDDK BÜLTEN | B2: 41999 | C2: 353346.2 | D2: 526178.83 | E2: 112.16 | F2: 155463.25 | G2: 2.31884 | H2: 879525.03 | K2: =J2/H2 -> 0 | O2: =I2/H2 -> 0 | V2: =(C2-C1)/H2 -> #VALUE! | W2: =(C2-#REF!)/(H2-#REF!) -> #REF! | AA2: =(D2-D1)/O2 -> #VALUE! | AD2: =(D2-#REF!)/(H2-#REF!) -> #REF! | AI2: =F2*G2 -> 360494.4 | AO2: =(E2+F2)*G2 -> 360754.48 | AP2: =H2/AO2 -> 2.4380155
B3: 42006 | C3: 355760.74 | D3: 519487.04 | E3: 109.33 | F3: 154576.58 | G3: 2.321875 | H3: 875247.77 | J3: =H3-H2 -> -4277.26 | K3: =J3/H3 -> -0.0048869133 | O3: =I3/H3 -> 0 | V3: =(C3-C2)/H3 -> 0.0027586931 | W3: =(C3-#REF!)/(H3-#REF!) -> #REF! | AA3: =(D3-D2)/O3 -> #DIV/0! | AD3: =(D3-#REF!)/(H3-#REF!) -> #REF! | AI3: =F3*G3 -> 358907.5 | AL3: =F3-F2 -> -886.67 | AM3: =AL3*G3 -> -2058.7369 | AO3: =(E3+F3)*G3 -> 359161.35 | AP3: =H3/AO3 -> 2.4369208
B4: 42013 | C4: 355131.13 | D4: 518851.38 | E4: 110.28 | F4: 153907.65 | G4: 2.32936 | H4: 873982.51 | J4: =H4-H3 -> -1265.26 | K4: =J4/H4 -> -0.0014476949 | O4: =I4/H4 -> 0 | V4: =(C4-C3)/(H4-H3) -> 0.49761314 | W4: =(C4-#REF!)/(H4-#REF!) -> #REF! | AA4: =(D4-D3)/O4 -> #DIV/0! | AD4: =(D4-#REF!)/(H4-#REF!) -> #REF! | AI4: =F4*G4 -> 358506.32 | AL4: =F4-F3 -> -668.93 | AM4: =AL4*G4 -> -1558.1788 | AO4: =(E4+F4)*G4 -> 358763.21 | AP4: =H4/AO4 -> 2.4360985
B5: 42020 | C5: 354536.18 | D5: 525016.71 | E5: 113.63 | F5: 153013.97 | G5: 2.28808 | H5: 879552.89 | J5: =H5-H4 -> 5570.38 | K5: =J5/H5 -> 0.006333195 | O5: =I5/H5 -> 0 | V5: =(C5-C4)/(H5-H4) -> -0.106806 | W5: =(C5-C1)/(H5-H1) -> #VALUE! | AA5: =(D5-D4)/O5 -> #DIV/0! | AD5: =(D5-D1)/(H5-H1) -> #VALUE! | AI5: =F5*G5 -> 350108.2 | AL5: =F5-F4 -> -893.68 | AM5: =AL5*G5 -> -2044.8113 | AO5: =(E5+F5)*G5 -> 350368.2 | AP5: =H5/AO5 -> 2.5103674
B6: 42027 | C6: 355250.21 | D6: 522413.23 | E6: 115.58 | F6: 152033.36 | G6: 2.33364 | H6: 877663.44 | I6: =H6-H2 -> -1861.59 | J6: =H6-H5 -> -1889.45 | K6: =J6/H6 -> -0.0021528184 | L6: =I6/G6 -> -797.71944 | M6: =L6+AK6 -> -4227.6094 | N6: =AK6-L6 -> -2632.1706 | O6: =I6/H6 -> -0.002121075 | P6: =(H6-H2)/H2 -> -0.0021165856 | S6: =(C6-C2)/C2 -> 0.0053885113 | V6: =(C6-C5)/(H6-H5) -> -0.37790362 | W6: =(C6-C2)/(H6-H2) -> -1.022787 | X6: =(D6-D2)/D2 -> -0.0071565023 | AA6: =(D6-D5)/(H6-H5) -> 1.3779036 | AF6: =(AE6-AE2)/AE2 -> #DIV/0! | AI6: =F6*G6 -> 354791.13 | AJ6: =(AI6-AI2)/AI2 -> -0.015820696 | AK6: =(F6-F2) -> -3429.89 | AL6: =F6-F5 -> -980.61 | AM6: =AL6*G6 -> -2288.3907 | AN6: =AK6*G6 -> -8004.1285 | AO6: =(E6+F6)*G6 -> 355060.85 | AP6: =H6/AO6 -> 2.4718677
B7: 42034 | C7: 357986.9 | D7: 529374.76 | E7: 114.19 | F7: 152437.86 | G7: 2.36258 | H7: 887361.66 | I7: =H7-H3 -> 12113.89 | J7: =H7-H6 -> 9698.22 | K7: =J7/H7 -> 0.010929275 | L7: =I7/G7 -> 5127.3989 | M7: =L7+AK7 -> 2988.6789 | N7: =AK7-L7 -> -7266.1189 | O7: =I7/H7 -> 0.013651581 | P7: =(H7-H3)/H3 -> 0.013840527 | S7: =(C7-C3)/C3 -> 0.0062574639 | V7: =(C7-C6)/(H7-H6) -> 0.28218477 | W7: =(C7-C3)/(H7-H3) -> 0.18376921 | X7: =(D7-D3)/D3 -> 0.019033622 | AA7: =(D7-D6)/(H7-H6) -> 0.71781523 | AD7: =(D7-D3)/(H7-H3) -> 0.81622996 | AF7: =(AE7-AE3)/AE3 -> #DIV/0! | AI7: =F7*G7 -> 360146.64 | AJ7: =(AI7-AI3)/AI3 -> 0.0034525403 | AK7: =(F7-F3) -> -2138.72 | AL7: =F7-F6 -> 404.5 | AM7: =AL7*G7 -> 955.66361 | AN7: =AK7*G7 -> -5052.8971 | AO7: =(E7+F7)*G7 -> 360416.42 | AP7: =H7/AO7 -> 2.4620456
B8: 42041 | C8: 358441.15 | D8: 529300.33 | E8: 80.81 | F8: 153178.82 | G8: 2.42202 | H8: 887741.48 | I8: =H8-H4 -> 13758.97 | J8: =H8-H7 -> 379.82 | K8: =J8/H8 -> 0.00042784978 | L8: =I8/G8 -> 5680.783 | M8: =L8+AK8 -> 4951.953 | N8: =AK8-L8 -> -6409.613 | O8: =I8/H8 -> 0.015498848 | P8: =(H8-H4)/H4 -> 0.015742844 | S8: =(C8-C4)/C4 -> 0.0093205572 | V8: =(C8-C7)/(H8-H7) -> 1.1959612 | W8: =(C8-C4)/(H8-H4) -> 0.24057179 | X8: =(D8-D4)/D4 -> 0.020138618 | AA8: =(D8-D7)/(H8-H7) -> -0.19596124 | AD8: =(D8-D4)/(H8-H4) -> 0.75942821 | AF8: =(AE8-AE4)/AE4 -> #DIV/0! | AI8: =F8*G8 -> 371002.17 | AJ8: =(AI8-AI4)/AI4 -> 0.03485529 | AK8: =(F8-F4) -> -728.83 | AL8: =F8-F7 -> 740.96 | AM8: =AL8*G8 -> 1794.6199 | AN8: =AK8*G8 -> -1765.2408 | AO8: =(E8+F8)*G8 -> 371197.89 | AP8: =H8/AO8 -> 2.3915585
B9: 42048 | C9: 360437.67 | D9: 534725.62 | E9: 86.27 | F9: 153528.26 | G9: 2.47554 | H9: 895163.29 | I9: =H9-H5 -> 15610.4 | J9: =H9-H8 -> 7421.81 | K9: =J9/H9 -> 0.0082910125 | L9: =I9/G9 -> 6305.8565 | M9: =L9+AK9 -> 6820.1465 | N9: =AK9-L9 -> -5791.5665 | O9: =I9/H9 -> 0.017438606 | P9: =(H9-H5)/H5 -> 0.017748108 | S9: =(C9-C5)/C5 -> 0.016645664 | V9: =(C9-C8)/(H9-H8) -> 0.26900716 | W9: =(C9-C5)/(H9-H5) -> 0.37804861 | X9: =(D9-D5)/D5 -> 0.018492573 | AA9: =(D9-D8)/(H9-H8) -> 0.73099284 | AD9: =(D9-D5)/(H9-H5) -> 0.62195139 | AF9: =(AE9-AE5)/AE5 -> #DIV/0! | AI9: =F9*G9 -> 380065.35 | AJ9: =(AI9-AI5)/AI5 -> 0.085565388 | AK9: =(F9-F5) -> 514.29 | AL9: =F9-F8 -> 349.44 | AM9: =AL9*G9 -> 865.0527 | AN9: =AK9*G9 -> 1273.1455 | AO9: =(E9+F9)*G9 -> 380278.91 | AP9: =H9/AO9 -> 2.3539651
B10: 42055 | C10: 358500.17 | D10: 536262.33 | E10: 86.9 | F10: 153622.3 | G10: 2.45428 | H10: 894762.5 | I10: =H10-H6 -> 17099.06 | J10: =H10-H9 -> -400.79 | K10: =J10/H10 -> -0.00044792892 | L10: =I10/G10 -> 6967.0372 | M10: =L10+AK10 -> 8555.9772 | N10: =AK10-L10 -> -5378.0972 | O10: =I10/H10 -> 0.019110166 | P10: =(H10-H6)/H6 -> 0.01948248 | S10: =(C10-C6)/C6 -> 0.009148369 | V10: =(C10-C9)/(H10-H9) -> 4.8342025 | W10: =(C10-C6)/(H10-H6) -> 0.19006659 | X10: =(D10-D6)/D6 -> 0.026509857 | AA10: =(D10-D9)/(H10-H9) -> -3.8342025 | AD10: =(D10-D6)/(H10-H6) -> 0.80993341 | AF10: =(AE10-AE6)/AE6 -> #DIV/0! | AI10: =F10*G10 -> 377032.14 | AJ10: =(AI10-AI6)/AI6 -> 0.062687611 | AK10: =(F10-F6) -> 1588.94 | AL10: =F10-F9 -> 94.04 | AM10: =AL10*G10 -> 230.80049 | AN10: =AK10*G10 -> 3899.7037 | AO10: =(E10+F10)*G10 -> 377245.42 | AP10: =H10/AO10 -> 2.3718313
B11: 42062 | C11: 359676.33 | D11: 544017.13 | E11: 78.33 | F11: 153759.37 | G11: 2.46906 | H11: 903693.45 | I11: =H11-H7 -> 16331.79 | J11: =H11-H10 -> 8930.95 | K11: =J11/H11 -> 0.0098827207 | L11: =I11/G11 -> 6614.578 | M11: =L11+AK11 -> 7936.088 | N11: =AK11-L11 -> -5293.068 | O11: =I11/H11 -> 0.018072268 | P11: =(H11-H7)/H7 -> 0.018404886 | S11: =(C11-C7)/C7 -> 0.0047192509 | V11: =(C11-C10)/(H11-H10) -> 0.13169484 | W11: =(C11-C7)/(H11-H7) -> 0.10344426 | X11: =(D11-D7)/D7 -> 0.027659743 | AA11: =(D11-D10)/(H11-H10) -> 0.86830628 | AD11: =(D11-D7)/(H11-H7) -> 0.89655635 | AF11: =(AE11-AE7)/AE7 -> #DIV/0! | AI11: =F11*G11 -> 379641.11 | AJ11: =(AI11-AI7)/AI7 -> 0.054129259 | AK11: =(F11-F7) -> 1321.51 | AL11: =F11-F10 -> 137.07 | AM11: =AL11*G11 -> 338.43405 | AN11: =AK11*G11 -> 3262.8875 | AO11: =(E11+F11)*G11 -> 379834.51 | AP11: =H11/AO11 -> 2.3791768
B12: 42069 | C12: 360105.04 | D12: 544398.71 | E12: 74.8 | F12: 152999.76 | G12: 2.53216 | H12: 904503.75 | I12: =H12-H8 -> 16762.27 | J12: =H12-H11 -> 810.3 | K12: =J12/H12 -> 0.00089585035 | L12: =I12/G12 -> 6619.7515 | M12: =L12+AK12 -> 6440.6915 | N12: =AK12-L12 -> -6798.8115 | O12: =I12/H12 -> 0.018532007 | P12: =(H12-H8)/H8 -> 0.018881927 | S12: =(C12-C8)/C8 -> 0.0046420172 | V12: =(C12-C11)/(H12-H11) -> 0.52907565 | W12: =(C12-C8)/(H12-H8) -> 0.099264002 | X12: =(D12-D8)/D8 -> 0.028525166 | AA12: =(D12-D11)/(H12-H11) -> 0.47091201 | AD12: =(D12-D8)/(H12-H8) -> 0.900736 | AF12: =(AE12-AE8)/AE8 -> #DIV/0! | AI12: =F12*G12 -> 387419.87 | AJ12: =(AI12-AI8)/AI8 -> 0.04425232 | AK12: =(F12-F8) -> -179.06 | AL12: =F12-F11 -> -759.61 | AM12: =AL12*G12 -> -1923.4541 | AN12: =AK12*G12 -> -453.40857 | AO12: =(E12+F12)*G12 -> 387609.28 | AP12: =H12/AO12 -> 2.3335451
B13: 42076 | C13: 361482.74 | D13: 547221.3 | E13: 105.97 | F13: 151756.57 | G13: 2.60754 | H13: 908704.04 | I13: =H13-H9 -> 13540.75 | J13: =H13-H12 -> 4200.29 | K13: =J13/H13 -> 0.004622286 | L13: =I13/G13 -> 5192.9213 | M13: =L13+AK13 -> 3421.2313 | N13: =AK13-L13 -> -6964.6113 | O13: =I13/H13 -> 0.014901166 | P13: =(H13-H9)/H9 -> 0.01512657 | S13: =(C13-C9)/C9 -> 0.0028994472 | V13: =(C13-C12)/(H13-H12) -> 0.32800116 | W13: =(C13-C9)/(H13-H9) -> 0.077179624 | X13: =(D13-D9)/D9 -> 0.023368396 | AA13: =(D13-D12)/(H13-H12) -> 0.67199884 | AD13: =(D13-D9)/(H13-H9) -> 0.92282038 | AF13: =(AE13-AE9)/AE9 -> #DIV/0! | AI13: =F13*G13 -> 395711.33 | AJ13: =(AI13-AI9)/AI9 -> 0.041166546 | AK13: =(F13-F9) -> -1771.69 | AL13: =F13-F12 -> -1243.19 | AM13: =AL13*G13 -> -3241.6677 | AN13: =AK13*G13 -> -4619.7525 | AO13: =(E13+F13)*G13 -> 395987.65 | AP13: =H13/AO13 -> 2.2947788
B14: 42083 | C14: 360704.08 | D14: 548372.33 | E14: 109.45 | F14: 152777.4 | G14: 2.61184 | H14: 909076.41 | I14: =H14-H10 -> 14313.91 | J14: =H14-H13 -> 372.37 | K14: =J14/H14 -> 0.00040961353 | L14: =I14/G14 -> 5480.3931 | M14: =L14+AK14 -> 4635.4931 | N14: =AK14-L14 -> -6325.2931 | O14: =I14/H14 -> 0.015745552 | P14: =(H14-H10)/H10 -> 0.015997441 | S14: =(C14-C10)/C10 -> 0.0061475843 | V14: =(C14-C13)/(H14-H13) -> -2.0910922 | W14: =(C14-C10)/(H14-H10) -> 0.15396981 | X14: =(D14-D10)/D10 -> 0.022582231 | AA14: =(D14-D13)/(H14-H13) -> 3.0910922 | AB14: =AVERAGE(AA2:AA14) -> #VALUE! | AC14: =AVERAGE(V2:V14) -> #VALUE! | AD14: =(D14-D10)/(H14-H10) -> 0.84603019 | AE14: =AVERAGE(H2:H14) -> 890536.79 | AF14: =(AE14-AE10)/AE10 -> #DIV/0! | AI14: =F14*G14 -> 399030.12 | AJ14: =(AI14-AI10)/AI10 -> 0.058345122 | AK14: =(F14-F10) -> -844.9 | AL14: =F14-F13 -> 1020.83 | AM14: =AL14*G14 -> 2666.2446 | AN14: =AK14*G14 -> -2206.7436 | AO14: =(E14+F14)*G14 -> 399315.99 | AP14: =H14/AO14 -> 2.276584
B15: 42090 | C15: 363049.28 | D15: 555083.17 | E15: 106 | F15: 153777.79 | G15: 2.60578 | H15: 918132.45 | I15: =H15-H11 -> 14439 | J15: =H15-H14 -> 9056.04 | K15: =J15/H15 -> 0.0098635442 | L15: =I15/G15 -> 5541.1432 | M15: =L15+AK15 -> 5559.5632 | N15: =AK15-L15 -> -5522.7232 | O15: =I15/H15 -> 0.015726489 | P15: =(H15-H11)/H11 -> 0.015977763 | S15: =(C15-C11)/C11 -> 0.0093777369 | U15: =(C15-C2)/C2 -> 0.027460547 | V15: =(C15-C14)/(H15-H14) -> 0.25896529 | W15: =(C15-C11)/(H15-H11) -> 0.23359997 | X15: =(D15-D11)/D11 -> 0.020341345 | Z15: =(D15-D2)/D2 -> 0.054932541 | AA15: =(D15-D14)/(H15-H14) -> 0.74103471 | AB15: =AVERAGE(AA3:AA15) -> #DIV/0! | AC15: =AVERAGE(V3:V15) -> 0.44258943 | AD15: =(D15-D11)/(H15-H11) -> 0.76639934 | AE15: =AVERAGE(H3:H15) -> 893506.59 | AF15: =(AE15-AE11)/AE11 -> #DIV/0! | AI15: =F15*G15 -> 400711.09 | AJ15: =(AI15-AI11)/AI11 -> 0.055499731 | AK15: =(F15-F11) -> 18.42 | AL15: =F15-F14 -> 1000.39 | AM15: =AL15*G15 -> 2606.7963 | AN15: =AK15*G15 -> 47.998468 | AO15: =(E15+F15)*G15 -> 400987.3 | AP15: =H15/AO15 -> 2.2896796
B16: 42097 | C16: 364627.6 | D16: 556032.83 | E16: 106.2 | F16: 154450 | G16: 2.58372 | H16: 920660.42 | I16: =H16-H12 -> 16156.67 | J16: =H16-H15 -> 2527.97 | K16: =J16/H16 -> 0.0027458224 | L16: =I16/G16 -> 6253.2589 | M16: =L16+AK16 -> 7703.4989 | N16: =AK16-L16 -> -4803.0189 | O16: =I16/H16 -> 0.017549 | P16: =(H16-H12)/H12 -> 0.017862469 | S16: =(C16-C12)/C12 -> 0.012559002 | U16: =(C16-C3)/C3 -> 0.024923661 | V16: =(C16-C15)/(H16-H15) -> 0.62434285 | W16: =(C16-C12)/(H16-H12) -> 0.27991907 | X16: =(D16-D12)/D12 -> 0.021370587 | Z16: =(D16-D3)/D3 -> 0.070349763 | AA16: =(D16-D15)/(H16-H15) -> 0.3756611 | AB16: =AVERAGE(AA4:AA16) -> #DIV/0! | AC16: =AVERAGE(V4:V16) -> 0.4904036 | AD16: =(D16-D12)/(H16-H12) -> 0.72008155 | AE16: =AVERAGE(H4:H16) -> 896999.87 | AF16: =(AE16-AE12)/AE12 -> #DIV/0! | AI16: =F16*G16 -> 399055.55 | AJ16: =(AI16-AI12)/AI12 -> 0.030033776 | AK16: =(F16-F12) -> 1450.24 | AL16: =F16-F15 -> 672.21 | AM16: =AL16*G16 -> 1736.8024 | AN16: =AK16*G16 -> 3747.0141 | AO16: =(E16+F16)*G16 -> 399329.95 | AP16: =H16/AO16 -> 2.3055131
B17: 42104 | C17: 365207.47 | D17: 562370.53 | E17: 106.56 | F17: 153515.04 | G17: 2.66732 | H17: 927577.99 | I17: =H17-H13 -> 18873.95 | J17: =H17-H16 -> 6917.57 | K17: =J17/H17 -> 0.0074576694 | L17: =I17/G17 -> 7075.9976 | M17: =L17+AK17 -> 8834.4676 | N17: =AK17-L17 -> -5317.5276 | O17: =I17/H17 -> 0.020347561 | P17: =(H17-H13)/H13 -> 0.020770184 | S17: =(C17-C13)/C13 -> 0.010304033 | U17: =(C17-C4)/C4 -> 0.028373576 | V17: =(C17-C16)/(H17-H16) -> 0.083825679 | W17: =(C17-C13)/(H17-H13) -> 0.19734767 | X17: =(D17-D13)/D13 -> 0.027683919 | Z17: =(D17-D4)/D4 -> 0.083875945 | AA17: =(D17-D16)/(H17-H16) -> 0.91617432 | AB17: =AVERAGE(AA5:AA17) -> #DIV/0! | AC17: =AVERAGE(V5:V17) -> 0.45857379 | AD17: =(D17-D13)/(H17-H13) -> 0.80265286 | AE17: =AVERAGE(H5:H17) -> 901122.6 | AF17: =(AE17-AE13)/AE13 -> #DIV/0! | AI17: =F17*G17 -> 409473.74 | AJ17: =(AI17-AI13)/AI13 -> 0.034778913 | AK17: =(F17-F13) -> 1758.47 | AL17: =F17-F16 -> -934.96 | AM17: =AL17*G17 -> -2493.8375 | AN17: =AK17*G17 -> 4690.4022 | AO17: =(E17+F17)*G17 -> 409757.97 | AP17: =H17/AO17 -> 2.2637217
B18: 42111 | C18: 364959.14 | D18: 562110.91 | E18: 111.32 | F18: 154516.54 | G18: 2.68995 | H18: 927070.05 | I18: =H18-H14 -> 17993.64 | J18: =H18-H17 -> -507.94 | K18: =J18/H18 -> -0.00054789819 | L18: =I18/G18 -> 6689.2098 | M18: =L18+AK18 -> 8428.3498 | N18: =AK18-L18 -> -4950.0698 | O18: =I18/H18 -> 0.019409148 | P18: =(H18-H14)/H14 -> 0.01979332 | S18: =(C18-C14)/C14 -> 0.01179654 | U18: =(C18-C5)/C5 -> 0.029398861 | V18: =(C18-C17)/(H18-H17) -> 0.48889633 | W18: =(C18-C14)/(H18-H14) -> 0.23647578 | X18: =(D18-D14)/D14 -> 0.025053379 | Z18: =(D18-D5)/D5 -> 0.07065337 | AA18: =(D18-D17)/(H18-H17) -> 0.51112336 | AB18: =AVERAGE(AA6:AA18) -> 0.49560391 | AC18: =AVERAGE(V6:V18) -> 0.50439705 | AD18: =(D18-D14)/(H18-H14) -> 0.76352422 | AE18: =AVERAGE(H6:H18) -> 904777.76 | AF18: =(AE18-AE14)/AE14 -> 0.015991454 | AI18: =F18*G18 -> 415641.77 | AJ18: =(AI18-AI14)/AI14 -> 0.041630046 | AK18: =(F18-F14) -> 1739.14 | AL18: =F18-F17 -> 1001.5 | AM18: =AL18*G18 -> 2693.9849 | AN18: =AK18*G18 -> 4678.1996 | AO18: =(E18+F18)*G18 -> 415941.21 | AP18: =H18/AO18 -> 2.2288487
B19: 42118 | C19: 366458.27 | D19: 562780.71 | E19: 112.74 | F19: 154813.11 | G19: 2.697 | H19: 929238.98 | I19: =H19-H15 -> 11106.53 | J19: =H19-H18 -> 2168.93 | K19: =J19/H19 -> 0.0023340928 | L19: =I19/G19 -> 4118.1053 | M19: =L19+AK19 -> 5153.4253 | N19: =AK19-L19 -> -3082.7853 | O19: =I19/H19 -> 0.011952286 | P19: =(H19-H15)/H15 -> 0.012096871 | S19: =(C19-C15)/C15 -> 0.0093898823 | U19: =(C19-C6)/C6 -> 0.031549763 | V19: =(C19-C18)/(H19-H18) -> 0.69118413 | W19: =(C19-C15)/(H19-H15) -> 0.30693565 | X19: =(D19-D15)/D15 -> 0.013867363 | Z19: =(D19-D6)/D6 -> 0.077271167 | AA19: =(D19-D18)/(H19-H18) -> 0.30881587 | AB19: =AVERAGE(AA7:AA19) -> 0.41336639 | AC19: =AVERAGE(V7:V19) -> 0.58663457 | AD19: =(D19-D15)/(H19-H15) -> 0.69306435 | AE19: =AVERAGE(H7:H19) -> 908745.11 | AF19: =(AE19-AE15)/AE15 -> 0.017054743 | AI19: =F19*G19 -> 417530.96 | AJ19: =(AI19-AI15)/AI15 -> 0.04197505 | AK19: =(F19-F15) -> 1035.32 | AL19: =F19-F18 -> 296.57 | AM19: =AL19*G19 -> 799.84929 | AN19: =AK19*G19 -> 2792.258 | AO19: =(E19+F19)*G19 -> 417835.02 | AP19: =H19/AO19 -> 2.2239375
B20: 42124 | C20: 368651.21 | D20: 571315.65 | E20: 87.12 | F20: 156547.69 | G20: 2.6967 | H20: 939966.86 | I20: =H20-H16 -> 19306.44 | J20: =H20-H19 -> 10727.88 | K20: =J20/H20 -> 0.011413041 | L20: =I20/G20 -> 7159.2836 | M20: =L20+AK20 -> 9256.9736 | N20: =AK20-L20 -> -5061.5936 | O20: =I20/H20 -> 0.02053949 | P20: =(H20-H16)/H16 -> 0.020970207 | S20: =(C20-C16)/C16 -> 0.011034848 | U20: =(C20-C7)/C7 -> 0.029789665 | V20: =(C20-C19)/(H20-H19) -> 0.20441504 | W20: =(C20-C16)/(H20-H16) -> 0.20840766 | X20: =(D20-D16)/D16 -> 0.027485463 | Z20: =(D20-D7)/D7 -> 0.079227219 | AA20: =(D20-D19)/(H20-H19) -> 0.79558496 | AB20: =AVERAGE(AA8:AA20) -> 0.41934868 | AC20: =AVERAGE(V8:V20) -> 0.58065228 | AD20: =(D20-D16)/(H20-H16) -> 0.79159182 | AE20: =AVERAGE(H8:H20) -> 912791.67 | AF20: =(AE20-AE16)/AE16 -> 0.017605129 | AI20: =F20*G20 -> 422162.16 | AJ20: =(AI20-AI16)/AI16 -> 0.05790322 | AK20: =(F20-F16) -> 2097.69 | AL20: =F20-F19 -> 1734.58 | AM20: =AL20*G20 -> 4677.6419 | AN20: =AK20*G20 -> 5656.8406 | AO20: =(E20+F20)*G20 -> 422397.09 | AP20: =H20/AO20 -> 2.2253157
B21: 42132 | C21: 367716.63 | D21: 569360.02 | E21: 114.67 | F21: 157230.04 | G21: 2.66766 | H21: 937076.65 | I21: =H21-H17 -> 9498.66 | J21: =H21-H20 -> -2890.21 | K21: =J21/H21 -> -0.0030842834 | L21: =I21/G21 -> 3560.6711 | M21: =L21+AK21 -> 7275.6711 | N21: =AK21-L21 -> 154.32885 | O21: =I21/H21 -> 0.010136481 | P21: =(H21-H17)/H17 -> 0.010240282 | S21: =(C21-C17)/C17 -> 0.0068705057 | U21: =(C21-C8)/C8 -> 0.025877274 | V21: =(C21-C20)/(H21-H20) -> 0.32336059 | W21: =(C21-C17)/(H21-H17) -> 0.26415937 | X21: =(D21-D17)/D17 -> 0.012428621 | Z21: =(D21-D8)/D8 -> 0.075684234 | AA21: =(D21-D20)/(H21-H20) -> 0.67663941 | AB21: =AVERAGE(AA9:AA21) -> 0.4864718 | AC21: =AVERAGE(V9:V21) -> 0.51352915 | AD21: =(D21-D17)/(H21-H17) -> 0.73583958 | AE21: =AVERAGE(H9:H21) -> 916586.68 | AF21: =(AE21-AE17)/AE17 -> 0.017160908 | AI21: =F21*G21 -> 419436.29 | AJ21: =(AI21-AI17)/AI17 -> 0.024330137 | AK21: =(F21-F17) -> 3715 | AL21: =F21-F20 -> 682.35 | AM21: =AL21*G21 -> 1820.2778 | AN21: =AK21*G21 -> 9910.3569 | AO21: =(E21+F21)*G21 -> 419742.19 | AP21: =H21/AO21 -> 2.2325053
B22: 42139 | C22: 368631.8 | D22: 575535.31 | E22: 123.33 | F22: 158520.25 | G22: 2.583475 | H22: 944167.11 | I22: =H22-H18 -> 17097.06 | J22: =H22-H21 -> 7090.46 | K22: =J22/H22 -> 0.0075097511 | L22: =I22/G22 -> 6617.8539 | M22: =L22+AK22 -> 10621.564 | N22: =AK22-L22 -> -2614.1439 | O22: =I22/H22 -> 0.018108087 | P22: =(H22-H18)/H18 -> 0.018442037 | S22: =(C22-C18)/C18 -> 0.010063209 | U22: =(C22-C9)/C9 -> 0.022733834 | V22: =(C22-C21)/(H22-H21) -> 0.12907061 | W22: =(C22-C18)/(H22-H18) -> 0.21481237 | X22: =(D22-D18)/D18 -> 0.02388212 | Z22: =(D22-D9)/D9 -> 0.076318935 | AA22: =(D22-D21)/(H22-H21) -> 0.87092939 | AB22: =AVERAGE(AA10:AA22) -> 0.49723615 | AC22: =AVERAGE(V10:V22) -> 0.5027648 | AD22: =(D22-D18)/(H22-H18) -> 0.78518763 | AE22: =AVERAGE(H10:H22) -> 920356.2 | AF22: =(AE22-AE18)/AE18 -> 0.017217975 | AI22: =F22*G22 -> 409533.1 | AJ22: =(AI22-AI18)/AI18 -> -0.014696944 | AK22: =(F22-F18) -> 4003.71 | AL22: =F22-F21 -> 1290.21 | AM22: =AL22*G22 -> 3333.2253 | AN22: =AK22*G22 -> 10343.485 | AO22: =(E22+F22)*G22 -> 409851.72 | AP22: =H22/AO22 -> 2.3036797
B23: 42146 | C23: 368421.26 | D23: 573818.35 | E23: 125.9 | F23: 156932.08 | G23: 2.62418 | H23: 942239.6 | I23: =H23-H19 -> 13000.62 | J23: =H23-H22 -> -1927.51 | K23: =J23/H23 -> -0.0020456686 | L23: =I23/G23 -> 4954.1647 | M23: =L23+AK23 -> 7073.1347 | N23: =AK23-L23 -> -2835.1947 | O23: =I23/H23 -> 0.013797573 | P23: =(H23-H19)/H19 -> 0.01399061 | S23: =(C23-C19)/C19 -> 0.0053566536 | U23: =(C23-C10)/C10 -> 0.027673878 | V23: =(C23-C22)/(H23-H22) -> 0.10922901 | W23: =(C23-C19)/(H23-H19) -> 0.15099203 | X23: =(D23-D19)/D19 -> 0.019612684 | Z23: =(D23-D10)/D10 -> 0.070032926 | AA23: =(D23-D22)/(H23-H22) -> 0.89076581 | AB23: =AVERAGE(AA11:AA23) -> 0.86069525 | AC23: =AVERAGE(V11:V23) -> 0.13930531 | AD23: =(D23-D19)/(H23-H19) -> 0.84900874 | AE23: =AVERAGE(H11:H23) -> 924008.29 | AF23: =(AE23-AE19)/AE19 -> 0.016795883 | AI23: =F23*G23 -> 411818.03 | AJ23: =(AI23-AI19)/AI19 -> -0.013682655 | AK23: =(F23-F19) -> 2118.97 | AL23: =F23-F22 -> -1588.17 | AM23: =AL23*G23 -> -4167.644 | AN23: =AK23*G23 -> 5560.5587 | AO23: =(E23+F23)*G23 -> 412148.41 | AP23: =H23/AO23 -> 2.2861658
B24: 42153 | C24: 371193.9 | D24: 580525.3 | E24: 118.52 | F24: 157331.55 | G24: 2.6775 | H24: 951719.21 | I24: =H24-H20 -> 11752.35 | J24: =H24-H23 -> 9479.61 | K24: =J24/H24 -> 0.0099605114 | L24: =I24/G24 -> 4389.2997 | M24: =L24+AK24 -> 5173.1597 | N24: =AK24-L24 -> -3605.4397 | O24: =I24/H24 -> 0.012348548 | P24: =(H24-H20)/H20 -> 0.012502941 | S24: =(C24-C20)/C20 -> 0.0068972783 | U24: =(C24-C11)/C11 -> 0.03202204 | V24: =(C24-C23)/(H24-H23) -> 0.29248461 | W24: =(C24-C20)/(H24-H20) -> 0.21635588 | X24: =(D24-D20)/D20 -> 0.016120073 | Z24: =(D24-D11)/D11 -> 0.067108493 | AA24: =(D24-D23)/(H24-H23) -> 0.70751328 | AB24: =AVERAGE(AA12:AA24) -> 0.84832656 | AC24: =AVERAGE(V12:V24) -> 0.15167375 | AD24: =(D24-D20)/(H24-H20) -> 0.78364327 | AE24: =AVERAGE(H12:H24) -> 927702.58 | AF24: =(AE24-AE20)/AE20 -> 0.016335504 | AI24: =F24*G24 -> 421255.23 | AJ24: =(AI24-AI20)/AI20 -> -0.0021482989 | AK24: =(F24-F20) -> 783.86 | AL24: =F24-F23 -> 399.47 | AM24: =AL24*G24 -> 1069.5809 | AN24: =AK24*G24 -> 2098.7851 | AO24: =(E24+F24)*G24 -> 421572.56 | AP24: =H24/AO24 -> 2.2575454
B25: 42160 | C25: 371861.58 | D25: 583673.14 | E25: 115.05 | F25: 158899.26 | G25: 2.73102 | H25: 955534.73 | I25: =H25-H21 -> 18458.08 | J25: =H25-H24 -> 3815.52 | K25: =J25/H25 -> 0.0039930731 | L25: =I25/G25 -> 6758.6762 | M25: =L25+AK25 -> 8427.8962 | N25: =AK25-L25 -> -5089.4562 | O25: =I25/H25 -> 0.019317016 | P25: =(H25-H21)/H21 -> 0.019697514 | S25: =(C25-C21)/C21 -> 0.011272131 | U25: =(C25-C12)/C12 -> 0.03264753 | V25: =(C25-C24)/(H25-H24) -> 0.17499056 | W25: =(C25-C21)/(H25-H21) -> 0.22456019 | X25: =(D25-D21)/D21 -> 0.025138962 | Z25: =(D25-D12)/D12 -> 0.072142768 | AA25: =(D25-D24)/(H25-H24) -> 0.82500944 | AB25: =AVERAGE(AA13:AA25) -> 0.87556482 | AC25: =AVERAGE(V13:V25) -> 0.12443644 | AD25: =(D25-D21)/(H25-H21) -> 0.77543927 | AE25: =AVERAGE(H13:H25) -> 931628.04 | AF25: =(AE25-AE21)/AE21 -> 0.016410187 | AI25: =F25*G25 -> 433957.06 | AJ25: =(AI25-AI21)/AI21 -> 0.034619724 | AK25: =(F25-F21) -> 1669.22 | AL25: =F25-F24 -> 1567.71 | AM25: =AL25*G25 -> 4281.4474 | AN25: =AK25*G25 -> 4558.6732 | AO25: =(E25+F25)*G25 -> 434271.26 | AP25: =H25/AO25 -> 2.2003177
B26: 42167 | C26: 373956.61 | D26: 586155.32 | E26: 116.66 | F26: 159983.72 | G26: 2.72662 | H26: 960111.93 | I26: =H26-H22 -> 15944.82 | J26: =H26-H25 -> 4577.2 | K26: =J26/H26 -> 0.0047673608 | L26: =I26/G26 -> 5847.8336 | M26: =L26+AK26 -> 7311.3036 | N26: =AK26-L26 -> -4384.3636 | O26: =I26/H26 -> 0.016607251 | P26: =(H26-H22)/H22 -> 0.01688771 | S26: =(C26-C22)/C22 -> 0.014444793 | U26: =(C26-C13)/C13 -> 0.034507512 | V26: =(C26-C25)/(H26-H25) -> 0.45770995 | W26: =(C26-C22)/(H26-H22) -> 0.33395234 | X26: =(D26-D22)/D22 -> 0.018452404 | Z26: =(D26-D13)/D13 -> 0.071148583 | AA26: =(D26-D25)/(H26-H25) -> 0.54229223 | AB26: =AVERAGE(AA14:AA26) -> 0.86558739 | AC26: =AVERAGE(V14:V26) -> 0.13441403 | AD26: =(D26-D22)/(H26-H22) -> 0.66604766 | AE26: =AVERAGE(H14:H26) -> 935582.49 | AF26: =(AE26-AE22)/AE22 -> 0.016543906 | AI26: =F26*G26 -> 436214.81 | AJ26: =(AI26-AI22)/AI22 -> 0.065151529 | AK26: =(F26-F22) -> 1463.47 | AL26: =F26-F25 -> 1084.46 | AM26: =AL26*G26 -> 2956.9103 | AN26: =AK26*G26 -> 3990.3266 | AO26: =(E26+F26)*G26 -> 436532.9 | AP26: =H26/AO26 -> 2.1994034
... B31: 42201 | C31: 373498.12 | D31: 593577.12 | E31: 132.5 | F31: 158875.66 | G31: 2.68472 | H31: 967075.25 | I31: =H31-H27 -> 8249.26 | J31: =H31-H30 -> -3331 | K31: =J31/H31 -> -0.0034444062 | L31: =I31/G31 -> 3072.6705 | M31: =L31+AK31 -> 1408.4805 | N31: =AK31-L31 -> -4736.8605 | O31: =I31/H31 -> 0.0085301118 | P31: =(H31-H27)/H27 -> 0.0086035006 | S31: =(C31-C27)/C27 -> 0.0030701082 | U31: =(C31-C18)/C18 -> 0.023397085 | V31: =(C31-C30)/(H31-H30) -> 0.32897328 | W31: =(C31-C27)/(H31-H27) -> 0.13857849 | X31: =(D31-D27)/D27 -> 0.012116677 | Z31: =(D31-D18)/D18 -> 0.05597865 | AA31: =(D31-D30)/(H31-H30) -> 0.67102972 | AB31: =AVERAGE(AA19:AA31) -> 0.74087222 | AC31: =AVERAGE(V19:V31) -> 0.25912762 | AD31: =(D31-D27)/(H31-H27) -> 0.8614203 | AE31: =AVERAGE(H19:H31) -> 953250.99 | AF31: =(AE31-AE27)/AE27 -> 0.014734375 | AI31: =F31*G31 -> 426536.66 | AJ31: =(AI31-AI27)/AI27 -> -0.008978267 | AK31: =(F31-F27) -> -1664.19 | AL31: =F31-F30 -> -571.69 | AM31: =AL31*G31 -> -1534.8276 | AN31: =AK31*G31 -> -4467.8842 | AO31: =(E31+F31)*G31 -> 426892.39 | AP31: =H31/AO31 -> 2.2653842
B32: 42209 | C32: 373731.08 | D32: 594570.59 | E32: 130.57 | F32: 159434.96 | G32: 2.75736 | H32: 968301.67 | I32: =H32-H28 -> -260.96 | J32: =H32-H31 -> 1226.42 | K32: =J32/H32 -> 0.0012665681 | L32: =I32/G32 -> -94.641251 | M32: =L32+AK32 -> -330.31125 | N32: =AK32-L32 -> -141.02875 | O32: =I32/H32 -> -0.00026950279 | P32: =(H32-H28)/H28 -> -0.00026943018 | S32: =(C32-C28)/C28 -> 0.00079231952 | U32: =(C32-C19)/C19 -> 0.019846216 | V32: =(C32-C31)/(H32-H31) -> 0.18995124 | W32: =(C32-C28)/(H32-H28) -> -1.1338136 | X32: =(D32-D28)/D28 -> -0.00093566516 | Z32: =(D32-D19)/D19 -> 0.056487153 | AA32: =(D32-D31)/(H32-H31) -> 0.81005691 | AB32: =AVERAGE(AA20:AA32) -> 0.77942923 | AC32: =AVERAGE(V20:V32) -> 0.22057124 | AE32: =AVERAGE(H20:H32) -> 956255.81 | AF32: =(AE32-AE28)/AE28 -> 0.013746787 | AI32: =F32*G32 -> 439619.58 | AJ32: =(AI32-AI28)/AI28 -> 0.027002202 | AK32: =(F32-F28) -> -235.67 | AL32: =F32-F31 -> 559.3 | AM32: =AL32*G32 -> 1542.1914 | AN32: =AK32*G32 -> -649.82703 | AO32: =(E32+F32)*G32 -> 439979.61 | AP32: =H32/AO32 -> 2.2007876
B33: 42216 | C33: 376911.5 | D33: 610337.21 | E33: 125.81 | F33: 160179.66 | G33: 2.7788 | H33: 987248.72 | I33: =H33-H29 -> 19911.01 | J33: =H33-H32 -> 18947.05 | K33: =J33/H33 -> 0.01919177 | L33: =I33/G33 -> 7165.3268 | M33: =L33+AK33 -> 7795.1268 | N33: =AK33-L33 -> -6535.5268 | O33: =I33/H33 -> 0.02016818 | P33: =(H33-H29)/H29 -> 0.020583308 | S33: =(C33-C29)/C29 -> 0.0067674397 | U33: =(C33-C20)/C20 -> 0.022406789 | V33: =(C33-C32)/(H33-H32) -> 0.16785832 | W33: =(C33-C29)/(H33-H29) -> 0.12724518 | X33: =(D33-D29)/D29 -> 0.029306237 | Z33: =(D33-D20)/D20 -> 0.068301227 | AA33: =(D33-D32)/(H33-H32) -> 0.83214115 | AB33: =AVERAGE(AA21:AA33) -> 0.78224124 | AC33: =AVERAGE(V21:V33) -> 0.21775918 | AD33: =(D33-D29)/(H33-H29) -> 0.87275432 | AE33: =AVERAGE(H21:H33) -> 959892.88 | AF33: =(AE33-AE29)/AE29 -> 0.013743773 | AI33: =F33*G33 -> 445107.24 | AJ33: =(AI33-AI29)/AI29 -> 0.039314261 | AK33: =(F33-F29) -> 629.8 | AL33: =F33-F32 -> 744.7 | AM33: =AL33*G33 -> 2069.3724 | AN33: =AK33*G33 -> 1750.0882 | AO33: =(E33+F33)*G33 -> 445456.84 | AP33: =H33/AO33 -> 2.2162612
B34: 42223 | C34: 377071.75 | D34: 598120.98 | E34: 123.26 | F34: 159482.79 | G34: 2.77856 | H34: 975192.73 | I34: =H34-H30 -> 4786.48 | J34: =H34-H33 -> -12055.99 | K34: =J34/H34 -> -0.012362674 | L34: =I34/G34 -> 1722.6477 | M34: =L34+AK34 -> 1758.0877 | N34: =AK34-L34 -> -1687.2077 | O34: =I34/H34 -> 0.00490824 | P34: =(H34-H30)/H30 -> 0.0049324497 | S34: =(C34-C30)/C30 -> 0.0066146827 | U34: =(C34-C21)/C21 -> 0.025441112 | V34: =(C34-C33)/(H34-H33) -> -0.013292148 | W34: =(C34-C30)/(H34-H30) -> 0.51767061 | X34: =(D34-D30)/D30 -> 0.0038748108 | Z34: =(D34-D21)/D21 -> 0.050514541 | AA34: =(D34-D33)/(H34-H33) -> 1.0132913 | AB34: =AVERAGE(AA22:AA34) -> 0.80813754 | AC34: =AVERAGE(V22:V34) -> 0.19186282 | AD34: =(D34-D30)/(H34-H30) -> 0.48232939 | AE34: =AVERAGE(H22:H34) -> 962824.89 | AF34: =(AE34-AE30)/AE30 -> 0.013314637 | AI34: =F34*G34 -> 443132.5 | AJ34: =(AI34-AI30)/AI30 -> 0.049716751 | AK34: =(F34-F30) -> 35.44 | AL34: =F34-F33 -> -696.87 | AM34: =AL34*G34 -> -1936.2951 | AN34: =AK34*G34 -> 98.472166 | AO34: =(E34+F34)*G34 -> 443474.99 | AP34: =H34/AO34 -> 2.1989802
B35: 42230 | C35: 379067.42 | D35: 598582.7 | E35: 125.73 | F35: 161339.97 | G35: 2.88432 | H35: 977650.12 | I35: =H35-H31 -> 10574.87 | J35: =H35-H34 -> 2457.39 | K35: =J35/H35 -> 0.0025135679 | L35: =I35/G35 -> 3666.3304 | M35: =L35+AK35 -> 6130.6404 | N35: =AK35-L35 -> -1202.0204 | O35: =I35/H35 -> 0.01081662 | P35: =(H35-H31)/H31 -> 0.010934899 | S35: =(C35-C31)/C31 -> 0.014911186 | U35: =(C35-C22)/C22 -> 0.028309061 | V35: =(C35-C34)/(H35-H34) -> 0.8121096 | W35: =(C35-C31)/(H35-H31) -> 0.52665423 | X35: =(D35-D31)/D31 -> 0.0084329059 | Z35: =(D35-D22)/D22 -> 0.040045136 | AA35: =(D35-D34)/(H35-H34) -> 0.1878904 | AB35: =AVERAGE(AA23:AA35) -> 0.75559608 | AC35: =AVERAGE(V23:V35) -> 0.24440428 | AD35: =(D35-D31)/(H35-H31) -> 0.47334672 | AE35: =AVERAGE(H23:H35) -> 965400.5 | AF35: =(AE35-AE31)/AE31 -> 0.012745343 | AI35: =F35*G35 -> 465356.1 | AJ35: =(AI35-AI31)/AI31 -> 0.091010794 | AK35: =(F35-F31) -> 2464.31 | AL35: =F35-F34 -> 1857.18 | AM35: =AL35*G35 -> 5356.7014 | AN35: =AK35*G35 -> 7107.8586 | AO35: =(E35+F35)*G35 -> 465718.75 | AP35: =H35/AO35 -> 2.0992286
B36: 42237 | C36: 376837.79 | D36: 602017.84 | E36: 127.18 | F36: 161619.02 | G36: 2.92674 | H36: 978855.62 | I36: =H36-H32 -> 10553.95 | J36: =H36-H35 -> 1205.5 | K36: =J36/H36 -> 0.0012315402 | L36: =I36/G36 -> 3606.0429 | M36: =L36+AK36 -> 5790.1029 | N36: =AK36-L36 -> -1421.9829 | O36: =I36/H36 -> 0.010781927 | P36: =(H36-H32)/H32 -> 0.010899444 | S36: =(C36-C32)/C32 -> 0.0083126884 | U36: =(C36-C23)/C23 -> 0.022844854 | V36: =(C36-C35)/(H36-H35) -> -1.8495479 | W36: =(C36-C32)/(H36-H32) -> 0.29436467 | X36: =(D36-D32)/D32 -> 0.012525426 | Z36: =(D36-D23)/D23 -> 0.049143584 | AA36: =(D36-D35)/(H36-H35) -> 2.8495562 | AB36: =AVERAGE(AA24:AA36) -> 0.90627226 | AC36: =AVERAGE(V24:V36) -> 0.093729134 | AD36: =(D36-D32)/(H36-H32) -> 0.70563628 | AE36: =AVERAGE(H24:H36) -> 968217.12 | AF36: =(AE36-AE32)/AE32 -> 0.012508479 | AI36: =F36*G36 -> 473016.85 | AJ36: =(AI36-AI32)/AI32 -> 0.075968566 | AK36: =(F36-F32) -> 2184.06 | AL36: =F36-F35 -> 279.05 | AM36: =AL36*G36 -> 816.7068 | AN36: =AK36*G36 -> 6392.1758 | AO36: =(E36+F36)*G36 -> 473389.07 | AP36: =H36/AO36 -> 2.0677613
B37: 42244 | C37: 378981.04 | D37: 605942.58 | E37: 124.01 | F37: 161657.42 | G37: 2.92866 | H37: 984923.62 | I37: =H37-H33 -> -2325.1 | J37: =H37-H36 -> 6068 | K37: =J37/H37 -> 0.0061608838 | L37: =I37/G37 -> -793.91257 | M37: =L37+AK37 -> 683.84743 | N37: =AK37-L37 -> 2271.6726 | O37: =I37/H37 -> -0.0023606907 | P37: =(H37-H33)/H33 -> -0.0023551309 | S37: =(C37-C33)/C33 -> 0.005490785 | U37: =(C37-C24)/C24 -> 0.020978631 | V37: =(C37-C36)/(H37-H36) -> 0.35320534 | W37: =(C37-C33)/(H37-H33) -> -0.89008645 | X37: =(D37-D33)/D33 -> -0.0072003311 | Z37: =(D37-D24)/D24 -> 0.043783243 | AA37: =(D37-D36)/(H37-H36) -> 0.64679301 | AB37: =AVERAGE(AA25:AA37) -> 0.90160147 | AC37: =AVERAGE(V25:V37) -> 0.098399959 | AE37: =AVERAGE(H25:H37) -> 970771.31 | AF37: =(AE37-AE33)/AE33 -> 0.011332957 | AI37: =F37*G37 -> 473439.62 | AJ37: =(AI37-AI33)/AI33 -> 0.063652931 | AK37: =(F37-F33) -> 1477.76 | AL37: =F37-F36 -> 38.4 | AM37: =AL37*G37 -> 112.46054 | AN37: =AK37*G37 -> 4327.8566 | AO37: =(E37+F37)*G37 -> 473802.8 | AP37: =H37/AO37 -> 2.0787628
B38: 42251 | C38: 379709.88 | D38: 604092.95 | E38: 115.25 | F38: 161015.85 | G38: 3.0129 | H38: 983802.83 | I38: =H38-H34 -> 8610.1 | J38: =H38-H37 -> -1120.79 | K38: =J38/H38 -> -0.0011392425 | L38: =I38/G38 -> 2857.745 | M38: =L38+AK38 -> 4390.805 | N38: =AK38-L38 -> -1324.685 | O38: =I38/H38 -> 0.0087518553 | P38: =(H38-H34)/H34 -> 0.0088291265 | S38: =(C38-C34)/C34 -> 0.0069963608 | U38: =(C38-C25)/C25 -> 0.021105434 | V38: =(C38-C37)/(H38-H37) -> -0.65029131 | W38: =(C38-C34)/(H38-H34) -> 0.30639946 | X38: =(D38-D34)/D34 -> 0.009984552 | Z38: =(D38-D25)/D25 -> 0.034985009 | AA38: =(D38-D37)/(H38-H37) -> 1.6502913 | AB38: =AVERAGE(AA26:AA38) -> 0.9650847 | AC38: =AVERAGE(V26:V38) -> 0.034916738 | AD38: =(D38-D34)/(H38-H34) -> 0.69360054 | AE38: =AVERAGE(H26:H38) -> 972945.77 | AF38: =(AE38-AE34)/AE34 -> 0.01051166 | AI38: =F38*G38 -> 485124.65 | AJ38: =(AI38-AI34)/AI34 -> 0.094762071 | AK38: =(F38-F34) -> 1533.06 | AL38: =F38-F37 -> -641.57 | AM38: =AL38*G38 -> -1932.9863 | AN38: =AK38*G38 -> 4618.9565 | AO38: =(E38+F38)*G38 -> 485471.89 | AP38: =H38/AO38 -> 2.0264877
B39: 42258 | C39: 380819.97 | D39: 607734.19 | E39: 117.67 | F39: 162172.39 | G39: 3.03274 | H39: 988554.16 | I39: =H39-H35 -> 10904.04 | J39: =H39-H38 -> 4751.33 | K39: =J39/H39 -> 0.0048063426 | L39: =I39/G39 -> 3595.4417 | M39: =L39+AK39 -> 4427.8617 | N39: =AK39-L39 -> -2763.0217 | O39: =I39/H39 -> 0.011030291 | P39: =(H39-H35)/H35 -> 0.011153315 | S39: =(C39-C35)/C35 -> 0.00462332 | U39: =(C39-C26)/C26 -> 0.018353359 | V39: =(C39-C38)/(H39-H38) -> 0.23363774 | W39: =(C39-C35)/(H39-H35) -> 0.16072483 | X39: =(D39-D35)/D35 -> 0.015288598 | Z39: =(D39-D26)/D26 -> 0.036814253 | AA39: =(D39-D38)/(H39-H38) -> 0.76636226 | AB39: =AVERAGE(AA27:AA39) -> 0.98232085 | AC39: =AVERAGE(V27:V39) -> 0.017680414 | AD39: =(D39-D35)/(H39-H35) -> 0.83927517 | AE39: =AVERAGE(H27:H39) -> 975133.64 | AF39: =(AE39-AE35)/AE35 -> 0.010081966 | AI39: =F39*G39 -> 491826.69 | AJ39: =(AI39-AI35)/AI35 -> 0.056882443 | AK39: =(F39-F35) -> 832.42 | AL39: =F39-F38 -> 1156.54 | AM39: =AL39*G39 -> 3507.4851 | AN39: =AK39*G39 -> 2524.5134 | AO39: =(E39+F39)*G39 -> 492183.56 | AP39: =H39/AO39 -> 2.0085071
B40: 42265 | C40: 379763.68 | D40: 608452.36 | E40: 122.98 | F40: 163079.98 | G40: 3.0002667 | H40: 988216.04 | I40: =H40-H36 -> 9360.42 | J40: =H40-H39 -> -338.12 | K40: =J40/H40 -> -0.0003421519 | L40: =I40/G40 -> 3119.8627 | M40: =L40+AK40 -> 4580.8227 | N40: =AK40-L40 -> -1658.9027 | O40: =I40/H40 -> 0.0094720381 | P40: =(H40-H36)/H36 -> 0.0095626156 | S40: =(C40-C36)/C36 -> 0.0077643222 | U40: =(C40-C27)/C27 -> 0.019896956 | V40: =(C40-C39)/(H40-H39) -> 3.1240092 | W40: =(C40-C36)/(H40-H36) -> 0.31258106 | X40: =(D40-D36)/D36 -> 0.010688255 | Z40: =(D40-D27)/D27 -> 0.037480657 | AA40: =(D40-D39)/(H40-H39) -> -2.1240092 | AB40: =AVERAGE(AA28:AA40) -> 0.83782144 | AC40: =AVERAGE(V28:V40) -> 0.16217982 | AD40: =(D40-D36)/(H40-H36) -> 0.68741787 | AE40: =AVERAGE(H28:H40) -> 977394.41 | AF40: =(AE40-AE36)/AE36 -> 0.0094785471 | AI40: =F40*G40 -> 489283.43 | AJ40: =(AI40-AI36)/AI36 -> 0.034389002 | AK40: =(F40-F36) -> 1460.96 | AL40: =F40-F39 -> 907.59 | AM40: =AL40*G40 -> 2723.012 | AN40: =AK40*G40 -> 4383.2696 | AO40: =(E40+F40)*G40 -> 489652.4 | AP40: =H40/AO40 -> 2.0181991
B41: 42270 | C41: 380412.19 | D41: 605032.28 | E41: 120.16 | F41: 161442.49 | G41: 3.02782 | H41: 985444.47 | I41: =H41-H37 -> 520.85 | J41: =H41-H40 -> -2771.57 | K41: =J41/H41 -> -0.0028125075 | L41: =I41/G41 -> 172.02145 | M41: =L41+AK41 -> -42.908546 | N41: =AK41-L41 -> -386.95145 | O41: =I41/H41 -> 0.00052854323 | P41: =(H41-H37)/H37 -> 0.00052882273 | S41: =(C41-C37)/C37 -> 0.0037763103 | U41: =(C41-C28)/C28 -> 0.018683268 | V41: =(C41-C40)/(H41-H40) -> -0.23398651 | W41: =(C41-C37)/(H41-H37) -> 2.7477201 | X41: =(D41-D37)/D37 -> -0.0015022876 | Z41: =(D41-D28)/D28 -> 0.016643242 | AA41: =(D41-D40)/(H41-H40) -> 1.2339865 | AB41: =AVERAGE(AA29:AA41) -> 0.86435478 | AC41: =AVERAGE(V29:V41) -> 0.13564648 | AE41: =AVERAGE(H29:H41) -> 978693.01 | AF41: =(AE41-AE37)/AE37 -> 0.0081602219 | AI41: =F41*G41 -> 488818.8 | AJ41: =(AI41-AI37)/AI37 -> 0.032483932 | AK41: =(F41-F37) -> -214.93 | AL41: =F41-F40 -> -1637.49 | AM41: =AL41*G41 -> -4958.025 | AN41: =AK41*G41 -> -650.76935 | AO41: =(E41+F41)*G41 -> 489182.62 | AP41: =H41/AO41 -> 2.0144715
B42: 42279 | C42: 379922.49 | D42: 606649.93 | E42: 123.22 | F42: 161416.21 | G42: 2.97552 | H42: 986572.42 | I42: =H42-H38 -> 2769.59 | J42: =H42-H41 -> 1127.95 | K42: =J42/H42 -> 0.0011433018 | L42: =I42/G42 -> 930.79193 | M42: =L42+AK42 -> 1331.1519 | N42: =AK42-L42 -> -530.43193 | O42: =I42/H42 -> 0.002807285 | P42: =(H42-H38)/H38 -> 0.0028151881 | S42: =(C42-C38)/C38 -> 0.00055992749 | U42: =(C42-C29)/C29 -> 0.014810088 | V42: =(C42-C41)/(H42-H41) -> -0.43415045 | W42: =(C42-C38)/(H42-H38) -> 0.076765875 | X42: =(D42-D38)/D38 -> 0.0042327592 | Z42: =(D42-D29)/D29 -> 0.023087805 | AA42: =(D42-D41)/(H42-H41) -> 1.4341504 | AB42: =AVERAGE(AA30:AA42) -> 0.83854961 | AC42: =AVERAGE(V30:V42) -> 0.16145165 | AD42: =(D42-D38)/(H42-H38) -> 0.92323412 | AE42: =AVERAGE(H30:H42) -> 980172.61 | AF42: =(AE42-AE38)/AE38 -> 0.0074277861 | AI42: =F42*G42 -> 480297.16 | AJ42: =(AI42-AI38)/AI38 -> -0.0099510368 | AK42: =(F42-F38) -> 400.36 | AL42: =F42-F41 -> -26.28 | AM42: =AL42*G42 -> -78.196666 | AN42: =AK42*G42 -> 1191.2792 | AO42: =(E42+F42)*G42 -> 480663.8 | AP42: =H42/AO42 -> 2.0525207
B43: 42286 | C43: 379654.73 | D43: 608764.87 | E43: 120.85 | F43: 162332.3 | G43: 2.9174 | H43: 988419.6 | I43: =H43-H39 -> -134.56 | J43: =H43-H42 -> 1847.18 | K43: =J43/H43 -> 0.0018688217 | L43: =I43/G43 -> -46.12326 | M43: =L43+AK43 -> 113.78674 | N43: =AK43-L43 -> 206.03326 | O43: =I43/H43 -> -0.00013613652 | P43: =(H43-H39)/H39 -> -0.00013611798 | S43: =(C43-C39)/C39 -> -0.0030598185 | U43: =(C43-C30)/C30 -> 0.013510096 | V43: =(C43-C42)/(H43-H42) -> -0.1449561 | W43: =(C43-C39)/(H43-H39) -> 8.6596314 | X43: =(D43-D39)/D39 -> 0.0016959388 | Z43: =(D43-D30)/D30 -> 0.021739312 | AA43: =(D43-D42)/(H43-H42) -> 1.1449561 | AB43: =AVERAGE(AA31:AA43) -> 0.85511509 | AC43: =AVERAGE(V31:V43) -> 0.14488618 | AE43: =AVERAGE(H31:H43) -> 981558.25 | AF43: =(AE43-AE39)/AE39 -> 0.0065884421 | AI43: =F43*G43 -> 473588.25 | AJ43: =(AI43-AI39)/AI39 -> -0.037083067 | AK43: =(F43-F39) -> 159.91 | AL43: =F43-F42 -> 916.09 | AM43: =AL43*G43 -> 2672.601 | AN43: =AK43*G43 -> 466.52143 | AO43: =(E43+F43)*G43 -> 473940.82 | AP43: =H43/AO43 -> 2.0855338
B44: 42293 | C44: 378051.75 | D44: 611387.47 | E44: 124.87 | F44: 162855.9 | G44: 2.89356 | H44: 989439.22 | I44: =H44-H40 -> 1223.18 | J44: =H44-H43 -> 1019.62 | K44: =J44/H44 -> 0.0010305029 | L44: =I44/G44 -> 422.72495 | M44: =L44+AK44 -> 198.64495 | N44: =AK44-L44 -> -646.80495 | O44: =I44/H44 -> 0.0012362356 | P44: =(H44-H40)/H40 -> 0.0012377658 | S44: =(C44-C40)/C40 -> -0.0045078824 | U44: =(C44-C31)/C31 -> 0.012191842 | V44: =(C44-C43)/(H44-H43) -> -1.5721347 | W44: =(C44-C40)/(H44-H40) -> -1.3995732 | X44: =(D44-D40)/D40 -> 0.0048238945 | Z44: =(D44-D31)/D31 -> 0.030005115 | AA44: =(D44-D43)/(H44-H43) -> 2.5721347 | AB44: =AVERAGE(AA32:AA44) -> 1.0013539 | AC44: =AVERAGE(V32:V44) -> -0.0013528982 | AE44: =AVERAGE(H32:H44) -> 983278.56 | AF44: =(AE44-AE40)/AE40 -> 0.0060202348 | AI44: =F44*G44 -> 471233.32 | AJ44: =(AI44-AI40)/AI40 -> -0.036890908 | AK44: =(F44-F40) -> -224.08 | AL44: =F44-F43 -> 523.6 | AM44: =AL44*G44 -> 1515.068 | AN44: =AK44*G44 -> -648.38892 | AO44: =(E44+F44)*G44 -> 471594.64 | AP44: =H44/AO44 -> 2.0980714
B45: 42300 | C45: 378114.13 | D45: 610355.69 | E45: 124.9 | F45: 161837.5 | G45: 2.88655 | H45: 988469.82 | I45: =H45-H41 -> 3025.35 | J45: =H45-H44 -> -969.4 | K45: =J45/H45 -> -0.00098070774 | L45: =I45/G45 -> 1048.0851 | M45: =L45+AK45 -> 1443.0951 | N45: =AK45-L45 -> -653.07508 | O45: =I45/H45 -> 0.0030606397 | P45: =(H45-H41)/H41 -> 0.003070036 | S45: =(C45-C41)/C41 -> -0.0060409736 | U45: =(C45-C32)/C32 -> 0.011727818 | V45: =(C45-C44)/(H45-H44) -> -0.064349082 | W45: =(C45-C41)/(H45-H41) -> -0.75960137 | X45: =(D45-D41)/D41 -> 0.0087985553 | Z45: =(D45-D32)/D32 -> 0.02654874 | AA45: =(D45-D44)/(H45-H44) -> 1.0643491 | AB45: =AVERAGE(AA33:AA45) -> 1.0209149 | AC45: =AVERAGE(V33:V45) -> -0.020914461 | AE45: =AVERAGE(H33:H45) -> 984829.95 | AF45: =(AE45-AE41)/AE41 -> 0.0062705433 | AI45: =F45*G45 -> 467152.04 | AJ45: =(AI45-AI41)/AI41 -> -0.044324736 | AK45: =(F45-F41) -> 395.01 | AL45: =F45-F44 -> -1018.4 | AM45: =AL45*G45 -> -2939.6625 | AN45: =AK45*G45 -> 1140.2161 | AO45: =(E45+F45)*G45 -> 467512.57 | AP45: =H45/AO45 -> 2.1143171
B46: 42307 | C46: 379736.29 | D46: 615928.08 | E46: 91.28 | F46: 161970.11 | G46: 2.8502 | H46: 995664.37 | I46: =H46-H42 -> 9091.95 | J46: =H46-H45 -> 7194.55 | K46: =J46/H46 -> 0.0072258787 | L46: =I46/G46 -> 3189.934 | M46: =L46+AK46 -> 3743.834 | N46: =AK46-L46 -> -2636.034 | O46: =I46/H46 -> 0.009131541 | P46: =(H46-H42)/H42 -> 0.0092156945 | S46: =(C46-C42)/C42 -> -0.00049009997 | U46: =(C46-C33)/C33 -> 0.007494571 | V46: =(C46-C45)/(H46-H45) -> 0.22547067 | W46: =(C46-C42)/(H46-H42) -> -0.020479655 | X46: =(D46-D42)/D42 -> 0.015294076 | Z46: =(D46-D33)/D33 -> 0.0091602968 | AA46: =(D46-D45)/(H46-H45) -> 0.77452933 | AB46: =AVERAGE(AA34:AA46) -> 1.0164832 | AC46: =AVERAGE(V34:V46) -> -0.016482742 | AD46: =(D46-D42)/(H46-H42) -> 1.0204797 | AE46: =AVERAGE(H34:H46) -> 985477.31 | AF46: =(AE46-AE42)/AE42 -> 0.0054120075 | AI46: =F46*G46 -> 461647.21 | AJ46: =(AI46-AI42)/AI42 -> -0.038830031 | AK46: =(F46-F42) -> 553.9 | AL46: =F46-F45 -> 132.61 | AM46: =AL46*G46 -> 377.96502 | AN46: =AK46*G46 -> 1578.7258 | AO46: =(E46+F46)*G46 -> 461907.37 | AP46: =H46/AO46 -> 2.1555498
B47: 42314 | C47: 378571.22 | D47: 611659.56 | E47: 116.94 | F47: 160874.88 | G47: 2.89398 | H47: 990230.78 | I47: =H47-H43 -> 1811.18 | J47: =H47-H46 -> -5433.59 | K47: =J47/H47 -> -0.0054871956 | L47: =I47/G47 -> 625.84399 | M47: =L47+AK47 -> -831.57601 | N47: =AK47-L47 -> -2083.264 | O47: =I47/H47 -> 0.0018290484 | P47: =(H47-H43)/H43 -> 0.0018323999 | S47: =(C47-C43)/C43 -> -0.0028539352 | U47: =(C47-C34)/C34 -> 0.0039766172 | V47: =(C47-C46)/(H47-H46) -> 0.21441993 | W47: =(C47-C43)/(H47-H43) -> -0.5982343 | X47: =(D47-D43)/D43 -> 0.0047550214 | Z47: =(D47-D34)/D34 -> 0.022635187 | AA47: =(D47-D46)/(H47-H46) -> 0.78558007 | AB47: =AVERAGE(AA35:AA47) -> 0.99896694 | AC47: =AVERAGE(V35:V47) -> 0.0010335714 | AE47: =AVERAGE(H35:H47) -> 986634.08 | AF47: =(AE47-AE43)/AE43 -> 0.0051711983 | AI47: =F47*G47 -> 465568.69 | AJ47: =(AI47-AI43)/AI43 -> -0.016933627 | AK47: =(F47-F43) -> -1457.42 | AL47: =F47-F46 -> -1095.23 | AM47: =AL47*G47 -> -3169.5737 | AN47: =AK47*G47 -> -4217.7443 | AO47: =(E47+F47)*G47 -> 465907.11 | AP47: =H47/AO47 -> 2.1253824
B48: 42321 | C48: 379729.6 | D48: 614513.11 | E48: 118.52 | F48: 160285.92 | G48: 2.86638 | H48: 994242.71 | I48: =H48-H44 -> 4803.49 | J48: =H48-H47 -> 4011.93 | K48: =J48/H48 -> 0.0040351616 | L48: =I48/G48 -> 1675.8036 | M48: =L48+AK48 -> -894.17637 | N48: =AK48-L48 -> -4245.7836 | O48: =I48/H48 -> 0.0048313052 | P48: =(H48-H44)/H44 -> 0.0048547601 | S48: =(C48-C44)/C44 -> 0.004438149 | U48: =(C48-C35)/C35 -> 0.001746866 | V48: =(C48-C47)/(H48-H47) -> 0.28873385 | W48: =(C48-C44)/(H48-H44) -> 0.34929811 | X48: =(D48-D44)/D44 -> 0.0051123717 | Z48: =(D48-D35)/D35 -> 0.026613549 | AA48: =(D48-D47)/(H48-H47) -> 0.71126615 | AB48: =AVERAGE(AA36:AA48) -> 1.0392266 | AC48: =AVERAGE(V36:V48) -> -0.039226101 | AD48: =(D48-D44)/(H48-H44) -> 0.65070189 | AE48: =AVERAGE(H36:H48) -> 987910.44 | AF48: =(AE48-AE44)/AE44 -> 0.0047106489 | AI48: =F48*G48 -> 459440.36 | AJ48: =(AI48-AI44)/AI44 -> -0.02502574 | AK48: =(F48-F44) -> -2569.98 | AL48: =F48-F47 -> -588.96 | AM48: =AL48*G48 -> -1688.1832 | AN48: =AK48*G48 -> -7366.5393 | AO48: =(E48+F48)*G48 -> 459780.08 | AP48: =H48/AO48 -> 2.162431
B49: 42328 | C49: 377218.5 | D49: 616855.45 | E49: 120.95 | F49: 159507.94 | G49: 2.86494 | H49: 994073.96 | I49: =H49-H45 -> 5604.14 | J49: =H49-H48 -> -168.75 | K49: =J49/H49 -> -0.00016975598 | L49: =I49/G49 -> 1956.1108 | M49: =L49+AK49 -> -373.44923 | N49: =AK49-L49 -> -4285.6708 | O49: =I49/H49 -> 0.0056375483 | P49: =(H49-H45)/H45 -> 0.0056695105 | S49: =(C49-C45)/C45 -> -0.0023686764 | U49: =(C49-C36)/C36 -> 0.0010102755 | V49: =(C49-C48)/(H49-H48) -> 14.880593 | W49: =(C49-C45)/(H49-H45) -> -0.15981578 | X49: =(D49-D45)/D45 -> 0.010649135 | Z49: =(D49-D36)/D36 -> 0.024646462 | AA49: =(D49-D48)/(H49-H48) -> -13.880533 | AB49: =AVERAGE(AA37:AA49) -> -0.24770335 | AC49: =AVERAGE(V37:V49) -> 1.2477078 | AD49: =(D49-D45)/(H49-H45) -> 1.159814 | AE49: =AVERAGE(H37:H49) -> 989081.08 | AF49: =(AE49-AE45)/AE45 -> 0.0043166085 | AI49: =F49*G49 -> 456980.68 | AJ49: =(AI49-AI45)/AI45 -> -0.021773121 | AK49: =(F49-F45) -> -2329.56 | AL49: =F49-F48 -> -777.98 | AM49: =AL49*G49 -> -2228.866 | AN49: =AK49*G49 -> -6674.0496 | AO49: =(E49+F49)*G49 -> 457327.19 | AP49: =H49/AO49 -> 2.1736603
B50: 42335 | C50: 378774.27 | D50: 625507.38 | E50: 115.91 | F50: 159255.75 | G50: 2.89624 | H50: 1004281.7 | I50: =H50-H46 -> 8617.28 | J50: =H50-H49 -> 10207.69 | K50: =J50/H50 -> 0.010164171 | L50: =I50/G50 -> 2975.3335 | M50: =L50+AK50 -> 260.97354 | N50: =AK50-L50 -> -5689.6935 | O50: =I50/H50 -> 0.0085805411 | P50: =(H50-H46)/H46 -> 0.008654804 | S50: =(C50-C46)/C46 -> -0.0025333897 | U50: =(C50-C37)/C37 -> -0.00054559458 | V50: =(C50-C49)/(H50-H49) -> 0.15241156 | W50: =(C50-C46)/(H50-H46) -> -0.11163848 | X50: =(D50-D46)/D46 -> 0.015552628 | Z50: =(D50-D37)/D37 -> 0.032288208 | AA50: =(D50-D49)/(H50-H49) -> 0.84758942 | AB50: =AVERAGE(AA38:AA50) -> -0.23225747 | AC50: =AVERAGE(V38:V50) -> 1.2322621 | AD50: =(D50-D46)/(H50-H46) -> 1.1116385 | AE50: =AVERAGE(H38:H50) -> 990570.16 | AF50: =(AE50-AE46)/AE46 -> 0.0051678987 | AI50: =F50*G50 -> 461242.87 | AJ50: =(AI50-AI46)/AI46 -> -0.00087585094 | AK50: =(F50-F46) -> -2714.36 | AL50: =F50-F49 -> -252.19 | AM50: =AL50*G50 -> -730.40277 | AN50: =AK50*G50 -> -7861.438 | AO50: =(E50+F50)*G50 -> 461578.58 | AP50: =H50/AO50 -> 2.1757545
B51: 42342 | C51: 379613.54 | D51: 619762.01 | E51: 114.88 | F51: 161017.3 | G51: 2.90294 | H51: 999375.55 | I51: =H51-H47 -> 9144.77 | J51: =H51-H50 -> -4906.1 | K51: =J51/H51 -> -0.0049091655 | L51: =I51/G51 -> 3150.1753 | M51: =L51+AK51 -> 3292.5953 | N51: =AK51-L51 -> -3007.7553 | O51: =I51/H51 -> 0.009150484 | P51: =(H51-H47)/H47 -> 0.0092349886 | S51: =(C51-C47)/C47 -> 0.0027532996 | U51: =(C51-C38)/C38 -> -0.00025372002 | V51: =(C51-C50)/(H51-H50) -> -0.17106663 | W51: =(C51-C47)/(H51-H47) -> 0.1139799 | X51: =(D51-D47)/D47 -> 0.013246666 | Z51: =(D51-D38)/D38 -> 0.025938161 | AA51: =(D51-D50)/(H51-H50) -> 1.1710666 | AB51: =AVERAGE(AA39:AA51) -> -0.26912091 | AC51: =AVERAGE(V39:V51) -> 1.2691255 | AD51: =(D51-D47)/(H51-H47) -> 0.8860201 | AE51: =AVERAGE(H39:H51) -> 991768.06 | AF51: =(AE51-AE47)/AE47 -> 0.0052035253 | AI51: =F51*G51 -> 467423.56 | AJ51: =(AI51-AI47)/AI47 -> 0.0039841074 | AK51: =(F51-F47) -> 142.42 | AL51: =F51-F50 -> 1761.55 | AM51: =AL51*G51 -> 5113.674 | AN51: =AK51*G51 -> 413.43671 | AO51: =(E51+F51)*G51 -> 467757.05 | AP51: =H51/AO51 -> 2.136527
B52: 42349 | C52: 380882.6 | D52: 622592.42 | E52: 115.71 | F52: 162279.62 | G52: 2.95532 | H52: 1003475 | I52: =H52-H48 -> 9232.31 | J52: =H52-H51 -> 4099.47 | K52: =J52/H52 -> 0.0040852736 | L52: =I52/G52 -> 3123.9629 | M52: =L52+AK52 -> 5117.6629 | N52: =AK52-L52 -> -1130.2629 | O52: =I52/H52 -> 0.0092003386 | P52: =(H52-H48)/H48 -> 0.0092857709 | S52: =(C52-C48)/C48 -> 0.0030363711 | U52: =(C52-C39)/C39 -> 0.00016446091 | V52: =(C52-C51)/(H52-H51) -> 0.30956685 | W52: =(C52-C48)/(H52-H48) -> 0.12488749 | X52: =(D52-D48)/D48 -> 0.013147498 | Z52: =(D52-D39)/D39 -> 0.024448567 | AA52: =(D52-D51)/(H52-H51) -> 0.69043315 | AB52: =AVERAGE(AA40:AA52) -> -0.27496161 | AC52: =AVERAGE(V40:V52) -> 1.2749662 | AD52: =(D52-D48)/(H52-H48) -> 0.87511251 | AE52: =AVERAGE(H40:H52) -> 992915.82 | AF52: =(AE52-AE48)/AE48 -> 0.0050666342 | AI52: =F52*G52 -> 479588.21 | AJ52: =(AI52-AI48)/AI48 -> 0.043853029 | AK52: =(F52-F48) -> 1993.7 | AL52: =F52-F51 -> 1262.32 | AM52: =AL52*G52 -> 3730.5595 | AN52: =AK52*G52 -> 5892.0215 | AO52: =(E52+F52)*G52 -> 479930.17 | AP52: =H52/AO52 -> 2.0908772
B53: 42356 | C53: 379840.63 | D53: 623331.41 | E53: 118.48 | F53: 161801.87 | G53: 2.91988 | H53: 1003172 | I53: =H53-H49 -> 9098.08 | J53: =H53-H52 -> -302.98 | K53: =J53/H53 -> -0.00030202197 | L53: =I53/G53 -> 3115.9089 | M53: =L53+AK53 -> 5409.8389 | N53: =AK53-L53 -> -821.97887 | O53: =I53/H53 -> 0.0090693118 | P53: =(H53-H49)/H49 -> 0.009152317 | S53: =(C53-C49)/C49 -> 0.0069512232 | U53: =(C53-C40)/C40 -> 0.00020262601 | V53: =(C53-C52)/(H53-H52) -> 3.4390719 | W53: =(C53-C49)/(H53-H49) -> 0.28820696 | X53: =(D53-D49)/D49 -> 0.010498343 | Z53: =(D53-D40)/D40 -> 0.024453928 | AA53: =(D53-D52)/(H53-H52) -> -2.4390719 | AB53: =AVERAGE(AA41:AA53) -> -0.2991972 | AC53: =AVERAGE(V41:V53) -> 1.2992018 | AD53: =(D53-D49)/(H53-H49) -> 0.71179414 | AE53: =AVERAGE(H41:H53) -> 994066.28 | AF53: =(AE53-AE49)/AE49 -> 0.0050402347 | AI53: =F53*G53 -> 472442.04 | AJ53: =(AI53-AI49)/AI49 -> 0.033833742 | AK53: =(F53-F49) -> 2293.93 | AL53: =F53-F52 -> -477.75 | AM53: =AL53*G53 -> -1394.9727 | AN53: =AK53*G53 -> 6698.0003 | AO53: =(E53+F53)*G53 -> 472787.99 | AP53: =H53/AO53 -> 2.1218222
B54: 42363 | C54: 381597.02 | D54: 624348.17 | E54: 116.62 | F54: 162775.39 | G54: 2.911 | H54: 1005945.2 | I54: =H54-H50 -> 1663.55 | J54: =H54-H53 -> 2773.16 | K54: =J54/H54 -> 0.0027567704 | L54: =I54/G54 -> 571.47029 | M54: =L54+AK54 -> 4091.1103 | N54: =AK54-L54 -> 2948.1697 | O54: =I54/H54 -> 0.0016537183 | P54: =(H54-H50)/H50 -> 0.0016564576 | S54: =(C54-C50)/C50 -> 0.0074523277 | U54: =(C54-C41)/C41 -> 0.0031145952 | V54: =(C54-C53)/(H54-H53) -> 0.63335329 | W54: =(C54-C50)/(H54-H50) -> 1.6968231 | X54: =(D54-D50)/D50 -> -0.0018532315 | Z54: =(D54-D41)/D41 -> 0.031925388 | AA54: =(D54-D53)/(H54-H53) -> 0.36664311 | AB54: =AVERAGE(AA42:AA54) -> -0.36591592 | AC54: =AVERAGE(V42:V54) -> 1.3659203 | AE54: =AVERAGE(H42:H54) -> 995643.26 | AF54: =(AE54-AE50)/AE50 -> 0.0051213947 | AI54: =F54*G54 -> 473839.16 | AJ54: =(AI54-AI50)/AI50 -> 0.027309445 | AK54: =(F54-F50) -> 3519.64 | AL54: =F54-F53 -> 973.52 | AM54: =AL54*G54 -> 2833.9167 | AN54: =AK54*G54 -> 10245.672 | AO54: =(E54+F54)*G54 -> 474178.64 | AP54: =H54/AO54 -> 2.1214477
B55: 42369 | C55: 384836.48 | D55: 628590.23 | E55: 83.23 | F55: 162426.32 | G55: 2.9712 | H55: 1013426.7 | I55: =H55-H51 -> 14051.16 | J55: =H55-H54 -> 7481.51 | K55: =J55/H55 -> 0.0073823888 | L55: =I55/G55 -> 4729.1195 | M55: =L55+AK55 -> 6138.1395 | N55: =AK55-L55 -> -3320.0995 | O55: =I55/H55 -> 0.013864999 | P55: =(H55-H51)/H51 -> 0.01405994 | Q55: =(H55-H2)/H2 -> 0.15224317 | S55: =(C55-C51)/C51 -> 0.013758571 | T55: =(C55-C2)/C2 -> 0.089120189 | U55: =(C55-C42)/C42 -> 0.012934191 | V55: =(C55-C54)/(H55-H54) -> 0.43299548 | W55: =(C55-C51)/(H55-H51) -> 0.37170881 | X55: =(D55-D51)/D51 -> 0.014244532 | Y55: =(D55-D2)/D2 -> 0.19463231 | Z55: =(D55-D42)/D42 -> 0.036166327 | AA55: =(D55-D54)/(H55-H54) -> 0.56700586 | AB55: =AVERAGE(AA43:AA55) -> -0.43261935 | AC55: =AVERAGE(V43:V55) -> 1.4326238 | AD55: =(D55-D51)/(H55-H51) -> 0.62829119 | AE55: =AVERAGE(H43:H55) -> 997708.97 | AF55: =(AE55-AE51)/AE51 -> 0.005990225 | AG55: =(AE55-AE2)/AE2 -> #DIV/0! | AI55: =F55*G55 -> 482601.08 | AJ55: =(AI55-AI51)/AI51 -> 0.032470595 | AK55: =(F55-F51) -> 1409.02 | AL55: =F55-F54 -> -349.07 | AM55: =AL55*G55 -> -1037.1568 | AN55: =AK55*G55 -> 4186.4802 | AO55: =(E55+F55)*G55 -> 482848.37 | AP55: =H55/AO55 -> 2.0988508
B56: 42377 | C56: 382350.03 | D56: 621835.93 | E56: 111.58 | F56: 162118.58 | G56: 3.01594 | H56: 1004186 | I56: =H56-H52 -> 710.95 | J56: =H56-H55 -> -9240.74 | K56: =J56/H56 -> -0.0092022198 | L56: =I56/G56 -> 235.73082 | M56: =L56+AK56 -> 74.690817 | N56: =AK56-L56 -> -396.77082 | O56: =I56/H56 -> 0.00070798639 | P56: =(H56-H52)/H52 -> 0.00070848799 | Q56: =(H56-H3)/H3 -> 0.14731623 | S56: =(C56-C52)/C52 -> 0.0038527095 | T56: =(C56-C3)/C3 -> 0.074739248 | U56: =(C56-C43)/C43 -> 0.0070993452 | V56: =(C56-C55)/(H56-H55) -> 0.26907477 | W56: =(C56-C52)/(H56-H52) -> 2.0640411 | X56: =(D56-D52)/D52 -> -0.0012150646 | Y56: =(D56-D3)/D3 -> 0.19701914 | Z56: =(D56-D43)/D43 -> 0.021471443 | AA56: =(D56-D55)/(H56-H55) -> 0.73092631 | AB56: =AVERAGE(AA44:AA56) -> -0.4644678 | AC56: =AVERAGE(V44:V56) -> 1.4644723 | AE56: =AVERAGE(H44:H56) -> 998921.77 | AF56: =(AE56-AE52)/AE52 -> 0.0060488039 | AG56: =(AE56-AE3)/AE3 -> #DIV/0! | AI56: =F56*G56 -> 488939.91 | AJ56: =(AI56-AI52)/AI52 -> 0.019499444 | AK56: =(F56-F52) -> -161.04 | AL56: =F56-F55 -> -307.74 | AM56: =AL56*G56 -> -928.12538 | AN56: =AK56*G56 -> -485.68698 | AO56: =(E56+F56)*G56 -> 489276.43 | AP56: =H56/AO56 -> 2.0523898
B57: 42384 | C57: 381702.3 | D57: 629812.97 | E57: 114.05 | F57: 162637.37 | G57: 3.0371 | H57: 1011515.3 | I57: =H57-H53 -> 8343.23 | J57: =H57-H56 -> 7329.3 | K57: =J57/H57 -> 0.0072458619 | L57: =I57/G57 -> 2747.1041 | M57: =L57+AK57 -> 3582.6041 | N57: =AK57-L57 -> -1911.6041 | O57: =I57/H57 -> 0.0082482492 | P57: =(H57-H53)/H53 -> 0.0083168486 | Q57: =(H57-H4)/H4 -> 0.15736329 | S57: =(C57-C53)/C53 -> 0.0049011871 | T57: =(C57-C4)/C4 -> 0.074820729 | U57: =(C57-C44)/C44 -> 0.0096562177 | V57: =(C57-C56)/(H57-H56) -> -0.088375425 | W57: =(C57-C53)/(H57-H53) -> 0.2231354 | X57: =(D57-D53)/D53 -> 0.010398257 | Y57: =(D57-D4)/D4 -> 0.21386007 | Z57: =(D57-D44)/D44 -> 0.030137189 | AA57: =(D57-D56)/(H57-H56) -> 1.0883768 | AB57: =AVERAGE(AA45:AA57) -> -0.57860302 | AC57: =AVERAGE(V45:V57) -> 1.5786077 | AD57: =(D57-D53)/(H57-H53) -> 0.7768646 | AE57: =AVERAGE(H45:H57) -> 1000619.9 | AF57: =(AE57-AE53)/AE53 -> 0.0065927689 | AG57: =(AE57-AE4)/AE4 -> #DIV/0! | AI57: =F57*G57 -> 493945.96 | AJ57: =(AI57-AI53)/AI53 -> 0.045516508 | AK57: =(F57-F53) -> 835.5 | AL57: =F57-F56 -> 518.79 | AM57: =AL57*G57 -> 1575.6171 | AN57: =AK57*G57 -> 2537.497 | AO57: =(E57+F57)*G57 -> 494292.34 | AP57: =H57/AO57 -> 2.0463908
B58: 42391 | C58: 380961.84 | D58: 625898.39 | E58: 115.09 | F58: 162440.82 | G58: 3.00356 | H58: 1006860.2 | I58: =H58-H54 -> 915.04 | J58: =H58-H57 -> -4655.03 | K58: =J58/H58 -> -0.004623313 | L58: =I58/G58 -> 304.65181 | M58: =L58+AK58 -> -29.918187 | N58: =AK58-L58 -> -639.22181 | O58: =I58/H58 -> 0.00090880538 | P58: =(H58-H54)/H54 -> 0.00090963206 | Q58: =(H58-H5)/H5 -> 0.14474098 | S58: =(C58-C54)/C54 -> -0.0016645308 | T58: =(C58-C5)/C5 -> 0.074535863 | U58: =(C58-C45)/C45 -> 0.0075313504 | V58: =(C58-C57)/(H58-H57) -> 0.15906664 | W58: =(C58-C54)/(H58-H54) -> -0.69415545 | X58: =(D58-D54)/D54 -> 0.0024829415 | Y58: =(D58-D5)/D5 -> 0.19214947 | Z58: =(D58-D45)/D45 -> 0.025464987 | AA58: =(D58-D57)/(H58-H57) -> 0.8409355 | AB58: =AVERAGE(AA46:AA58) -> -0.59578868 | AC58: =AVERAGE(V46:V58) -> 1.5957935 | AE58: =AVERAGE(H46:H58) -> 1002034.6 | AF58: =(AE58-AE54)/AE54 -> 0.0064192849 | AG58: =(AE58-AE5)/AE5 -> #DIV/0! | AI58: =F58*G58 -> 487900.75 | AJ58: =(AI58-AI54)/AI54 -> 0.029675869 | AK58: =(F58-F54) -> -334.57 | AL58: =F58-F57 -> -196.55 | AM58: =AL58*G58 -> -590.34972 | AN58: =AK58*G58 -> -1004.9011 | AO58: =(E58+F58)*G58 -> 488246.43 | AP58: =H58/AO58 -> 2.0621968
B59: 42398 | C59: 383037.61 | D59: 632711.59 | E59: 114.88 | F59: 162740.49 | G59: 2.94652 | H59: 1015749.2 | I59: =H59-H55 -> 2322.49 | J59: =H59-H58 -> 8888.96 | K59: =J59/H59 -> 0.0087511366 | L59: =I59/G59 -> 788.21457 | M59: =L59+AK59 -> 1102.3846 | N59: =AK59-L59 -> -474.04457 | O59: =I59/H59 -> 0.0022864798 | P59: =(H59-H55)/H55 -> 0.0022917197 | Q59: =(H59-H6)/H6 -> 0.15733339 | S59: =(C59-C55)/C55 -> -0.0046743749 | T59: =(C59-C6)/C6 -> 0.078219236 | U59: =(C59-C46)/C46 -> 0.0086937174 | V59: =(C59-C58)/(H59-H58) -> 0.23352226 | W59: =(C59-C55)/(H59-H55) -> -0.7745437 | X59: =(D59-D55)/D55 -> 0.006556513 | Y59: =(D59-D6)/D6 -> 0.2111324 | Z59: =(D59-D46)/D46 -> 0.027249139 | AA59: =(D59-D58)/(H59-H58) -> 0.76647887 | AB59: =AVERAGE(AA47:AA59) -> -0.59640795 | AC59: =AVERAGE(V47:V59) -> 1.5964129 | AE59: =AVERAGE(H47:H59) -> 1003579.6 | AF59: =(AE59-AE55)/AE55 -> 0.0058840706 | AG59: =(AE59-AE6)/AE6 -> #DIV/0! | AI59: =F59*G59 -> 479518.11 | AJ59: =(AI59-AI55)/AI55 -> -0.0063882438 | AK59: =(F59-F55) -> 314.17 | AL59: =F59-F58 -> 299.67 | AM59: =AL59*G59 -> 882.98365 | AN59: =AK59*G59 -> 925.70819 | AO59: =(E59+F59)*G59 -> 479856.6 | AP59: =H59/AO59 -> 2.1167765
B60: 42405 | C60: 383528.27 | D60: 631380.26 | E60: 118.96 | F60: 164983.13 | G60: 2.92686 | H60: 1014908.5 | I60: =H60-H56 -> 10722.56 | J60: =H60-H59 -> -840.67 | K60: =J60/H60 -> -0.00082832095 | L60: =I60/G60 -> 3663.5029 | M60: =L60+AK60 -> 6528.0529 | N60: =AK60-L60 -> -798.95287 | O60: =I60/H60 -> 0.010565051 | P60: =(H60-H56)/H56 -> 0.010677863 | Q60: =(H60-H7)/H7 -> 0.14373719 | S60: =(C60-C56)/C56 -> 0.0030815742 | T60: =(C60-C7)/C7 -> 0.07134722 | U60: =(C60-C47)/C47 -> 0.013094102 | V60: =(C60-C59)/(H60-H59) -> -0.58365351 | W60: =(C60-C56)/(H60-H56) -> 0.10988421 | X60: =(D60-D56)/D56 -> 0.015348631 | Y60: =(D60-D7)/D7 -> 0.19269052 | Z60: =(D60-D47)/D47 -> 0.032241301 | AA60: =(D60-D59)/(H60-H59) -> 1.5836535 | AB60: =AVERAGE(AA48:AA60) -> -0.53501769 | AC60: =AVERAGE(V48:V60) -> 1.5350226 | AD60: =(D60-D56)/(H60-H56) -> 0.89011673 | AE60: =AVERAGE(H48:H60) -> 1005477.8 | AF60: =(AE60-AE56)/AE56 -> 0.0065631574 | AG60: =(AE60-AE7)/AE7 -> #DIV/0! | AI60: =F60*G60 -> 482882.52 | AJ60: =(AI60-AI56)/AI56 -> -0.012388815 | AK60: =(F60-F56) -> 2864.55 | AL60: =F60-F59 -> 2242.64 | AM60: =AL60*G60 -> 6563.8933 | AN60: =AK60*G60 -> 8384.1368 | AO60: =(E60+F60)*G60 -> 483230.7 | AP60: =H60/AO60 -> 2.1002567
B61: 42412 | C61: 384842.57 | D61: 633655.48 | E61: 121.02 | F61: 165816.36 | G61: 2.94862 | H61: 1018498 | I61: =H61-H57 -> 6982.77 | J61: =H61-H60 -> 3589.51 | K61: =J61/H61 -> 0.003524317 | L61: =I61/G61 -> 2368.1485 | M61: =L61+AK61 -> 5547.1385 | N61: =AK61-L61 -> 810.84151 | O61: =I61/H61 -> 0.0068559484 | P61: =(H61-H57)/H57 -> 0.0069032769 | Q61: =(H61-H8)/H8 -> 0.14729126 | S61: =(C61-C57)/C57 -> 0.0082270136 | T61: =(C61-C8)/C8 -> 0.073656219 | U61: =(C61-C48)/C48 -> 0.013464765 | V61: =(C61-C60)/(H61-H60) -> 0.36615025 | W61: =(C61-C57)/(H61-H57) -> 0.44971695 | X61: =(D61-D57)/D57 -> 0.0061010335 | Y61: =(D61-D8)/D8 -> 0.19715678 | Z61: =(D61-D48)/D48 -> 0.031150466 | AA61: =(D61-D60)/(H61-H60) -> 0.63385253 | AB61: =AVERAGE(AA49:AA61) -> -0.54097258 | AC61: =AVERAGE(V49:V61) -> 1.5409777 | AD61: =(D61-D57)/(H61-H57) -> 0.55028449 | AE61: =AVERAGE(H49:H61) -> 1007343.6 | AF61: =(AE61-AE57)/AE57 -> 0.0067195521 | AG61: =(AE61-AE8)/AE8 -> #DIV/0! | AI61: =F61*G61 -> 488929.44 | AJ61: =(AI61-AI57)/AI57 -> -0.010156012 | AK61: =(F61-F57) -> 3178.99 | AL61: =F61-F60 -> 833.23 | AM61: =AL61*G61 -> 2456.8786 | AN61: =AK61*G61 -> 9373.6335 | AO61: =(E61+F61)*G61 -> 489286.28 | AP61: =H61/AO61 -> 2.0815994
B62: 42419 | C62: 383044.15 | D62: 635240.37 | E62: 122.33 | F62: 165186.71 | G62: 2.94292 | H62: 1018284.5 | I62: =H62-H58 -> 11424.28 | J62: =H62-H61 -> -213.52 | K62: =J62/H62 -> -0.00020968599 | L62: =I62/G62 -> 3881.954 | M62: =L62+AK62 -> 6627.844 | N62: =AK62-L62 -> -1136.064 | O62: =I62/H62 -> 0.011219143 | P62: =(H62-H58)/H58 -> 0.011346441 | Q62: =(H62-H9)/H9 -> 0.13754053 | S62: =(C62-C58)/C58 -> 0.005465928 | T62: =(C62-C9)/C9 -> 0.062719527 | U62: =(C62-C49)/C49 -> 0.015443702 | V62: =(C62-C61)/(H62-H61) -> 8.4227239 | W62: =(C62-C58)/(H62-H58) -> 0.18227057 | X62: =(D62-D58)/D58 -> 0.014925713 | Y62: =(D62-D9)/D9 -> 0.18797444 | Z62: =(D62-D49)/D49 -> 0.02980426 | AA62: =(D62-D61)/(H62-H61) -> -7.422677 | AB62: =AVERAGE(AA50:AA62) -> -0.044214403 | AC62: =AVERAGE(V50:V62) -> 1.0442186 | AD62: =(D62-D58)/(H62-H58) -> 0.81773031 | AE62: =AVERAGE(H50:H62) -> 1009206 | AF62: =(AE62-AE58)/AE58 -> 0.0071568596 | AG62: =(AE62-AE9)/AE9 -> #DIV/0! | AI62: =F62*G62 -> 486131.27 | AJ62: =(AI62-AI58)/AI58 -> -0.0036267145 | AK62: =(F62-F58) -> 2745.89 | AL62: =F62-F61 -> -629.65 | AM62: =AL62*G62 -> -1853.0096 | AN62: =AK62*G62 -> 8080.9346 | AO62: =(E62+F62)*G62 -> 486491.28 | AP62: =H62/AO62 -> 2.0931198
B63: 42426 | C63: 384138.38 | D63: 641602.59 | E63: 113.43 | F63: 164892.06 | G63: 2.93886 | H63: 1025741 | I63: =H63-H59 -> 9991.77 | J63: =H63-H62 -> 7456.45 | K63: =J63/H63 -> 0.0072693304 | L63: =I63/G63 -> 3399.8795 | M63: =L63+AK63 -> 5551.4495 | N63: =AK63-L63 -> -1248.3095 | O63: =I63/H63 -> 0.0097410265 | P63: =(H63-H59)/H59 -> 0.0098368475 | Q63: =(H63-H10)/H10 -> 0.1463835 | S63: =(C63-C59)/C59 -> 0.0028737909 | T63: =(C63-C10)/C10 -> 0.071515196 | U63: =(C63-C50)/C50 -> 0.014161759 | V63: =(C63-C62)/(H63-H62) -> 0.14674946 | W63: =(C63-C59)/(H63-H59) -> 0.11016767 | X63: =(D63-D59)/D59 -> 0.014052216 | Y63: =(D63-D10)/D10 -> 0.1964342 | Z63: =(D63-D50)/D50 -> 0.025731447 | AA63: =(D63-D62)/(H63-H62) -> 0.85325054 | AB63: =AVERAGE(AA51:AA63) -> -0.043778931 | AC63: =AVERAGE(V51:V63) -> 1.043783 | AD63: =(D63-D59)/(H63-H59) -> 0.88983233 | AE63: =AVERAGE(H51:H63) -> 1010856.7 | AF63: =(AE63-AE59)/AE59 -> 0.0072511947 | AG63: =(AE63-AE10)/AE10 -> #DIV/0! | AI63: =F63*G63 -> 484594.68 | AJ63: =(AI63-AI59)/AI59 -> 0.010586818 | AK63: =(F63-F59) -> 2151.57 | AL63: =F63-F62 -> -294.65 | AM63: =AL63*G63 -> -865.9351 | AN63: =AK63*G63 -> 6323.163 | AO63: =(E63+F63)*G63 -> 484928.03 | AP63: =H63/AO63 -> 2.1152437
B64: 42433 | C64: 384759.96 | D64: 636468.73 | E64: 111.51 | F64: 164413.03 | G64: 2.9101 | H64: 1021228.7 | I64: =H64-H60 -> 6320.15 | J64: =H64-H63 -> -4512.29 | K64: =J64/H64 -> -0.0044184913 | L64: =I64/G64 -> 2171.7982 | M64: =L64+AK64 -> 1601.6982 | N64: =AK64-L64 -> -2741.8982 | O64: =I64/H64 -> 0.0061887706 | P64: =(H64-H60)/H60 -> 0.00622731 | Q64: =(H64-H11)/H11 -> 0.13006095 | S64: =(C64-C60)/C60 -> 0.0032114712 | T64: =(C64-C11)/C11 -> 0.069739452 | U64: =(C64-C51)/C51 -> 0.013556998 | V64: =(C64-C63)/(H64-H63) -> -0.13775267 | W64: =(C64-C60)/(H64-H60) -> 0.19488303 | X64: =(D64-D60)/D60 -> 0.0080592795 | Y64: =(D64-D11)/D11 -> 0.16994244 | Z64: =(D64-D51)/D51 -> 0.02695667 | AA64: =(D64-D63)/(H64-H63) -> 1.1377505 | AB64: =AVERAGE(AA52:AA64) -> -0.046341714 | AC64: =AVERAGE(V52:V64) -> 1.0463456 | AD64: =(D64-D60)/(H64-H60) -> 0.80511855 | AE64: =AVERAGE(H52:H64) -> 1012537.7 | AF64: =(AE64-AE60)/AE60 -> 0.0070214101 | AG64: =(AE64-AE11)/AE11 -> #DIV/0! | AI64: =F64*G64 -> 478458.36 | AJ64: =(AI64-AI60)/AI60 -> -0.0091619909 | AK64: =(F64-F60) -> -570.1 | AL64: =F64-F63 -> -479.03 | AM64: =AL64*G64 -> -1394.0252 | AN64: =AK64*G64 -> -1659.048 | AO64: =(E64+F64)*G64 -> 478782.86 | AP64: =H64/AO64 -> 2.1329683
B65: 42440 | C65: 384963.8 | D65: 639620.12 | E65: 112.08 | F65: 165610.23 | G65: 2.88048 | H65: 1024583.9 | I65: =H65-H61 -> 6085.87 | J65: =H65-H64 -> 3355.23 | K65: =J65/H65 -> 0.0032747245 | L65: =I65/G65 -> 2112.7972 | M65: =L65+AK65 -> 1906.6672 | N65: =AK65-L65 -> -2318.9272 | O65: =I65/H65 -> 0.0059398454 | P65: =(H65-H61)/H61 -> 0.005975338 | Q65: =(H65-H12)/H12 -> 0.13275806 | S65: =(C65-C61)/C61 -> 0.00031501193 | T65: =(C65-C12)/C12 -> 0.069031969 | U65: =(C65-C52)/C52 -> 0.010715113 | V65: =(C65-C64)/(H65-H64) -> 0.060752914 | W65: =(C65-C61)/(H65-H61) -> 0.019919913 | X65: =(D65-D61)/D61 -> 0.0094130647 | Y65: =(D65-D12)/D12 -> 0.17491116 | Z65: =(D65-D52)/D52 -> 0.027349674 | AA65: =(D65-D64)/(H65-H64) -> 0.93924709 | AB65: =AVERAGE(AA53:AA65) -> -0.027202181 | AC65: =AVERAGE(V53:V65) -> 1.0272061 | AD65: =(D65-D61)/(H65-H61) -> 0.98008009 | AE65: =AVERAGE(H53:H65) -> 1014161.5 | AF65: =(AE65-AE61)/AE61 -> 0.0067681357 | AG65: =(AE65-AE12)/AE12 -> #DIV/0! | AI65: =F65*G65 -> 477036.96 | AJ65: =(AI65-AI61)/AI61 -> -0.02432351 | AK65: =(F65-F61) -> -206.13 | AL65: =F65-F64 -> 1197.2 | AM65: =AL65*G65 -> 3448.5107 | AN65: =AK65*G65 -> -593.75334 | AO65: =(E65+F65)*G65 -> 477359.8 | AP65: =H65/AO65 -> 2.1463557
B66: 42447 | C66: 383855.97 | D66: 639662.29 | E66: 116.76 | F66: 167006.94 | G66: 2.86908 | H66: 1023518.3 | I66: =H66-H62 -> 5233.74 | J66: =H66-H65 -> -1065.65 | K66: =J66/H66 -> -0.0010411636 | L66: =I66/G66 -> 1824.1875 | M66: =L66+AK66 -> 3644.4175 | N66: =AK66-L66 -> -3.9575444 | O66: =I66/H66 -> 0.0051134799 | P66: =(H66-H62)/H62 -> 0.0051397619 | Q66: =(H66-H13)/H13 -> 0.12634941 | S66: =(C66-C62)/C62 -> 0.0021193902 | T66: =(C66-C13)/C13 -> 0.061892941 | U66: =(C66-C53)/C53 -> 0.010571118 | V66: =(C66-C65)/(H66-H65) -> 1.0395815 | W66: =(C66-C62)/(H66-H62) -> 0.15511279 | X66: =(D66-D62)/D62 -> 0.0069610186 | Y66: =(D66-D13)/D13 -> 0.16892798 | Z66: =(D66-D53)/D53 -> 0.026199354 | AA66: =(D66-D65)/(H66-H65) -> -0.039572092 | AB66: =AVERAGE(AA54:AA66) -> 0.15737473 | AC66: =AVERAGE(V54:V66) -> 0.84262991 | AD66: =(D66-D62)/(H66-H62) -> 0.84488721 | AE66: =AVERAGE(H54:H66) -> 1015726.6 | AF66: =(AE66-AE62)/AE62 -> 0.0064611007 | AG66: =(AE66-AE13)/AE13 -> #DIV/0! | AI66: =F66*G66 -> 479156.27 | AJ66: =(AI66-AI62)/AI62 -> -0.014347979 | AK66: =(F66-F62) -> 1820.23 | AL66: =F66-F65 -> 1396.71 | AM66: =AL66*G66 -> 4007.2727 | AN66: =AK66*G66 -> 5222.3855 | AO66: =(E66+F66)*G66 -> 479491.27 | AP66: =H66/AO66 -> 2.1345921
B67: 42454 | C67: 385129.38 | D67: 640019.14 | E67: 115.55 | F67: 166732.29 | G67: 2.85432 | H67: 1025148.5 | I67: =H67-H63 -> -592.44 | J67: =H67-H66 -> 1630.27 | K67: =J67/H67 -> 0.0015902769 | L67: =I67/G67 -> -207.55907 | M67: =L67+AK67 -> 1632.6709 | N67: =AK67-L67 -> 2047.7891 | O67: =I67/H67 -> -0.0005779065 | P67: =(H67-H63)/H63 -> -0.00057757272 | Q67: =(H67-H14)/H14 -> 0.12768137 | S67: =(C67-C63)/C63 -> 0.0025797995 | T67: =(C67-C14)/C14 -> 0.067715619 | U67: =(C67-C54)/C54 -> 0.0092567809 | V67: =(C67-C66)/(H67-H66) -> 0.78110374 | W67: =(C67-C63)/(H67-H63) -> -1.6727432 | X67: =(D67-D63)/D63 -> -0.0024679607 | Y67: =(D67-D14)/D14 -> 0.16712515 | Z67: =(D67-D54)/D54 -> 0.025099729 | AA67: =(D67-D66)/(H67-H66) -> 0.21889012 | AB67: =AVERAGE(AA55:AA67) -> 0.14600911 | AC67: =AVERAGE(V55:V67) -> 0.85399533 | AE67: =AVERAGE(H55:H67) -> 1017203.8 | AF67: =(AE67-AE63)/AE63 -> 0.0062788759 | AG67: =(AE67-AE14)/AE14 -> 0.14223665 | AI67: =F67*G67 -> 475907.31 | AJ67: =(AI67-AI63)/AI63 -> -0.017927084 | AK67: =(F67-F63) -> 1840.23 | AL67: =F67-F66 -> -274.65 | AM67: =AL67*G67 -> -783.93899 | AN67: =AK67*G67 -> 5252.6053 | AO67: =(E67+F67)*G67 -> 476237.13 | AP67: =H67/AO67 -> 2.152601
B68: 42461 | C68: 387606.84 | D68: 644172.03 | E68: 112.26 | F68: 168650.87 | G68: 2.83006 | H68: 1031778.9 | I68: =H68-H64 -> 10550.19 | J68: =H68-H67 -> 6630.34 | K68: =J68/H68 -> 0.006426125 | L68: =I68/G68 -> 3727.9033 | M68: =L68+AK68 -> 7965.7433 | N68: =AK68-L68 -> 509.9367 | O68: =I68/H68 -> 0.010225243 | P68: =(H68-H64)/H64 -> 0.010330879 | Q68: =(H68-H15)/H15 -> 0.12377998 | S68: =(C68-C64)/C64 -> 0.0073991067 | T68: =(C68-C15)/C15 -> 0.067642497 | U68: =(C68-C55)/C55 -> 0.0071987978 | V68: =(C68-C67)/(H68-H67) -> 0.37365505 | W68: =(C68-C64)/(H68-H64) -> 0.26984159 | X68: =(D68-D64)/D64 -> 0.012103187 | Y68: =(D68-D15)/D15 -> 0.16049642 | Z68: =(D68-D55)/D55 -> 0.024788486 | AA68: =(D68-D67)/(H68-H67) -> 0.62634646 | AB68: =AVERAGE(AA56:AA68) -> 0.15057377 | AC68: =AVERAGE(V56:V68) -> 0.84943068 | AD68: =(D68-D64)/(H68-H64) -> 0.73015747 | AE68: =AVERAGE(H56:H68) -> 1018615.5 | AF68: =(AE68-AE64)/AE64 -> 0.006002481 | AG68: =(AE68-AE15)/AE15 -> 0.14002009 | AI68: =F68*G68 -> 477292.08 | AJ68: =(AI68-AI64)/AI64 -> -0.0024375736 | AK68: =(F68-F64) -> 4237.84 | AL68: =F68-F67 -> 1918.58 | AM68: =AL68*G68 -> 5429.6965 | AN68: =AK68*G68 -> 11993.341 | AO68: =(E68+F68)*G68 -> 477609.78 | AP68: =H68/AO68 -> 2.1602968
B69: 42468 | C69: 387541.46 | D69: 644490.73 | E69: 113.63 | F69: 168382.63 | G69: 2.845 | H69: 1032032.2 | I69: =H69-H65 -> 7448.28 | J69: =H69-H68 -> 253.32 | K69: =J69/H69 -> 0.00024545746 | L69: =I69/G69 -> 2618.0246 | M69: =L69+AK69 -> 5390.4246 | N69: =AK69-L69 -> 154.3754 | O69: =I69/H69 -> 0.0072171005 | P69: =(H69-H65)/H65 -> 0.0072695657 | Q69: =(H69-H16)/H16 -> 0.12096943 | S69: =(C69-C65)/C65 -> 0.0066958504 | T69: =(C69-C16)/C16 -> 0.062841814 | U69: =(C69-C56)/C56 -> 0.01357769 | V69: =(C69-C68)/(H69-H68) -> -0.25809253 | W69: =(C69-C65)/(H69-H65) -> 0.34607453 | X69: =(D69-D65)/D65 -> 0.007614848 | Y69: =(D69-D16)/D16 -> 0.15908755 | Z69: =(D69-D56)/D56 -> 0.036432118 | AA69: =(D69-D68)/(H69-H68) -> 1.2580925 | AB69: =AVERAGE(AA57:AA69) -> 0.19112502 | AC69: =AVERAGE(V57:V69) -> 0.80887935 | AD69: =(D69-D65)/(H69-H65) -> 0.65392413 | AE69: =AVERAGE(H57:H69) -> 1020757.5 | AF69: =(AE69-AE65)/AE65 -> 0.0065038899 | AG69: =(AE69-AE16)/AE16 -> 0.13796837 | AI69: =F69*G69 -> 479048.58 | AJ69: =(AI69-AI65)/AI65 -> 0.0042169208 | AK69: =(F69-F65) -> 2772.4 | AL69: =F69-F68 -> -268.24 | AM69: =AL69*G69 -> -763.1428 | AN69: =AK69*G69 -> 7887.478 | AO69: =(E69+F69)*G69 -> 479371.86 | AP69: =H69/AO69 -> 2.1528844
B70: 42475 | C70: 387745.26 | D70: 650754.85 | E70: 116.73 | F70: 168275.17 | G70: 2.83758 | H70: 1038500.1 | I70: =H70-H66 -> 14981.85 | J70: =H70-H69 -> 6467.92 | K70: =J70/H70 -> 0.0062281361 | L70: =I70/G70 -> 5279.7983 | M70: =L70+AK70 -> 6548.0283 | N70: =AK70-L70 -> -4011.5683 | O70: =I70/H70 -> 0.014426431 | P70: =(H70-H66)/H66 -> 0.014637599 | Q70: =(H70-H17)/H17 -> 0.11958253 | S70: =(C70-C66)/C66 -> 0.01013216 | T70: =(C70-C17)/C17 -> 0.061712292 | U70: =(C70-C57)/C57 -> 0.015831605 | V70: =(C70-C69)/(H70-H69) -> 0.031509357 | W70: =(C70-C66)/(H70-H66) -> 0.25960012 | X70: =(D70-D66)/D66 -> 0.017341276 | Y70: =(D70-D17)/D17 -> 0.15716385 | Z70: =(D70-D57)/D57 -> 0.033250951 | AA70: =(D70-D69)/(H70-H69) -> 0.96849064 | AB70: =AVERAGE(AA58:AA70) -> 0.18190301 | AC70: =AVERAGE(V58:V70) -> 0.81810125 | AD70: =(D70-D66)/(H70-H66) -> 0.74039988 | AE70: =AVERAGE(H58:H70) -> 1022833.2 | AF70: =(AE70-AE66)/AE66 -> 0.0069966247 | AG70: =(AE70-AE17)/AE17 -> 0.13506557 | AI70: =F70*G70 -> 477494.26 | AJ70: =(AI70-AI66)/AI66 -> -0.0034686273 | AK70: =(F70-F66) -> 1268.23 | AL70: =F70-F69 -> -107.46 | AM70: =AL70*G70 -> -304.92635 | AN70: =AK70*G70 -> 3598.7041 | AO70: =(E70+F70)*G70 -> 477825.49 | AP70: =H70/AO70 -> 2.1733879
B71: 42482 | C71: 387708.37 | D71: 646564.33 | E71: 118.77 | F71: 168475.37 | G71: 2.82828 | H71: 1034272.7 | I71: =H71-H67 -> 9124.16 | J71: =H71-H70 -> -4227.42 | K71: =J71/H71 -> -0.004087336 | L71: =I71/G71 -> 3226.0455 | M71: =L71+AK71 -> 4969.1255 | N71: =AK71-L71 -> -1482.9655 | O71: =I71/H71 -> 0.0088218127 | P71: =(H71-H67)/H67 -> 0.0089003298 | Q71: =(H71-H18)/H18 -> 0.11563597 | S71: =(C71-C67)/C67 -> 0.006696425 | T71: =(C71-C18)/C18 -> 0.062333635 | U71: =(C71-C58)/C58 -> 0.017709202 | V71: =(C71-C70)/(H71-H70) -> 0.0087263627 | W71: =(C71-C67)/(H71-H67) -> 0.28265506 | X71: =(D71-D67)/D67 -> 0.010226554 | Y71: =(D71-D18)/D18 -> 0.15024334 | Z71: =(D71-D58)/D58 -> 0.033018043 | AA71: =(D71-D70)/(H71-H70) -> 0.99127127 | AB71: =AVERAGE(AA59:AA71) -> 0.1934673 | AC71: =AVERAGE(V59:V71) -> 0.80653662 | AD71: =(D71-D67)/(H71-H67) -> 0.71734713 | AE71: =AVERAGE(H59:H71) -> 1024941.9 | AF71: =(AE71-AE67)/AE67 -> 0.0076072551 | AG71: =(AE71-AE18)/AE18 -> 0.13281065 | AI71: =F71*G71 -> 476495.52 | AJ71: =(AI71-AI67)/AI67 -> 0.0012359749 | AK71: =(F71-F67) -> 1743.08 | AL71: =F71-F70 -> 200.2 | AM71: =AL71*G71 -> 566.22166 | AN71: =AK71*G71 -> 4929.9183 | AO71: =(E71+F71)*G71 -> 476831.43 | AP71: =H71/AO71 -> 2.1690531
B72: 42489 | C72: 390041.03 | D72: 651195.81 | E72: 117.46 | F72: 169908.25 | G72: 2.93836 | H72: 1041236.8 | I72: =H72-H68 -> 9457.97 | J72: =H72-H71 -> 6964.15 | K72: =J72/H72 -> 0.0066883438 | L72: =I72/G72 -> 3218.7921 | M72: =L72+AK72 -> 4476.1721 | N72: =AK72-L72 -> -1961.4121 | O72: =I72/H72 -> 0.0090833993 | P72: =(H72-H68)/H68 -> 0.0091666638 | Q72: =(H72-H19)/H19 -> 0.12052643 | S72: =(C72-C68)/C68 -> 0.0062800491 | T72: =(C72-C19)/C19 -> 0.064353194 | U72: =(C72-C59)/C59 -> 0.018283896 | V72: =(C72-C71)/(H72-H71) -> 0.33495258 | W72: =(C72-C68)/(H72-H68) -> 0.25736918 | X72: =(D72-D68)/D68 -> 0.010903578 | Y72: =(D72-D19)/D19 -> 0.157104 | Z72: =(D72-D59)/D59 -> 0.02921429 | AA72: =(D72-D71)/(H72-H71) -> 0.66504599 | AB72: =AVERAGE(AA60:AA72) -> 0.18566477 | AC72: =AVERAGE(V60:V72) -> 0.81433895 | AD72: =(D72-D68)/(H72-H68) -> 0.74263082 | AE72: =AVERAGE(H60:H72) -> 1026902.5 | AF72: =(AE72-AE68)/AE68 -> 0.0081355643 | AG72: =(AE72-AE19)/AE19 -> 0.13002255 | AI72: =F72*G72 -> 499251.61 | AJ72: =(AI72-AI68)/AI68 -> 0.046008566 | AK72: =(F72-F68) -> 1257.38 | AL72: =F72-F71 -> 1432.88 | AM72: =AL72*G72 -> 4210.3173 | AN72: =AK72*G72 -> 3694.6351 | AO72: =(E72+F72)*G72 -> 499596.75 | AP72: =H72/AO72 -> 2.0841546
B73: 42496 | C73: 390181.3 | D73: 652541.68 | E73: 115.64 | F73: 170472.9 | G73: 2.968 | H73: 1042723 | I73: =H73-H69 -> 10690.78 | J73: =H73-H72 -> 1486.13 | K73: =J73/H73 -> 0.0014252395 | L73: =I73/G73 -> 3602.0148 | M73: =L73+AK73 -> 5692.2848 | N73: =AK73-L73 -> -1511.7448 | O73: =I73/H73 -> 0.010252752 | P73: =(H73-H69)/H69 -> 0.01035896 | Q73: =(H73-H20)/H20 -> 0.10931886 | S73: =(C73-C69)/C69 -> 0.0068117615 | T73: =(C73-C20)/C20 -> 0.058402331 | U73: =(C73-C60)/C60 -> 0.017346909 | V73: =(C73-C72)/(H73-H72) -> 0.09438609 | W73: =(C73-C69)/(H73-H69) -> 0.24692679 | X73: =(D73-D69)/D69 -> 0.012491956 | Y73: =(D73-D20)/D20 -> 0.14217365 | Z73: =(D73-D60)/D60 -> 0.033516125 | AA73: =(D73-D72)/(H73-H72) -> 0.90562064 | AB73: =AVERAGE(AA61:AA73) -> 0.1335084 | AC73: =AVERAGE(V61:V73) -> 0.86649584 | AD73: =(D73-D69)/(H73-H69) -> 0.75307414 | AE73: =AVERAGE(H61:H73) -> 1029042 | AF73: =(AE73-AE69)/AE69 -> 0.0081160972 | AG73: =(AE73-AE20)/AE20 -> 0.12735697 | AI73: =F73*G73 -> 505963.57 | AJ73: =(AI73-AI69)/AI69 -> 0.056184249 | AK73: =(F73-F69) -> 2090.27 | AL73: =F73-F72 -> 564.65 | AM73: =AL73*G73 -> 1675.8812 | AN73: =AK73*G73 -> 6203.9214 | AO73: =(E73+F73)*G73 -> 506306.79 | AP73: =H73/AO73 -> 2.0594687
B74: 42503 | C74: 392173.84 | D74: 652660.1 | E74: 117.16 | F74: 170147.99 | G74: 2.9638 | H74: 1044833.9 | I74: =H74-H70 -> 6333.83 | J74: =H74-H73 -> 2110.97 | K74: =J74/H74 -> 0.002020388 | L74: =I74/G74 -> 2137.0639 | M74: =L74+AK74 -> 4009.8839 | N74: =AK74-L74 -> -264.2439 | O74: =I74/H74 -> 0.0060620447 | P74: =(H74-H70)/H70 -> 0.0060990172 | Q74: =(H74-H21)/H21 -> 0.11499304 | S74: =(C74-C70)/C70 -> 0.011421365 | T74: =(C74-C21)/C21 -> 0.066511025 | U74: =(C74-C61)/C61 -> 0.019050049 | V74: =(C74-C73)/(H74-H73) -> 0.94389783 | W74: =(C74-C70)/(H74-H70) -> 0.69919464 | X74: =(D74-D70)/D70 -> 0.0029277538 | Y74: =(D74-D21)/D21 -> 0.14630476 | Z74: =(D74-D61)/D61 -> 0.029992039 | AA74: =(D74-D73)/(H74-H73) -> 0.056097434 | AB74: =AVERAGE(AA62:AA74) -> 0.089065696 | AC74: =AVERAGE(V62:V74) -> 0.91093796 | AD74: =(D74-D70)/(H74-H70) -> 0.30080536 | AE74: =AVERAGE(H62:H74) -> 1031067.9 | AF74: =(AE74-AE70)/AE70 -> 0.0080508222 | AG74: =(AE74-AE21)/AE21 -> 0.12489948 | AI74: =F74*G74 -> 504284.61 | AJ74: =(AI74-AI70)/AI70 -> 0.056106132 | AK74: =(F74-F70) -> 1872.82 | AL74: =F74-F73 -> -324.91 | AM74: =AL74*G74 -> -962.96826 | AN74: =AK74*G74 -> 5550.6639 | AO74: =(E74+F74)*G74 -> 504631.85 | AP74: =H74/AO74 -> 2.0704875
B75: 42510 | C75: 390181.69 | D75: 654297.2 | E75: 121.81 | F75: 169738.55 | G75: 2.94712 | H75: 1044478.9 | I75: =H75-H71 -> 10206.2 | J75: =H75-H74 -> -355.05 | K75: =J75/H75 -> -0.00033993028 | L75: =I75/G75 -> 3463.1097 | M75: =L75+AK75 -> 4726.2897 | N75: =AK75-L75 -> -2199.9297 | O75: =I75/H75 -> 0.0097715714 | P75: =(H75-H71)/H71 -> 0.0098679972 | Q75: =(H75-H22)/H22 -> 0.10624367 | S75: =(C75-C71)/C71 -> 0.0063793309 | T75: =(C75-C22)/C22 -> 0.058459118 | U75: =(C75-C62)/C62 -> 0.018633727 | V75: =(C75-C74)/(H75-H74) -> 5.6108999 | W75: =(C75-C71)/(H75-H71) -> 0.24233505 | X75: =(D75-D71)/D71 -> 0.011959939 | Y75: =(D75-D22)/D22 -> 0.1368498 | Z75: =(D75-D62)/D62 -> 0.0299994 | AA75: =(D75-D74)/(H75-H74) -> -4.6108999 | AB75: =AVERAGE(AA63:AA75) -> 0.30535625 | AC75: =AVERAGE(V63:V75) -> 0.69464381 | AD75: =(D75-D71)/(H75-H71) -> 0.75766397 | AE75: =AVERAGE(H63:H75) -> 1033082.8 | AF75: =(AE75-AE71)/AE71 -> 0.0079428406 | AG75: =(AE75-AE22)/AE22 -> 0.12248152 | AI75: =F75*G75 -> 500239.88 | AJ75: =(AI75-AI71)/AI71 -> 0.049831226 | AK75: =(F75-F71) -> 1263.18 | AL75: =F75-F74 -> -409.44 | AM75: =AL75*G75 -> -1206.6688 | AN75: =AK75*G75 -> 3722.743 | AO75: =(E75+F75)*G75 -> 500598.86 | AP75: =H75/AO75 -> 2.0864588
B76: 42517 | C76: 392308.54 | D76: 661214.12 | E76: 116.75 | F76: 170558.86 | G76: 2.9071 | H76: 1053522.7 | I76: =H76-H72 -> 12285.82 | J76: =H76-H75 -> 9043.77 | K76: =J76/H76 -> 0.0085843146 | L76: =I76/G76 -> 4226.1429 | M76: =L76+AK76 -> 4876.7529 | N76: =AK76-L76 -> -3575.5329 | O76: =I76/H76 -> 0.011661657 | P76: =(H76-H72)/H72 -> 0.011799256 | Q76: =(H76-H23)/H23 -> 0.11810484 | S76: =(C76-C72)/C72 -> 0.0058135166 | T76: =(C76-C23)/C23 -> 0.064836866 | U76: =(C76-C63)/C63 -> 0.021268794 | V76: =(C76-C75)/(H76-H75) -> 0.23517294 | W76: =(C76-C72)/(H76-H72) -> 0.18456318 | X76: =(D76-D72)/D72 -> 0.015384482 | Y76: =(D76-D23)/D23 -> 0.15230564 | Z76: =(D76-D63)/D63 -> 0.030566476 | AA76: =(D76-D75)/(H76-H75) -> 0.76482706 | AB76: =AVERAGE(AA64:AA76) -> 0.29855444 | AC76: =AVERAGE(V64:V76) -> 0.70144562 | AD76: =(D76-D72)/(H76-H72) -> 0.81543682 | AE76: =AVERAGE(H64:H76) -> 1035219.9 | AF76: =(AE76-AE72)/AE72 -> 0.0080995183 | AG76: =(AE76-AE23)/AE23 -> 0.12035779 | AI76: =F76*G76 -> 495831.66 | AJ76: =(AI76-AI72)/AI72 -> -0.0068501403 | AK76: =(F76-F72) -> 650.61 | AL76: =F76-F75 -> 820.31 | AM76: =AL76*G76 -> 2384.7232 | AN76: =AK76*G76 -> 1891.3883 | AO76: =(E76+F76)*G76 -> 496171.07 | AP76: =H76/AO76 -> 2.1233053
B77: 42524 | C77: 394005.21 | D77: 658178.27 | E77: 100.58 | F77: 170543.63 | G77: 2.92376 | H77: 1052183.5 | I77: =H77-H73 -> 9460.5 | J77: =H77-H76 -> -1339.19 | K77: =J77/H77 -> -0.0012727723 | L77: =I77/G77 -> 3235.7307 | M77: =L77+AK77 -> 3306.4607 | N77: =AK77-L77 -> -3165.0007 | O77: =I77/H77 -> 0.0089913026 | P77: =(H77-H73)/H73 -> 0.0090728796 | Q77: =(H77-H24)/H24 -> 0.10556082 | S77: =(C77-C73)/C73 -> 0.0098003415 | T77: =(C77-C24)/C24 -> 0.061453892 | U77: =(C77-C64)/C64 -> 0.024028618 | V77: =(C77-C76)/(H77-H76) -> -1.2669375 | W77: =(C77-C73)/(H77-H73) -> 0.40419745 | X77: =(D77-D73)/D73 -> 0.0086379003 | Y77: =(D77-D24)/D24 -> 0.13376328 | Z77: =(D77-D64)/D64 -> 0.034109358 | AA77: =(D77-D76)/(H77-H76) -> 2.26693 | AB77: =AVERAGE(AA65:AA77) -> 0.38541441 | AC77: =AVERAGE(V65:V77) -> 0.61458525 | AD77: =(D77-D73)/(H77-H73) -> 0.59580255 | AE77: =AVERAGE(H65:H77) -> 1037601 | AF77: =(AE77-AE73)/AE73 -> 0.0083174257 | AG77: =(AE77-AE24)/AE24 -> 0.11846302 | AI77: =F77*G77 -> 498628.64 | AJ77: =(AI77-AI73)/AI73 -> -0.01449694 | AK77: =(F77-F73) -> 70.73 | AL77: =F77-F76 -> -15.23 | AM77: =AL77*G77 -> -44.528865 | AN77: =AK77*G77 -> 206.79754 | AO77: =(E77+F77)*G77 -> 498922.72 | AP77: =H77/AO77 -> 2.1089107
B78: 42531 | C78: 394623.65 | D78: 661554.94 | E78: 100.36 | F78: 171149.71 | G78: 2.902 | H78: 1056178.6 | I78: =H78-H74 -> 11344.66 | J78: =H78-H77 -> 3995.13 | K78: =J78/H78 -> 0.0037826273 | L78: =I78/G78 -> 3909.2557 | M78: =L78+AK78 -> 4910.9757 | N78: =AK78-L78 -> -2907.5357 | O78: =I78/H78 -> 0.010741233 | P78: =(H78-H74)/H74 -> 0.010857859 | Q78: =(H78-H25)/H25 -> 0.10532728 | S78: =(C78-C74)/C74 -> 0.0062467451 | T78: =(C78-C25)/C25 -> 0.061211137 | U78: =(C78-C65)/C65 -> 0.025092879 | V78: =(C78-C77)/(H78-H77) -> 0.15479847 | W78: =(C78-C74)/(H78-H74) -> 0.21594389 | X78: =(D78-D74)/D74 -> 0.013628595 | Y78: =(D78-D25)/D25 -> 0.13343393 | Z78: =(D78-D65)/D65 -> 0.034293512 | AA78: =(D78-D77)/(H78-H77) -> 0.84519653 | AB78: =AVERAGE(AA66:AA78) -> 0.37817975 | AC78: =AVERAGE(V66:V78) -> 0.62181952 | AD78: =(D78-D74)/(H78-H74) -> 0.78405523 | AE78: =AVERAGE(H66:H78) -> 1040031.4 | AF78: =(AE78-AE74)/AE74 -> 0.008693417 | AG78: =(AE78-AE25)/AE25 -> 0.11635904 | AI78: =F78*G78 -> 496676.46 | AJ78: =(AI78-AI74)/AI74 -> -0.015087025 | AK78: =(F78-F74) -> 1001.72 | AL78: =F78-F77 -> 606.08 | AM78: =AL78*G78 -> 1758.8442 | AN78: =AK78*G78 -> 2906.9914 | AO78: =(E78+F78)*G78 -> 496967.7 | AP78: =H78/AO78 -> 2.125246
B79: 42538 | C79: 392992.16 | D79: 662891.74 | E79: 105.01 | F79: 171320.68 | G79: 2.9109 | H79: 1055883.9 | I79: =H79-H75 -> 11405.01 | J79: =H79-H78 -> -294.7 | K79: =J79/H79 -> -0.00027910266 | L79: =I79/G79 -> 3918.0357 | M79: =L79+AK79 -> 5500.1657 | N79: =AK79-L79 -> -2335.9057 | O79: =I79/H79 -> 0.010801386 | P79: =(H79-H75)/H75 -> 0.01091933 | Q79: =(H79-H26)/H26 -> 0.099750838 | S79: =(C79-C75)/C75 -> 0.0072029777 | T79: =(C79-C26)/C26 -> 0.050903098 | U79: =(C79-C66)/C66 -> 0.023801089 | V79: =(C79-C78)/(H79-H78) -> 5.5361045 | W79: =(C79-C75)/(H79-H75) -> 0.24642416 | X79: =(D79-D75)/D75 -> 0.013135529 | Y79: =(D79-D26)/D26 -> 0.13091482 | Z79: =(D79-D66)/D66 -> 0.036315178 | AA79: =(D79-D78)/(H79-H78) -> -4.5361384 | AB79: =AVERAGE(AA67:AA79) -> 0.032290028 | AC79: =AVERAGE(V67:V79) -> 0.96770591 | AD79: =(D79-D75)/(H79-H75) -> 0.75357584 | AE79: =AVERAGE(H67:H79) -> 1042521.1 | AF79: =(AE79-AE75)/AE75 -> 0.0091359723 | AG79: =(AE79-AE26)/AE26 -> 0.11430158 | AI79: =F79*G79 -> 498697.37 | AJ79: =(AI79-AI75)/AI75 -> -0.0030835368 | AK79: =(F79-F75) -> 1582.13 | AL79: =F79-F78 -> 170.97 | AM79: =AL79*G79 -> 497.67657 | AN79: =AK79*G79 -> 4605.4222 | AO79: =(E79+F79)*G79 -> 499003.04 | AP79: =H79/AO79 -> 2.1159869
... B85: 42580 | C85: 394385.24 | D85: 675059.03 | E85: 100.69 | F85: 171394.27 | G85: 2.97594 | H85: 1069444.3 | I85: =H85-H81 -> -2357.3 | J85: =H85-H84 -> 3074.31 | K85: =J85/H85 -> 0.0028746799 | L85: =I85/G85 -> -792.11946 | M85: =L85+AK85 -> -691.47946 | N85: =AK85-L85 -> 892.75946 | O85: =I85/H85 -> -0.0022042289 | P85: =(H85-H81)/H81 -> -0.002199381 | Q85: =(H85-H32)/H32 -> 0.1044536 | S85: =(C85-C81)/C81 -> -0.005924348 | T85: =(C85-C32)/C32 -> 0.055264764 | U85: =(C85-C72)/C72 -> 0.011137828 | V85: =(C85-C84)/(H85-H84) -> 0.097169771 | W85: =(C85-C81)/(H85-H81) -> 0.99707292 | X85: =(D85-D81)/D81 -> -1.0221224e-05 | Y85: =(D85-D32)/D32 -> 0.13537239 | Z85: =(D85-D72)/D72 -> 0.03664523 | AA85: =(D85-D84)/(H85-H84) -> 0.90283023 | AB85: =AVERAGE(AA73:AA85) -> 0.090054892 | AC85: =AVERAGE(V73:V85) -> 0.90994305 | AD85: =(D85-D81)/(H85-H81) -> 0.0029270776 | AE85: =AVERAGE(H73:H85) -> 1057777.7 | AF85: =(AE85-AE81)/AE81 -> 0.0091087103 | AG85: =(AE85-AE32)/AE32 -> 0.10616607 | AI85: =F85*G85 -> 510059.06 | AJ85: =(AI85-AI81)/AI81 -> 0.027214175 | AK85: =(F85-F81) -> 100.64 | AL85: =F85-F84 -> 988.59 | AM85: =AL85*G85 -> 2941.9845 | AN85: =AK85*G85 -> 299.4986 | AO85: =(E85+F85)*G85 -> 510358.71 | AP85: =H85/AO85 -> 2.0954757
B86: 42587 | C86: 394577.86 | D86: 673310.28 | E86: 96.51 | F86: 171518.75 | G86: 2.93868 | H86: 1067888.1 | I86: =H86-H82 -> 1304.68 | J86: =H86-H85 -> -1556.13 | K86: =J86/H86 -> -0.0014572032 | L86: =I86/G86 -> 443.96804 | M86: =L86+AK86 -> 1321.848 | N86: =AK86-L86 -> 433.91196 | O86: =I86/H86 -> 0.0012217384 | P86: =(H86-H82)/H82 -> 0.0012232329 | Q86: =(H86-H33)/H33 -> 0.081680957 | S86: =(C86-C82)/C82 -> -0.0052960746 | T86: =(C86-C33)/C33 -> 0.046871374 | U86: =(C86-C73)/C73 -> 0.011267993 | V86: =(C86-C85)/(H86-H85) -> -0.12378143 | W86: =(C86-C82)/(H86-H82) -> -1.6102339 | X86: =(D86-D82)/D82 -> 0.0050835883 | Y86: =(D86-D33)/D33 -> 0.1031775 | Z86: =(D86-D73)/D73 -> 0.031827239 | AA86: =(D86-D85)/(H86-H85) -> 1.1237814 | AB86: =AVERAGE(AA74:AA86) -> 0.10683649 | AC86: =AVERAGE(V74:V86) -> 0.89316093 | AE86: =AVERAGE(H74:H86) -> 1059713.5 | AF86: =(AE86-AE82)/AE82 -> 0.0083986278 | AG86: =(AE86-AE33)/AE33 -> 0.10399144 | AI86: =F86*G86 -> 504038.72 | AJ86: =(AI86-AI82)/AI82 -> -0.0094107872 | AK86: =(F86-F82) -> 877.88 | AL86: =F86-F85 -> 124.48 | AM86: =AL86*G86 -> 365.80689 | AN86: =AK86*G86 -> 2579.8084 | AO86: =(E86+F86)*G86 -> 504322.33 | AP86: =H86/AO86 -> 2.1174714
B87: 42594 | C87: 396038.02 | D87: 673895.61 | E87: 94.98 | F87: 172040.62 | G87: 2.94162 | H87: 1069933.6 | I87: =H87-H83 -> 2165.22 | J87: =H87-H86 -> 2045.49 | K87: =J87/H87 -> 0.0019117915 | L87: =I87/G87 -> 736.0638 | M87: =L87+AK87 -> 2667.3238 | N87: =AK87-L87 -> 1195.1962 | O87: =I87/H87 -> 0.0020236956 | P87: =(H87-H83)/H83 -> 0.0020277993 | Q87: =(H87-H34)/H34 -> 0.09715095 | S87: =(C87-C83)/C83 -> 0.0018380952 | T87: =(C87-C34)/C34 -> 0.050298836 | U87: =(C87-C74)/C74 -> 0.0098532324 | V87: =(C87-C86)/(H87-H86) -> 0.71384363 | W87: =(C87-C83)/(H87-H83) -> 0.33558715 | X87: =(D87-D83)/D83 -> 0.002139304 | Y87: =(D87-D34)/D34 -> 0.1266878 | Z87: =(D87-D74)/D74 -> 0.03253686 | AA87: =(D87-D86)/(H87-H86) -> 0.28615637 | AB87: =AVERAGE(AA75:AA87) -> 0.12453333 | AC87: =AVERAGE(V75:V87) -> 0.87546446 | AD87: =(D87-D83)/(H87-H83) -> 0.66440824 | AE87: =AVERAGE(H75:H87) -> 1061644.3 | AF87: =(AE87-AE83)/AE83 -> 0.0080761908 | AG87: =(AE87-AE34)/AE34 -> 0.10263484 | AI87: =F87*G87 -> 506078.13 | AJ87: =(AI87-AI83)/AI83 -> -0.020002913 | AK87: =(F87-F83) -> 1931.26 | AL87: =F87-F86 -> 521.87 | AM87: =AL87*G87 -> 1535.1432 | AN87: =AK87*G87 -> 5681.033 | AO87: =(E87+F87)*G87 -> 506357.52 | AP87: =H87/AO87 -> 2.1130004
B88: 42601 | C88: 394830.92 | D88: 676236.2 | E88: 97.22 | F88: 173529.51 | G88: 2.9496 | H88: 1071067.1 | I88: =H88-H84 -> 4697.17 | J88: =H88-H87 -> 1133.5 | K88: =J88/H88 -> 0.0010582903 | L88: =I88/G88 -> 1592.4769 | M88: =L88+AK88 -> 4716.3069 | N88: =AK88-L88 -> 1531.3531 | O88: =I88/H88 -> 0.0043855048 | P88: =(H88-H84)/H84 -> 0.0044048221 | Q88: =(H88-H35)/H35 -> 0.095552599 | S88: =(C88-C84)/C84 -> 0.0018889507 | T88: =(C88-C35)/C35 -> 0.041584951 | U88: =(C88-C75)/C75 -> 0.011915551 | V88: =(C88-C87)/(H88-H87) -> -1.0649316 | W88: =(C88-C84)/(H88-H84) -> 0.15848053 | X88: =(D88-D84)/D84 -> 0.0058795884 | Y88: =(D88-D35)/D35 -> 0.12972894 | Z88: =(D88-D75)/D75 -> 0.033530634 | AA88: =(D88-D87)/(H88-H87) -> 2.0649228 | AB88: =AVERAGE(AA76:AA88) -> 0.63805815 | AC88: =AVERAGE(V76:V88) -> 0.36193896 | AD88: =(D88-D84)/(H88-H84) -> 0.84151734 | AE88: =AVERAGE(H76:H88) -> 1063689.5 | AF88: =(AE88-AE84)/AE84 -> 0.007655853 | AG88: =(AE88-AE35)/AE35 -> 0.10181164 | AI88: =F88*G88 -> 511842.64 | AJ88: =(AI88-AI84)/AI84 -> 0.00031679775 | AK88: =(F88-F84) -> 3123.83 | AL88: =F88-F87 -> 1488.89 | AM88: =AL88*G88 -> 4391.6299 | AN88: =AK88*G88 -> 9214.049 | AO88: =(E88+F88)*G88 -> 512129.4 | AP88: =H88/AO88 -> 2.0913994
B89: 42608 | C89: 397108.12 | D89: 682995.77 | E89: 93.61 | F89: 173550.99 | G89: 2.94092 | H89: 1080103.9 | I89: =H89-H85 -> 10659.62 | J89: =H89-H88 -> 9036.76 | K89: =J89/H89 -> 0.0083665656 | L89: =I89/G89 -> 3624.5869 | M89: =L89+AK89 -> 5781.3069 | N89: =AK89-L89 -> -1467.8669 | O89: =I89/H89 -> 0.0098690692 | P89: =(H89-H85)/H85 -> 0.0099674385 | Q89: =(H89-H36)/H36 -> 0.10343535 | S89: =(C89-C85)/C85 -> 0.0069041123 | T89: =(C89-C36)/C36 -> 0.053790598 | U89: =(C89-C76)/C76 -> 0.012234197 | V89: =(C89-C88)/(H89-H88) -> 0.25199297 | W89: =(C89-C85)/(H89-H85) -> 0.25543875 | X89: =(D89-D85)/D85 -> 0.011757105 | Y89: =(D89-D36)/D36 -> 0.13451085 | Z89: =(D89-D76)/D76 -> 0.032941901 | AA89: =(D89-D88)/(H89-H88) -> 0.74800814 | AB89: =AVERAGE(AA77:AA89) -> 0.63676439 | AC89: =AVERAGE(V77:V89) -> 0.36323281 | AD89: =(D89-D85)/(H89-H85) -> 0.74456125 | AE89: =AVERAGE(H77:H89) -> 1065734.2 | AF89: =(AE89-AE85)/AE85 -> 0.0075218892 | AG89: =(AE89-AE36)/AE36 -> 0.10071822 | AI89: =F89*G89 -> 510399.58 | AJ89: =(AI89-AI85)/AI85 -> 0.0006675965 | AK89: =(F89-F85) -> 2156.72 | AL89: =F89-F88 -> 21.48 | AM89: =AL89*G89 -> 63.170962 | AN89: =AK89*G89 -> 6342.741 | AO89: =(E89+F89)*G89 -> 510674.88 | AP89: =H89/AO89 -> 2.1150519
B90: 42615 | C90: 399661.81 | D90: 676653.1 | E90: 96.04 | F90: 172848.49 | G90: 2.9552 | H90: 1076314.9 | I90: =H90-H86 -> 8426.77 | J90: =H90-H89 -> -3788.98 | K90: =J90/H90 -> -0.0035203266 | L90: =I90/G90 -> 2851.5058 | M90: =L90+AK90 -> 4181.2458 | N90: =AK90-L90 -> -1521.7658 | O90: =I90/H90 -> 0.0078292793 | P90: =(H90-H86)/H86 -> 0.0078910606 | Q90: =(H90-H37)/H37 -> 0.092790231 | S90: =(C90-C86)/C86 -> 0.012884529 | T90: =(C90-C37)/C37 -> 0.054569405 | U90: =(C90-C77)/C77 -> 0.014356663 | V90: =(C90-C89)/(H90-H89) -> -0.67397822 | W90: =(C90-C86)/(H90-H86) -> 0.60330945 | X90: =(D90-D86)/D86 -> 0.0049647541 | Y90: =(D90-D37)/D37 -> 0.11669508 | Z90: =(D90-D77)/D77 -> 0.028069644 | AA90: =(D90-D89)/(H90-H89) -> 1.6739782 | AB90: =AVERAGE(AA78:AA90) -> 0.59115271 | AC90: =AVERAGE(V78:V90) -> 0.40884506 | AD90: =(D90-D86)/(H90-H86) -> 0.39669055 | AE90: =AVERAGE(H78:H90) -> 1067590.5 | AF90: =(AE90-AE86)/AE86 -> 0.007433112 | AG90: =(AE90-AE37)/AE37 -> 0.099734287 | AI90: =F90*G90 -> 510801.86 | AJ90: =(AI90-AI86)/AI86 -> 0.013417893 | AK90: =(F90-F86) -> 1329.74 | AL90: =F90-F89 -> -702.5 | AM90: =AL90*G90 -> -2076.028 | AN90: =AK90*G90 -> 3929.6476 | AO90: =(E90+F90)*G90 -> 511085.68 | AP90: =H90/AO90 -> 2.1059383
B91: 42622 | C91: 398999.14 | D91: 679697.32 | E91: 94.27 | F91: 173881.93 | G91: 2.96732 | H91: 1078696.5 | I91: =H91-H87 -> 8762.84 | J91: =H91-H90 -> 2381.56 | K91: =J91/H91 -> 0.0022078129 | L91: =I91/G91 -> 2953.1159 | M91: =L91+AK91 -> 4794.4259 | N91: =AK91-L91 -> -1111.8059 | O91: =I91/H91 -> 0.0081235456 | P91: =(H91-H87)/H87 -> 0.0081900781 | Q91: =(H91-H38)/H38 -> 0.096455953 | S91: =(C91-C87)/C87 -> 0.0074768579 | T91: =(C91-C38)/C38 -> 0.050799995 | U91: =(C91-C78)/C78 -> 0.011087754 | V91: =(C91-C90)/(H91-H90) -> -0.27825039 | W91: =(C91-C87)/(H91-H87) -> 0.33791784 | X91: =(D91-D87)/D87 -> 0.0086092117 | Y91: =(D91-D38)/D38 -> 0.12515354 | Z91: =(D91-D78)/D78 -> 0.027423845 | AA91: =(D91-D90)/(H91-H90) -> 1.2782462 | AB91: =AVERAGE(AA79:AA91) -> 0.62446423 | AC91: =AVERAGE(V79:V91) -> 0.37553361 | AD91: =(D91-D87)/(H91-H87) -> 0.66208101 | AE91: =AVERAGE(H79:H91) -> 1069322.6 | AF91: =(AE91-AE87)/AE87 -> 0.0072325241 | AG91: =(AE91-AE38)/AE38 -> 0.099056762 | AI91: =F91*G91 -> 515963.33 | AJ91: =(AI91-AI87)/AI87 -> 0.019532952 | AK91: =(F91-F87) -> 1841.31 | AL91: =F91-F90 -> 1033.44 | AM91: =AL91*G91 -> 3066.5472 | AN91: =AK91*G91 -> 5463.756 | AO91: =(E91+F91)*G91 -> 516243.06 | AP91: =H91/AO91 -> 2.0895128
B92: 42629 | C92: 398666.23 | D92: 680686.23 | E92: 108.48 | F92: 173256.45 | G92: 2.97504 | H92: 1079352.4 | I92: =H92-H88 -> 8285.32 | J92: =H92-H91 -> 655.98 | K92: =J92/H92 -> 0.00060775329 | L92: =I92/G92 -> 2784.9441 | M92: =L92+AK92 -> 2511.8841 | N92: =AK92-L92 -> -3058.0041 | O92: =I92/H92 -> 0.0076761951 | P92: =(H92-H88)/H88 -> 0.0077355749 | Q92: =(H92-H39)/H39 -> 0.091849586 | S92: =(C92-C88)/C88 -> 0.0097138036 | T92: =(C92-C39)/C39 -> 0.046862721 | U92: =(C92-C79)/C79 -> 0.014438125 | V92: =(C92-C91)/(H92-H91) -> -0.50750023 | W92: =(C92-C88)/(H92-H88) -> 0.46290427 | X92: =(D92-D88)/D88 -> 0.0065805853 | Y92: =(D92-D39)/D39 -> 0.12003939 | Z92: =(D92-D79)/D79 -> 0.026843735 | AA92: =(D92-D91)/(H92-H91) -> 1.5075307 | AB92: =AVERAGE(AA80:AA92) -> 1.0893619 | AC92: =AVERAGE(V80:V92) -> -0.089359066 | AD92: =(D92-D88)/(H92-H88) -> 0.53709814 | AE92: =AVERAGE(H80:H92) -> 1071127.9 | AF92: =(AE92-AE88)/AE88 -> 0.0069930101 | AG92: =(AE92-AE39)/AE39 -> 0.098442166 | AI92: =F92*G92 -> 515444.87 | AJ92: =(AI92-AI88)/AI88 -> 0.0070377612 | AK92: =(F92-F88) -> -273.06 | AL92: =F92-F91 -> -625.48 | AM92: =AL92*G92 -> -1860.828 | AN92: =AK92*G92 -> -812.36442 | AO92: =(E92+F92)*G92 -> 515767.6 | AP92: =H92/AO92 -> 2.0927108
B93: 42636 | C93: 399519.72 | D93: 673274.88 | E93: 115.5 | F93: 173472.91 | G93: 3.02752 | H93: 1072794.6 | I93: =H93-H89 -> -7309.3 | J93: =H93-H92 -> -6557.86 | K93: =J93/H93 -> -0.0061128757 | L93: =I93/G93 -> -2414.2863 | M93: =L93+AK93 -> -2492.3663 | N93: =AK93-L93 -> 2336.2063 | O93: =I93/H93 -> -0.0068133267 | P93: =(H93-H89)/H89 -> -0.0067672194 | Q93: =(H93-H40)/H40 -> 0.085587105 | S93: =(C93-C89)/C89 -> 0.0060729053 | T93: =(C93-C40)/C40 -> 0.052021931 | U93: =(C93-C80)/C80 -> 0.01180494 | V93: =(C93-C92)/(H93-H92) -> -0.13014764 | W93: =(C93-C89)/(H93-H89) -> -0.32993584 | X93: =(D93-D89)/D89 -> -0.014232724 | Y93: =(D93-D40)/D40 -> 0.10653672 | Z93: =(D93-D80)/D80 -> 0.013235642 | AA93: =(D93-D92)/(H93-H92) -> 1.1301476 | AB93: =AVERAGE(AA81:AA93) -> 1.1409293 | AC93: =AVERAGE(V81:V93) -> -0.14092673 | AE93: =AVERAGE(H81:H93) -> 1072163 | AF93: =(AE93-AE89)/AE89 -> 0.0060322414 | AG93: =(AE93-AE40)/AE40 -> 0.096960427 | AI93: =F93*G93 -> 525192.7 | AJ93: =(AI93-AI89)/AI89 -> 0.028983423 | AK93: =(F93-F89) -> -78.08 | AL93: =F93-F92 -> 216.46 | AM93: =AL93*G93 -> 655.33698 | AN93: =AK93*G93 -> -236.38876 | AO93: =(E93+F93)*G93 -> 525542.38 | AP93: =H93/AO93 -> 2.0413094
B94: 42643 | C94: 402837.32 | D94: 685866.99 | E94: 103.9 | F94: 174047.83 | G94: 3.0734 | H94: 1088704.3 | I94: =H94-H90 -> 12389.4 | J94: =H94-H93 -> 15909.72 | K94: =J94/H94 -> 0.014613444 | L94: =I94/G94 -> 4031.1707 | M94: =L94+AK94 -> 5230.5107 | N94: =AK94-L94 -> -2831.8307 | O94: =I94/H94 -> 0.011379949 | P94: =(H94-H90)/H90 -> 0.011510943 | Q94: =(H94-H41)/H41 -> 0.10478504 | S94: =(C94-C90)/C90 -> 0.0079454927 | T94: =(C94-C41)/C41 -> 0.058949557 | U94: =(C94-C81)/C81 -> 0.015379712 | V94: =(C94-C93)/(H94-H93) -> 0.20852661 | W94: =(C94-C90)/(H94-H90) -> 0.25630862 | X94: =(D94-D90)/D90 -> 0.013616859 | Y94: =(D94-D41)/D41 -> 0.13360396 | Z94: =(D94-D81)/D81 -> 0.016000008 | AA94: =(D94-D93)/(H94-H93) -> 0.79147276 | AB94: =AVERAGE(AA82:AA94) -> 1.136475 | AC94: =AVERAGE(V82:V94) -> -0.13647244 | AD94: =(D94-D90)/(H94-H90) -> 0.74369138 | AE94: =AVERAGE(H82:H94) -> 1073463.2 | AF94: =(AE94-AE90)/AE90 -> 0.0055009035 | AG94: =(AE94-AE41)/AE41 -> 0.096833415 | AI94: =F94*G94 -> 534918.6 | AJ94: =(AI94-AI90)/AI90 -> 0.047213499 | AK94: =(F94-F90) -> 1199.34 | AL94: =F94-F93 -> 574.92 | AM94: =AL94*G94 -> 1766.9591 | AN94: =AK94*G94 -> 3686.0516 | AO94: =(E94+F94)*G94 -> 535237.93 | AP94: =H94/AO94 -> 2.0340567
B95: 42650 | C95: 403189.05 | D95: 679688.33 | E95: 100.9 | F95: 174107.58 | G95: 3.08422 | H95: 1082877.4 | I95: =H95-H91 -> 4180.91 | J95: =H95-H94 -> -5826.93 | K95: =J95/H95 -> -0.0053809694 | L95: =I95/G95 -> 1355.581 | M95: =L95+AK95 -> 1581.231 | N95: =AK95-L95 -> -1129.931 | O95: =I95/H95 -> 0.0038609265 | P95: =(H95-H91)/H91 -> 0.0038758911 | Q95: =(H95-H42)/H42 -> 0.097615703 | S95: =(C95-C91)/C91 -> 0.01050105 | T95: =(C95-C42)/C42 -> 0.061240281 | U95: =(C95-C82)/C82 -> 0.016412149 | V95: =(C95-C94)/(H95-H94) -> -0.060362833 | W95: =(C95-C91)/(H95-H91) -> 1.0021526 | X95: =(D95-D91)/D91 -> -1.3226476e-05 | Y95: =(D95-D42)/D42 -> 0.12039629 | Z95: =(D95-D82)/D82 -> 0.014604419 | AA95: =(D95-D94)/(H95-H94) -> 1.0603628 | AB95: =AVERAGE(AA83:AA95) -> 1.1419577 | AC95: =AVERAGE(V83:V95) -> -0.14195512 | AE95: =AVERAGE(H83:H95) -> 1074716.6 | AF95: =(AE95-AE91)/AE91 -> 0.0050442652 | AG95: =(AE95-AE42)/AE42 -> 0.096456452 | AI95: =F95*G95 -> 536986.08 | AJ95: =(AI95-AI91)/AI91 -> 0.040744663 | AK95: =(F95-F91) -> 225.65 | AL95: =F95-F94 -> 59.75 | AM95: =AL95*G95 -> 184.28215 | AN95: =AK95*G95 -> 695.95424 | AO95: =(E95+F95)*G95 -> 537297.28 | AP95: =H95/AO95 -> 2.0154157
B96: 42657 | C96: 405786.41 | D96: 680392.92 | E96: 99.51 | F96: 173692.27 | G96: 3.08026 | H96: 1086179.3 | I96: =H96-H92 -> 6826.88 | J96: =H96-H95 -> 3301.95 | K96: =J96/H96 -> 0.0030399676 | L96: =I96/G96 -> 2216.3324 | M96: =L96+AK96 -> 2652.1524 | N96: =AK96-L96 -> -1780.5124 | O96: =I96/H96 -> 0.0062852236 | P96: =(H96-H92)/H92 -> 0.0063249775 | Q96: =(H96-H43)/H43 -> 0.098905091 | S96: =(C96-C92)/C92 -> 0.017860003 | T96: =(C96-C43)/C43 -> 0.068830118 | U96: =(C96-C83)/C83 -> 0.026498123 | V96: =(C96-C95)/(H96-H95) -> 0.78661397 | W96: =(C96-C92)/(H96-H92) -> 1.0429625 | X96: =(D96-D92)/D92 -> -0.00043090338 | Y96: =(D96-D43)/D43 -> 0.11766127 | Z96: =(D96-D83)/D83 -> 0.011801349 | AA96: =(D96-D95)/(H96-H95) -> 0.21338603 | AB96: =AVERAGE(AA84:AA96) -> 0.99268764 | AC96: =AVERAGE(V84:V96) -> 0.007314288 | AE96: =AVERAGE(H84:H96) -> 1076132.8 | AF96: =(AE96-AE92)/AE92 -> 0.0046725498 | AG96: =(AE96-AE43)/AE43 -> 0.096351444 | AI96: =F96*G96 -> 535017.35 | AJ96: =(AI96-AI92)/AI92 -> 0.037972019 | AK96: =(F96-F92) -> 435.82 | AL96: =F96-F95 -> -415.31 | AM96: =AL96*G96 -> -1279.2628 | AN96: =AK96*G96 -> 1342.4389 | AO96: =(E96+F96)*G96 -> 535323.87 | AP96: =H96/AO96 -> 2.0290135
B97: 42664 | C97: 403935.95 | D97: 681250.99 | E97: 100.84 | F97: 173474.9 | G97: 3.1049 | H97: 1085186.9 | I97: =H97-H93 -> 12392.35 | J97: =H97-H96 -> -992.39 | K97: =J97/H97 -> -0.0009144876 | L97: =I97/G97 -> 3991.2235 | M97: =L97+AK97 -> 3993.2135 | N97: =AK97-L97 -> -3989.2335 | O97: =I97/H97 -> 0.011419553 | P97: =(H97-H93)/H93 -> 0.011551466 | Q97: =(H97-H44)/H44 -> 0.096769683 | S97: =(C97-C93)/C93 -> 0.011053847 | T97: =(C97-C44)/C44 -> 0.068467346 | U97: =(C97-C84)/C84 -> 0.024993091 | V97: =(C97-C96)/(H97-H96) -> 1.86465 | W97: =(C97-C93)/(H97-H93) -> 0.35636744 | X97: =(D97-D93)/D93 -> 0.011846736 | Y97: =(D97-D44)/D44 -> 0.11427045 | Z97: =(D97-D84)/D84 -> 0.013338927 | AA97: =(D97-D96)/(H97-H96) -> -0.86464999 | AB97: =AVERAGE(AA85:AA97) -> 0.91662872 | AC97: =AVERAGE(V85:V97) -> 0.083372659 | AD97: =(D97-D93)/(H97-H93) -> 0.64363176 | AE97: =AVERAGE(H85:H97) -> 1077580.3 | AF97: =(AE97-AE93)/AE93 -> 0.0050526589 | AG97: =(AE97-AE44)/AE44 -> 0.095905386 | AI97: =F97*G97 -> 538622.22 | AJ97: =(AI97-AI93)/AI93 -> 0.025570638 | AK97: =(F97-F93) -> 1.99 | AL97: =F97-F96 -> -217.37 | AM97: =AL97*G97 -> -674.91211 | AN97: =AK97*G97 -> 6.178751 | AO97: =(E97+F97)*G97 -> 538935.32 | AP97: =H97/AO97 -> 2.0135755
B98: 42671 | C98: 406692.06 | D98: 684553.56 | E98: 95.41 | F98: 174302.89 | G98: 3.17058 | H98: 1091245.6 | I98: =H98-H94 -> 2541.31 | J98: =H98-H97 -> 6058.68 | K98: =J98/H98 -> 0.0055520773 | L98: =I98/G98 -> 801.52843 | M98: =L98+AK98 -> 1056.5884 | N98: =AK98-L98 -> -546.46843 | O98: =I98/H98 -> 0.0023288158 | P98: =(H98-H94)/H94 -> 0.0023342518 | Q98: =(H98-H45)/H45 -> 0.10397465 | S98: =(C98-C94)/C94 -> 0.0095689744 | T98: =(C98-C45)/C45 -> 0.075580169 | U98: =(C98-C85)/C85 -> 0.031205072 | V98: =(C98-C97)/(H98-H97) -> 0.45490272 | W98: =(C98-C94)/(H98-H94) -> 1.5168319 | X98: =(D98-D94)/D94 -> -0.0019149923 | Y98: =(D98-D45)/D45 -> 0.12156497 | Z98: =(D98-D85)/D85 -> 0.01406474 | AA98: =(D98-D97)/(H98-H97) -> 0.54509728 | AB98: =AVERAGE(AA86:AA98) -> 0.8891108 | AC98: =AVERAGE(V86:V98) -> 0.11089058 | AE98: =AVERAGE(H86:H98) -> 1079257.3 | AF98: =(AE98-AE94)/AE94 -> 0.0053975674 | AG98: =(AE98-AE45)/AE45 -> 0.095881873 | AI98: =F98*G98 -> 552641.26 | AJ98: =(AI98-AI94)/AI94 -> 0.033131501 | AK98: =(F98-F94) -> 255.06 | AL98: =F98-F97 -> 827.99 | AM98: =AL98*G98 -> 2625.2085 | AN98: =AK98*G98 -> 808.68813 | AO98: =(E98+F98)*G98 -> 552943.76 | AP98: =H98/AO98 -> 1.9735201
B99: 42678 | C99: 407914.54 | D99: 682743.79 | E99: 92.51 | F99: 175800.7 | G99: 3.28496 | H99: 1090658.3 | I99: =H99-H95 -> 7780.96 | J99: =H99-H98 -> -587.28 | K99: =J99/H99 -> -0.00053846377 | L99: =I99/G99 -> 2368.662 | M99: =L99+AK99 -> 4061.782 | N99: =AK99-L99 -> -675.54202 | O99: =I99/H99 -> 0.0071341865 | P99: =(H99-H95)/H95 -> 0.0071854488 | Q99: =(H99-H46)/H46 -> 0.095407622 | S99: =(C99-C95)/C95 -> 0.011720284 | T99: =(C99-C46)/C46 -> 0.074204786 | U99: =(C99-C86)/C86 -> 0.033799869 | V99: =(C99-C98)/(H99-H98) -> -2.0815965 | W99: =(C99-C95)/(H99-H95) -> 0.60731452 | X99: =(D99-D95)/D95 -> 0.0044953839 | Y99: =(D99-D46)/D46 -> 0.10847973 | Z99: =(D99-D86)/D86 -> 0.014010643 | AA99: =(D99-D98)/(H99-H98) -> 3.0816135 | AB99: =AVERAGE(AA87:AA99) -> 1.0397133 | AC99: =AVERAGE(V87:V99) -> -0.039710582 | AD99: =(D99-D95)/(H99-H95) -> 0.39268419 | AE99: =AVERAGE(H87:H99) -> 1081008.8 | AF99: =(AE99-AE95)/AE95 -> 0.0058548137 | AG99: =(AE99-AE46)/AE46 -> 0.096939356 | AI99: =F99*G99 -> 577498.27 | AJ99: =(AI99-AI95)/AI95 -> 0.075443645 | AK99: =(F99-F95) -> 1693.12 | AL99: =F99-F98 -> 1497.81 | AM99: =AL99*G99 -> 4920.2459 | AN99: =AK99*G99 -> 5561.8315 | AO99: =(E99+F99)*G99 -> 577802.16 | AP99: =H99/AO99 -> 1.8875982
B100: 42685 | C100: 409300.74 | D100: 686660.2 | E100: 90.82 | F100: 174294.14 | G100: 3.38066 | H100: 1095960.9 | I100: =H100-H96 -> 9781.61 | J100: =H100-H99 -> 5302.6 | K100: =J100/H100 -> 0.0048383111 | L100: =I100/G100 -> 2893.4025 | M100: =L100+AK100 -> 3495.2725 | N100: =AK100-L100 -> -2291.5325 | O100: =I100/H100 -> 0.0089251447 | P100: =(H100-H96)/H96 -> 0.0090055203 | Q100: =(H100-H47)/H47 -> 0.10677325 | S100: =(C100-C96)/C96 -> 0.0086605414 | T100: =(C100-C47)/C47 -> 0.081172362 | U100: =(C100-C87)/C87 -> 0.033488502 | V100: =(C100-C99)/(H100-H99) -> 0.26141893 | W100: =(C100-C96)/(H100-H96) -> 0.3592793 | X100: =(D100-D96)/D96 -> 0.0092112657 | Y100: =(D100-D47)/D47 -> 0.12261827 | Z100: =(D100-D87)/D87 -> 0.018941495 | AA100: =(D100-D99)/(H100-H99) -> 0.73858296 | AB100: =AVERAGE(AA88:AA100) -> 1.0745153 | AC100: =AVERAGE(V88:V100) -> -0.074512482 | AD100: =(D100-D96)/(H100-H96) -> 0.6407207 | AE100: =AVERAGE(H88:H100) -> 1083010.9 | AF100: =(AE100-AE96)/AE96 -> 0.006391536 | AG100: =(AE100-AE47)/AE47 -> 0.09768248 | AI100: =F100*G100 -> 589229.23 | AJ100: =(AI100-AI96)/AI96 -> 0.10132732 | AK100: =(F100-F96) -> 601.87 | AL100: =F100-F99 -> -1506.56 | AM100: =AL100*G100 -> -5093.1671 | AN100: =AK100*G100 -> 2034.7178 | AO100: =(E100+F100)*G100 -> 589536.26 | AP100: =H100/AO100 -> 1.8590221
B101: 42692 | C101: 408734.12 | D101: 690029.37 | E101: 97.66 | F101: 172611.13 | G101: 3.42878 | H101: 1098763.5 | I101: =H101-H97 -> 13576.55 | J101: =H101-H100 -> 2802.55 | K101: =J101/H101 -> 0.0025506399 | L101: =I101/G101 -> 3959.5862 | M101: =L101+AK101 -> 3095.8162 | N101: =AK101-L101 -> -4823.3562 | O101: =I101/H101 -> 0.012356208 | P101: =(H101-H97)/H97 -> 0.012510794 | Q101: =(H101-H48)/H48 -> 0.10512602 | S101: =(C101-C97)/C97 -> 0.011878542 | T101: =(C101-C48)/C48 -> 0.076382036 | U101: =(C101-C88)/C88 -> 0.035213048 | V101: =(C101-C100)/(H101-H100) -> -0.20218016 | W101: =(C101-C97)/(H101-H97) -> 0.353416 | X101: =(D101-D97)/D97 -> 0.012885677 | Y101: =(D101-D48)/D48 -> 0.12288796 | Z101: =(D101-D88)/D88 -> 0.020396971 | AA101: =(D101-D100)/(H101-H100) -> 1.2021802 | AB101: =AVERAGE(AA89:AA101) -> 1.0081505 | AC101: =AVERAGE(V89:V101) -> -0.0081469845 | AD101: =(D101-D97)/(H101-H97) -> 0.646584 | AE101: =AVERAGE(H89:H101) -> 1085141.4 | AF101: =(AE101-AE97)/AE97 -> 0.0070168052 | AG101: =(AE101-AE48)/AE48 -> 0.098420865 | AI101: =F101*G101 -> 591845.59 | AJ101: =(AI101-AI97)/AI97 -> 0.098813921 | AK101: =(F101-F97) -> -863.77 | AL101: =F101-F100 -> -1683.01 | AM101: =AL101*G101 -> -5770.671 | AN101: =AK101*G101 -> -2961.6773 | AO101: =(E101+F101)*G101 -> 592180.44 | AP101: =H101/AO101 -> 1.8554539
B102: 42699 | C102: 411549.98 | D102: 691267.09 | E102: 91.32 | F102: 172429.73 | G102: 3.46978 | H102: 1102817.1 | I102: =H102-H98 -> 11571.45 | J102: =H102-H101 -> 4053.58 | K102: =J102/H102 -> 0.0036756595 | L102: =I102/G102 -> 3334.9233 | M102: =L102+AK102 -> 1461.7633 | N102: =AK102-L102 -> -5208.0833 | O102: =I102/H102 -> 0.010492629 | P102: =(H102-H98)/H98 -> 0.010603891 | Q102: =(H102-H49)/H49 -> 0.10939137 | S102: =(C102-C98)/C98 -> 0.011944959 | T102: =(C102-C49)/C49 -> 0.091012185 | U102: =(C102-C89)/C89 -> 0.036367577 | V102: =(C102-C101)/(H102-H101) -> 0.69466003 | W102: =(C102-C98)/(H102-H98) -> 0.41981947 | X102: =(D102-D98)/D98 -> 0.0098071654 | Y102: =(D102-D49)/D49 -> 0.1206306 | Z102: =(D102-D89)/D89 -> 0.012110353 | AA102: =(D102-D101)/(H102-H101) -> 0.30533997 | AB102: =AVERAGE(AA90:AA102) -> 0.9740991 | AC102: =AVERAGE(V90:V102) -> 0.025904328 | AD102: =(D102-D98)/(H102-H98) -> 0.58018053 | AE102: =AVERAGE(H90:H102) -> 1086888.6 | AF102: =(AE102-AE98)/AE98 -> 0.0070708918 | AG102: =(AE102-AE49)/AE49 -> 0.098887269 | AI102: =F102*G102 -> 598293.23 | AJ102: =(AI102-AI98)/AI98 -> 0.082606883 | AK102: =(F102-F98) -> -1873.16 | AL102: =F102-F101 -> -181.4 | AM102: =AL102*G102 -> -629.41809 | AN102: =AK102*G102 -> -6499.4531 | AO102: =(E102+F102)*G102 -> 598610.09 | AP102: =H102/AO102 -> 1.8422962
B103: 42706 | C103: 415017.21 | D103: 694674.39 | E103: 92.72 | F103: 172898.04 | G103: 3.4872 | H103: 1109691.6 | I103: =H103-H99 -> 19033.26 | J103: =H103-H102 -> 6874.53 | K103: =J103/H103 -> 0.0061949915 | L103: =I103/G103 -> 5458.0351 | M103: =L103+AK103 -> 2555.3751 | N103: =AK103-L103 -> -8360.6951 | O103: =I103/H103 -> 0.017151847 | P103: =(H103-H99)/H99 -> 0.017451166 | Q103: =(H103-H50)/H50 -> 0.10496055 | S103: =(C103-C99)/C99 -> 0.017412152 | T103: =(C103-C50)/C50 -> 0.095684799 | U103: =(C103-C90)/C90 -> 0.038420984 | V103: =(C103-C102)/(H103-H102) -> 0.50435884 | W103: =(C103-C99)/(H103-H99) -> 0.37317149 | X103: =(D103-D99)/D99 -> 0.017474491 | Y103: =(D103-D50)/D50 -> 0.11057745 | Z103: =(D103-D90)/D90 -> 0.026632982 | AA103: =(D103-D102)/(H103-H102) -> 0.49564116 | AB103: =AVERAGE(AA91:AA103) -> 0.88345779 | AC103: =AVERAGE(V91:V103) -> 0.11654564 | AD103: =(D103-D99)/(H103-H99) -> 0.62682904 | AE103: =AVERAGE(H91:H103) -> 1089456 | AF103: =(AE103-AE99)/AE99 -> 0.0078141779 | AG103: =(AE103-AE50)/AE50 -> 0.09982724 | AI103: =F103*G103 -> 602930.05 | AJ103: =(AI103-AI99)/AI99 -> 0.044037842 | AK103: =(F103-F99) -> -2902.66 | AL103: =F103-F102 -> 468.31 | AM103: =AL103*G103 -> 1633.0906 | AN103: =AK103*G103 -> -10122.156 | AO103: =(E103+F103)*G103 -> 603253.38 | AP103: =H103/AO103 -> 1.8395116
B104: 42713 | C104: 415502.7 | D104: 699349.34 | E104: 89.63 | F104: 172475.19 | G104: 3.50316 | H104: 1114852 | I104: =H104-H100 -> 18891.09 | J104: =H104-H103 -> 5160.43 | K104: =J104/H104 -> 0.0046288026 | L104: =I104/G104 -> 5392.5856 | M104: =L104+AK104 -> 3573.6356 | N104: =AK104-L104 -> -7211.5356 | O104: =I104/H104 -> 0.01694493 | P104: =(H104-H100)/H100 -> 0.01723701 | Q104: =(H104-H51)/H51 -> 0.11554863 | S104: =(C104-C100)/C100 -> 0.015152575 | T104: =(C104-C51)/C51 -> 0.094541306 | U104: =(C104-C91)/C91 -> 0.041362395 | V104: =(C104-C103)/(H104-H103) -> 0.094079369 | W104: =(C104-C100)/(H104-H100) -> 0.3283008 | X104: =(D104-D100)/D100 -> 0.018479504 | Y104: =(D104-D51)/D51 -> 0.12841595 | Z104: =(D104-D91)/D91 -> 0.028912899 | AA104: =(D104-D103)/(H104-H103) -> 0.90592257 | AB104: =AVERAGE(AA92:AA104) -> 0.85481751 | AC104: =AVERAGE(V92:V104) -> 0.14518639 | AD104: =(D104-D100)/(H104-H100) -> 0.67169973 | AE104: =AVERAGE(H92:H104) -> 1092237.2 | AF104: =(AE104-AE100)/AE100 -> 0.008519112 | AG104: =(AE104-AE51)/AE51 -> 0.1013031 | AI104: =F104*G104 -> 604208.19 | AJ104: =(AI104-AI100)/AI100 -> 0.025421277 | AK104: =(F104-F100) -> -1818.95 | AL104: =F104-F103 -> -422.85 | AM104: =AL104*G104 -> -1481.3112 | AN104: =AK104*G104 -> -6372.0729 | AO104: =(E104+F104)*G104 -> 604522.17 | AP104: =H104/AO104 -> 1.8441872
B105: 42720 | C105: 414971.02 | D105: 705719.49 | E105: 90.24 | F105: 171160.39 | G105: 3.518 | H105: 1120690.5 | I105: =H105-H101 -> 21927.02 | J105: =H105-H104 -> 5838.48 | K105: =J105/H105 -> 0.0052097166 | L105: =I105/G105 -> 6232.8084 | M105: =L105+AK105 -> 4782.0684 | N105: =AK105-L105 -> -7683.5484 | O105: =I105/H105 -> 0.019565634 | P105: =(H105-H101)/H101 -> 0.019956087 | Q105: =(H105-H52)/H52 -> 0.11680957 | S105: =(C105-C101)/C101 -> 0.015259064 | T105: =(C105-C52)/C52 -> 0.089498496 | U105: =(C105-C92)/C92 -> 0.040898347 | V105: =(C105-C104)/(H105-H104) -> -0.091064798 | W105: =(C105-C101)/(H105-H101) -> 0.28443902 | X105: =(D105-D101)/D101 -> 0.022738336 | Y105: =(D105-D52)/D52 -> 0.13351764 | Z105: =(D105-D92)/D92 -> 0.036776504 | AA105: =(D105-D104)/(H105-H104) -> 1.0910631 | AB105: =AVERAGE(AA93:AA105) -> 0.82278154 | AC105: =AVERAGE(V93:V105) -> 0.17721989 | AD105: =(D105-D101)/(H105-H101) -> 0.71556098 | AE105: =AVERAGE(H93:H105) -> 1095417.1 | AF105: =(AE105-AE101)/AE101 -> 0.0094694136 | AG105: =(AE105-AE52)/AE52 -> 0.10323259 | AI105: =F105*G105 -> 602142.25 | AJ105: =(AI105-AI101)/AI101 -> 0.017397547 | AK105: =(F105-F101) -> -1450.74 | AL105: =F105-F104 -> -1314.8 | AM105: =AL105*G105 -> -4625.4664 | AN105: =AK105*G105 -> -5103.7033 | AO105: =(E105+F105)*G105 -> 602459.72 | AP105: =H105/AO105 -> 1.8601916
B106: 42727 | C106: 416229.88 | D106: 705639.14 | E106: 90.36 | F106: 171234.47 | G106: 3.5593 | H106: 1121869 | I106: =H106-H102 -> 19051.95 | J106: =H106-H105 -> 1178.51 | K106: =J106/H106 -> 0.0010504881 | L106: =I106/G106 -> 5352.7239 | M106: =L106+AK106 -> 4157.4639 | N106: =AK106-L106 -> -6547.9839 | O106: =I106/H106 -> 0.01698233 | P106: =(H106-H102)/H102 -> 0.017275712 | Q106: =(H106-H53)/H53 -> 0.11832166 | S106: =(C106-C102)/C102 -> 0.011371401 | T106: =(C106-C53)/C53 -> 0.095801363 | U106: =(C106-C93)/C93 -> 0.04182562 | V106: =(C106-C105)/(H106-H105) -> 1.0681793 | W106: =(C106-C102)/(H106-H102) -> 0.2456389 | X106: =(D106-D102)/D102 -> 0.020790878 | Y106: =(D106-D53)/D53 -> 0.13204489 | Z106: =(D106-D93)/D93 -> 0.048069906 | AA106: =(D106-D105)/(H106-H105) -> -0.068179311 | AB106: =AVERAGE(AA94:AA106) -> 0.73060254 | AC106: =AVERAGE(V94:V106) -> 0.26939888 | AD106: =(D106-D102)/(H106-H102) -> 0.7543611 | AE106: =AVERAGE(H94:H106) -> 1099192 | AF106: =(AE106-AE102)/AE102 -> 0.011319874 | AG106: =(AE106-AE53)/AE53 -> 0.10575328 | AI106: =F106*G106 -> 609474.85 | AJ106: =(AI106-AI102)/AI102 -> 0.018689198 | AK106: =(F106-F102) -> -1195.26 | AL106: =F106-F105 -> 74.08 | AM106: =AL106*G106 -> 263.67294 | AN106: =AK106*G106 -> -4254.2889 | AO106: =(E106+F106)*G106 -> 609796.47 | AP106: =H106/AO106 -> 1.8397434
B107: 42734 | C107: 419615.72 | D107: 711070.62 | E107: 84.23 | F107: 171754.82 | G107: 3.7541 | H107: 1130686.3 | I107: =H107-H103 -> 20994.74 | J107: =H107-H106 -> 8817.32 | K107: =J107/H107 -> 0.0077982016 | L107: =I107/G107 -> 5592.4829 | M107: =L107+AK107 -> 4449.2629 | N107: =AK107-L107 -> -6735.7029 | O107: =I107/H107 -> 0.018568138 | P107: =(H107-H103)/H103 -> 0.018919437 | Q107: =(H107-H54)/H54 -> 0.12400391 | S107: =(C107-C103)/C103 -> 0.011080287 | T107: =(C107-C54)/C54 -> 0.099630495 | U107: =(C107-C94)/C94 -> 0.04165056 | V107: =(C107-C106)/(H107-H106) -> 0.38399877 | W107: =(C107-C103)/(H107-H103) -> 0.21903153 | X107: =(D107-D103)/D103 -> 0.023602756 | Y107: =(D107-D54)/D54 -> 0.13890078 | Z107: =(D107-D94)/D94 -> 0.03674711 | AA107: =(D107-D106)/(H107-H106) -> 0.61600123 | AB107: =AVERAGE(AA95:AA107) -> 0.71710473 | AC107: =AVERAGE(V95:V107) -> 0.28289674 | AD107: =(D107-D103)/(H107-H103) -> 0.78096847 | AE107: =AVERAGE(H95:H107) -> 1102421.4 | AF107: =(AE107-AE103)/AE103 -> 0.011900793 | AG107: =(AE107-AE54)/AE54 -> 0.10724542 | AI107: =F107*G107 -> 644784.77 | AJ107: =(AI107-AI103)/AI103 -> 0.069418874 | AK107: =(F107-F103) -> -1143.22 | AL107: =F107-F106 -> 520.35 | AM107: =AL107*G107 -> 1953.4459 | AN107: =AK107*G107 -> -4291.7622 | AO107: =(E107+F107)*G107 -> 645100.98 | AP107: =H107/AO107 -> 1.7527277
B108: 42741 | C108: 418977.08 | D108: 709519.93 | E108: 82.32 | F108: 171710.23 | G108: 3.78298 | H108: 1128497 | I108: =H108-H104 -> 13644.97 | J108: =H108-H107 -> -2189.34 | K108: =J108/H108 -> -0.0019400495 | L108: =I108/G108 -> 3606.9369 | M108: =L108+AK108 -> 2841.9769 | N108: =AK108-L108 -> -4371.8969 | O108: =I108/H108 -> 0.012091277 | P108: =(H108-H104)/H104 -> 0.012239266 | Q108: =(H108-H55)/H55 -> 0.11354574 | S108: =(C108-C104)/C104 -> 0.0083618711 | T108: =(C108-C55)/C55 -> 0.088714563 | U108: =(C108-C95)/C95 -> 0.039157884 | V108: =(C108-C107)/(H108-H107) -> 0.29170435 | W108: =(C108-C104)/(H108-H104) -> 0.25462716 | X108: =(D108-D104)/D104 -> 0.014542932 | Y108: =(D108-D55)/D55 -> 0.12874794 | Z108: =(D108-D95)/D95 -> 0.043890117 | AA108: =(D108-D107)/(H108-H107) -> 0.70829108 | AB108: =AVERAGE(AA96:AA108) -> 0.69002229 | AC108: =AVERAGE(V96:V108) -> 0.30997883 | AD108: =(D108-D104)/(H108-H104) -> 0.74537284 | AE108: =AVERAGE(H96:H108) -> 1105930.6 | AF108: =(AE108-AE104)/AE104 -> 0.012537016 | AG108: =(AE108-AE55)/AE55 -> 0.10847017 | AI108: =F108*G108 -> 649576.37 | AJ108: =(AI108-AI104)/AI104 -> 0.075086999 | AK108: =(F108-F104) -> -764.96 | AL108: =F108-F107 -> -44.59 | AM108: =AL108*G108 -> -168.68308 | AN108: =AK108*G108 -> -2893.8284 | AO108: =(E108+F108)*G108 -> 649887.78 | AP108: =H108/AO108 -> 1.736449
B109: 42748 | C109: 420296.24 | D109: 718140.31 | E109: 83.24 | F109: 172185.67 | G109: 3.79506 | H109: 1138436.6 | I109: =H109-H105 -> 17746.04 | J109: =H109-H108 -> 9939.55 | K109: =J109/H109 -> 0.0087308774 | L109: =I109/G109 -> 4676.0894 | M109: =L109+AK109 -> 5701.3694 | N109: =AK109-L109 -> -3650.8094 | O109: =I109/H109 -> 0.01558808 | P109: =(H109-H105)/H105 -> 0.015834916 | Q109: =(H109-H56)/H56 -> 0.13369095 | S109: =(C109-C105)/C105 -> 0.012832752 | T109: =(C109-C56)/C56 -> 0.099244689 | U109: =(C109-C96)/C96 -> 0.035757309 | V109: =(C109-C108)/(H109-H108) -> 0.13271828 | W109: =(C109-C105)/(H109-H105) -> 0.30007934 | X109: =(D109-D105)/D105 -> 0.017600222 | Y109: =(D109-D56)/D56 -> 0.15487104 | Z109: =(D109-D96)/D96 -> 0.055478811 | AA109: =(D109-D108)/(H109-H108) -> 0.86728071 | AB109: =AVERAGE(AA97:AA109) -> 0.74032188 | AC109: =AVERAGE(V97:V109) -> 0.25967916 | AD109: =(D109-D105)/(H109-H105) -> 0.69992066 | AE109: =AVERAGE(H97:H109) -> 1109950.4 | AF109: =(AE109-AE105)/AE105 -> 0.013267395 | AG109: =(AE109-AE56)/AE56 -> 0.11114849 | AI109: =F109*G109 -> 653454.95 | AJ109: =(AI109-AI105)/AI105 -> 0.085216901 | AK109: =(F109-F105) -> 1025.28 | AL109: =F109-F108 -> 475.44 | AM109: =AL109*G109 -> 1804.3233 | AN109: =AK109*G109 -> 3890.9991 | AO109: =(E109+F109)*G109 -> 653770.85 | AP109: =H109/AO109 -> 1.7413388
...

Sheet Tüketici Kredi Alt Kalemleri
B1: Tüketici Kredi Tipleri | V1: Bireysel Kredi Kartları
A2: HER PERŞEMBE | C2: Konut | D2: Konut Kredileri Yıllık | E2: Konut Kredileri Aylık | F2: 3mKonutKredisi | G2: Konut Kredisi - Haftalık Flow | H2: 6m konut kredisi | J2: Haftalık Flow | L2: Taşıt | M2: Taşıt Kredileri Yıllık | N2: Taşıt Kredileri Aylık | O2: Haftalık Flow | Q2: İhtiyaç | R2: YoY | S2: MoM | T2: Haftalık Flow | V2: Bireysel Kredi Kartları / a) Taksitli | W2: / b) Taksitsiz | X2: Taksitli 13w | Y2: Taksitsiz 13w | Z2: Toplam | AA2: YoY | AB2: MoM | AC2: 13w Credit Card Grıowth | AF2: Krediler / KOBİ Kredileri (Bilgi) | AG2: Kobi Kredileri YoY | AH2: MoM | AI2: 3m
A3: BDDK BÜLTEN
B6: 46017 | C6: 673845 | D6: =(C6-C58)/C58 -> 0.31809353 | E6: =(C6-C10)/C10 -> 0.022691055 | F6: =(C6-C19)/C19 -> 0.082770667 | G6: =C6-C7 -> 4540 | H6: =(C6-C31)/C31 -> 0.15048924 | J6: =C6-C7 -> 4540 | L6: 51299 | M6: =(L6-L58)/L58 -> -0.32114547 | N6: =(L6-L10)/L10 -> 0.03903022 | O6: =L6-L7 -> 1257 | Q6: 2155993 | R6: =(Q6-Q58)/Q58 -> 0.51320373 | S6: =(Q6-Q10)/Q10 -> 0.041296022 | T6: =Q6-Q7 -> 40000 | V6: 1001843 | W6: 1682356 | X6: =(V6-V19)/V19 -> 0.095316188 | Y6: =(W6-W19)/W19 -> 0.069118298 | Z6: =V6+W6 -> 2684199 | AA6: =(Z6-Z58)/Z58 -> 0.49983908 | AB6: =(Z6-Z10)/Z10 -> 0.020099487 | AC6: =(Z6-Z19)/Z19 -> 0.078748423 | AF6: 4964235 | AG6: =(AF6-AF58)/AF58 -> 0.45713257 | AH6: =(AF6-AF10)/AF10 -> 0.031546498 | AI6: =(AF6-AF19)/AF19 -> 0.11436468
B7: 46010 | C7: 669305 | D7: =(C7-C59)/C59 -> 0.32099063 | E7: =(C7-C11)/C11 -> 0.022940722 | F7: =(C7-C20)/C20 -> 0.082705952 | G7: =C7-C8 -> 2749 | H7: =(C7-C32)/C32 -> 0.14777812 | J7: =C7-C8 -> 2749 | L7: 50042 | M7: =(L7-L59)/L59 -> -0.33017441 | N7: =(L7-L11)/L11 -> 0.03369069 | O7: =L7-L8 -> -302 | Q7: 2115993 | R7: =(Q7-Q59)/Q59 -> 0.50993628 | S7: =(Q7-Q11)/Q11 -> 0.030170061 | T7: =Q7-Q8 -> 2998 | V7: 990739 | W7: 1643919 | X7: =(V7-V20)/V20 -> 0.088728961 | Y7: =(W7-W20)/W20 -> 0.064546836 | Z7: =V7+W7 -> 2634658 | AA7: =(Z7-Z59)/Z59 -> 0.52881538 | AB7: =(Z7-Z11)/Z11 -> 0.027145102 | AC7: =(Z7-Z20)/Z20 -> 0.073513215 | AF7: 4909595 | AG7: =(AF7-AF59)/AF59 -> 0.45882924 | AH7: =(AF7-AF11)/AF11 -> 0.033872107 | AI7: =(AF7-AF20)/AF20 -> 0.11726492
B8: 46003 | C8: 666556 | D8: =(C8-C60)/C60 -> 0.32289397 | E8: =(C8-C12)/C12 -> 0.022739269 | F8: =(C8-C21)/C21 -> 0.083630026 | G8: =C8-C9 -> 3811 | H8: =(C8-C33)/C33 -> 0.14943068 | J8: =C8-C9 -> 3811 | L8: 50344 | M8: =(L8-L60)/L60 -> -0.33282975 | N8: =(L8-L12)/L12 -> 0.021881216 | O8: =L8-L9 -> 854 | Q8: 2112995 | R8: =(Q8-Q60)/Q60 -> 0.5100404 | S8: =(Q8-Q12)/Q12 -> 0.032297353 | T8: =Q8-Q9 -> 36902 | V8: 976010 | W8: 1687851 | X8: =(V8-V21)/V21 -> 0.089965939 | Y8: =(W8-W21)/W21 -> 0.05224732 | Z8: =V8+W8 -> 2663861 | AA8: =(Z8-Z60)/Z60 -> 0.51635748 | AB8: =(Z8-Z12)/Z12 -> 0.021240535 | AC8: =(Z8-Z21)/Z21 -> 0.06576011 | AF8: 4866813 | AG8: =(AF8-AF60)/AF60 -> 0.45283811 | AH8: =(AF8-AF12)/AF12 -> 0.033375906 | AI8: =(AF8-AF21)/AF21 -> 0.11472692
B9: 45996 | C9: 662745 | D9: =(C9-C61)/C61 -> 0.32588246 | E9: =(C9-C13)/C13 -> 0.024015686 | F9: =(C9-C22)/C22 -> 0.082348964 | G9: =C9-C10 -> 3851 | H9: =(C9-C34)/C34 -> 0.14421243 | J9: =C9-C10 -> 3851 | L9: 49490 | M9: =(L9-L61)/L61 -> -0.33916411 | N9: =(L9-L13)/L13 -> 0.011734402 | O9: =L9-L10 -> 118 | Q9: 2076093 | R9: =(Q9-Q61)/Q61 -> 0.50873479 | S9: =(Q9-Q13)/Q13 -> 0.035002557 | T9: =Q9-Q10 -> 5603 | V9: 974644 | W9: 1664080 | X9: =(V9-V22)/V22 -> 0.10284411 | Y9: =(W9-W22)/W22 -> 0.062347343 | Z9: =V9+W9 -> 2638724 | AA9: =(Z9-Z61)/Z61 -> 0.52221811 | AB9: =(Z9-Z13)/Z13 -> 0.038290934 | AC9: =(Z9-Z22)/Z22 -> 0.076954158 | AF9: 4822089 | AG9: =(AF9-AF61)/AF61 -> 0.45311223 | AH9: =(AF9-AF13)/AF13 -> 0.030899476 | AI9: =(AF9-AF22)/AF22 -> 0.11303772
B10: 45989 | C10: 658894 | D10: =(C10-C62)/C62 -> 0.32781566 | E10: =(C10-C14)/C14 -> 0.026050937 | F10: =(C10-C23)/C23 -> 0.082210298 | G10: =C10-C11 -> 4599 | H10: =(C10-C35)/C35 -> 0.1409736 | J10: =C10-C11 -> 4599 | L10: 49372 | M10: =(L10-L62)/L62 -> -0.34357965 | N10: =(L10-L14)/L14 -> -0.0041349819 | O10: =L10-L11 -> 961 | Q10: 2070490 | R10: =(Q10-Q62)/Q62 -> 0.51006435 | S10: =(Q10-Q14)/Q14 -> 0.03471264 | T10: =Q10-Q11 -> 16467 | V10: 965747 | W10: 1665564 | X10: =(V10-V23)/V23 -> 0.12499054 | Y10: =(W10-W23)/W23 -> 0.057725257 | Z10: =V10+W10 -> 2631311 | AA10: =(Z10-Z62)/Z62 -> 0.51347066 | AB10: =(Z10-Z14)/Z14 -> 0.018907779 | AC10: =(Z10-Z23)/Z23 -> 0.08145772 | AF10: 4812420 | AG10: =(AF10-AF62)/AF62 -> 0.45167975 | AH10: =(AF10-AF14)/AF14 -> 0.028545195 | AI10: =(AF10-AF23)/AF23 -> 0.12026556
B11: 45982 | C11: 654295 | D11: =(C11-C63)/C63 -> 0.33002738 | E11: =(C11-C15)/C15 -> 0.024317351 | F11: =(C11-C24)/C24 -> 0.08218947 | G11: =C11-C12 -> 2559 | H11: =(C11-C36)/C36 -> 0.13675674 | J11: =C11-C12 -> 2559 | L11: 48411 | M11: =(L11-L63)/L63 -> -0.3477804 | N11: =(L11-L15)/L15 -> -0.016736062 | O11: =L11-L12 -> -855 | Q11: 2054023 | R11: =(Q11-Q63)/Q63 -> 0.51803852 | S11: =(Q11-Q15)/Q15 -> 0.045231984 | T11: =Q11-Q12 -> 7137 | V11: 957995 | W11: 1607035 | X11: =(V11-V24)/V24 -> 0.12801773 | Y11: =(W11-W24)/W24 -> 0.058864885 | Z11: =V11+W11 -> 2565030 | AA11: =(Z11-Z63)/Z63 -> 0.5246355 | AB11: =(Z11-Z15)/Z15 -> 0.024380367 | AC11: =(Z11-Z24)/Z24 -> 0.083677057 | AF11: 4748745 | AG11: =(AF11-AF63)/AF63 -> 0.44387995 | AH11: =(AF11-AF15)/AF15 -> 0.028011962 | AI11: =(AF11-AF24)/AF24 -> 0.12025864
B12: 45975 | C12: 651736 | D12: =(C12-C64)/C64 -> 0.33416855 | E12: =(C12-C16)/C16 -> 0.0282083 | F12: =(C12-C25)/C25 -> 0.084056746 | G12: =C12-C13 -> 4534 | H12: =(C12-C37)/C37 -> 0.13948888 | J12: =C12-C13 -> 4534 | L12: 49266 | M12: =(L12-L64)/L64 -> -0.33506991 | N12: =(L12-L16)/L16 -> 0.0066817875 | O12: =L12-L13 -> 350 | Q12: 2046886 | R12: =(Q12-Q64)/Q64 -> 0.5380834 | S12: =(Q12-Q16)/Q16 -> 0.054418114 | T12: =Q12-Q13 -> 41004 | V12: 948131 | W12: 1660325 | X12: =(V12-V25)/V25 -> 0.13571065 | Y12: =(W12-W25)/W25 -> 0.095904561 | Z12: =V12+W12 -> 2608456 | AA12: =(Z12-Z64)/Z64 -> 0.56063017 | AB12: =(Z12-Z16)/Z16 -> 0.055496545 | AC12: =(Z12-Z25)/Z25 -> 0.11004646 | AF12: 4709625 | AG12: =(AF12-AF64)/AF64 -> 0.43900016 | AH12: =(AF12-AF16)/AF16 -> 0.027374848 | AI12: =(AF12-AF25)/AF25 -> 0.12695852
B13: 45968 | C13: 647202 | D13: =(C13-C65)/C65 -> 0.33367541 | E13: =(C13-C17)/C17 -> 0.026351721 | F13: =(C13-C26)/C26 -> 0.081109704 | G13: =C13-C14 -> 5037 | H13: =(C13-C38)/C38 -> 0.13659695 | J13: =C13-C14 -> 5037 | L13: 48916 | M13: =(L13-L65)/L65 -> -0.34854236 | N13: =(L13-L17)/L17 -> -0.017711555 | O13: =L13-L14 -> -661 | Q13: 2005882 | R13: =(Q13-Q65)/Q65 -> 0.50063253 | S13: =(Q13-Q17)/Q17 -> 0.035283783 | T13: =Q13-Q14 -> 4853 | V13: 939015 | W13: 1602396 | X13: =(V13-V26)/V26 -> 0.13269442 | Y13: =(W13-W26)/W26 -> 0.051502352 | Z13: =V13+W13 -> 2541411 | AA13: =(Z13-Z65)/Z65 -> 0.5281866 | AB13: =(Z13-Z17)/Z17 -> 0.0012414016 | AC13: =(Z13-Z26)/Z26 -> 0.080108937 | AF13: 4677555 | AG13: =(AF13-AF65)/AF65 -> 0.43795963 | AH13: =(AF13-AF17)/AF17 -> 0.033261004 | AI13: =(AF13-AF26)/AF26 -> 0.13906873
B14: 45961 | C14: 642165 | D14: =(C14-C66)/C66 -> 0.33389764 | E14: =(C14-C18)/C18 -> 0.024807698 | F14: =(C14-C27)/C27 -> 0.07878119 | G14: =C14-C15 -> 3403 | H14: =(C14-C39)/C39 -> 0.13324966 | J14: =C14-C15 -> 3403 | L14: 49577 | M14: =(L14-L66)/L66 -> -0.3442456 | N14: =(L14-L18)/L18 -> -0.0043379592 | O14: =L14-L15 -> 342 | Q14: 2001029 | R14: =(Q14-Q66)/Q66 -> 0.50715758 | S14: =(Q14-Q18)/Q18 -> 0.040127225 | T14: =Q14-Q15 -> 35893 | V14: 934434 | W14: 1648048 | X14: =(V14-V27)/V27 -> 0.14998769 | Y14: =(W14-W27)/W27 -> 0.053586212 | Z14: =V14+W14 -> 2582482 | AA14: =(Z14-Z66)/Z66 -> 0.54422432 | AB14: =(Z14-Z18)/Z18 -> 0.020452258 | AC14: =(Z14-Z27)/Z27 -> 0.086543304 | AF14: 4678861 | AG14: =(AF14-AF66)/AF66 -> 0.43911174 | AH14: =(AF14-AF18)/AF18 -> 0.036853147 | AI14: =(AF14-AF27)/AF27 -> 0.15339528
B15: 45954 | C15: 638762 | D15: =(C15-C67)/C67 -> 0.33452977 | E15: =(C15-C19)/C19 -> 0.026397401 | F15: =(C15-C28)/C28 -> 0.079359983 | G15: =C15-C16 -> 4906 | H15: =(C15-C40)/C40 -> 0.13534766 | J15: =C15-C16 -> 4906 | L15: 49235 | M15: =(L15-L67)/L67 -> -0.35200905 | N15: =(L15-L19)/L19 -> -0.022979382 | O15: =L15-L16 -> 296 | Q15: 1965136 | R15: =(Q15-Q67)/Q67 -> 0.49337224 | S15: =(Q15-Q19)/Q19 -> 0.027717694 | T15: =Q15-Q16 -> 23889 | V15: 932320 | W15: 1571662 | X15: =(V15-V28)/V28 -> 0.19194765 | Y15: =(W15-W28)/W28 -> 0.049699816 | Z15: =V15+W15 -> 2503982 | AA15: =(Z15-Z67)/Z67 -> 0.53811405 | AB15: =(Z15-Z19)/Z19 -> 0.0063213025 | AC15: =(Z15-Z28)/Z28 -> 0.098511865 | AF15: 4619348 | AG15: =(AF15-AF67)/AF67 -> 0.4231756 | AH15: =(AF15-AF19)/AF19 -> 0.036944918 | AI15: =(AF15-AF28)/AF28 -> 0.15233039
B16: 45947 | C16: 633856 | D16: =(C16-C68)/C68 -> 0.33619183 | E16: =(C16-C20)/C20 -> 0.025361627 | F16: =(C16-C29)/C29 -> 0.076404739 | G16: =C16-C17 -> 3271 | H16: =(C16-C41)/C41 -> 0.13338447 | J16: =C16-C17 -> 3271 | L16: 48939 | M16: =(L16-L68)/L68 -> -0.356988 | N16: =(L16-L20)/L20 -> -0.033380079 | O16: =L16-L17 -> -859 | Q16: 1941247 | R16: =(Q16-Q68)/Q68 -> 0.49556895 | S16: =(Q16-Q20)/Q20 -> 0.035029781 | T16: =Q16-Q17 -> 3728 | V16: 929724 | W16: 1541583 | X16: =(V16-V29)/V29 -> 0.20431662 | Y16: =(W16-W29)/W29 -> 0.055359039 | Z16: =V16+W16 -> 2471307 | AA16: =(Z16-Z68)/Z68 -> 0.54670229 | AB16: =(Z16-Z20)/Z20 -> 0.0069544979 | AC16: =(Z16-Z29)/Z29 -> 0.10686331 | AF16: 4584135 | AG16: =(AF16-AF68)/AF68 -> 0.42313011 | AH16: =(AF16-AF20)/AF20 -> 0.043200757 | AI16: =(AF16-AF29)/AF29 -> 0.14675133
B17: 45940 | C17: 630585 | D17: =(C17-C69)/C69 -> 0.33747282 | E17: =(C17-C21)/C21 -> 0.025151435 | F17: =(C17-C30)/C30 -> 0.071719925 | G17: =C17-C18 -> 3965 | H17: =(C17-C42)/C42 -> 0.13640736 | J17: =C17-C18 -> 3965 | L17: 49798 | M17: =(L17-L69)/L69 -> -0.35891758 | N17: =(L17-L21)/L21 -> -0.042806343 | O17: =L17-L18 -> 5 | Q17: 1937519 | R17: =(Q17-Q69)/Q69 -> 0.48592431 | S17: =(Q17-Q21)/Q21 -> 0.030542589 | T17: =Q17-Q18 -> 13688 | V17: 923765 | W17: 1614495 | X17: =(V17-V30)/V30 -> 0.21532835 | Y17: =(W17-W30)/W30 -> 0.080795848 | Z17: =V17+W17 -> 2538260 | AA17: =(Z17-Z69)/Z69 -> 0.55568004 | AB17: =(Z17-Z21)/Z21 -> 0.015509539 | AC17: =(Z17-Z30)/Z30 -> 0.12616504 | AF17: 4526983 | AG17: =(AF17-AF69)/AF69 -> 0.41517204 | AH17: =(AF17-AF21)/AF21 -> 0.036890015 | AI17: =(AF17-AF30)/AF30 -> 0.13884273
... B451: 42902 | C451: 179938.99 | D451: =(C451-C503)/C503 -> 0.19465401 | E451: =(C451-C455)/C455 -> 0.013358225 | F451: =(C451-C464)/C464 -> 0.055406761 | G451: =C451-C452 -> 432.94 | H451: =(C451-C476)/C476 -> 0.10427355 | J451: =C451-C452 -> 432.94 | L451: 6594.33 | M451: =(L451-L503)/L503 -> 0.036151942 | N451: =(L451-L455)/L455 -> 0.0099071312 | O451: =L451-L452 -> 4.24 | Q451: 178974.9 | R451: =(Q451-Q503)/Q503 -> 0.13369637 | S451: =(Q451-Q455)/Q455 -> 0.015166215 | T451: =Q451-Q452 -> 130.01 | V451: 38714.13 | W451: 43391.15 | X451: =(V451-V464)/V464 -> 0.019543869 | Y451: =(W451-W464)/W464 -> 0.039627718 | Z451: =V451+W451 -> 82105.28 | AA451: =(Z451-Z503)/Z503 -> 0.050755657 | AB451: =(Z451-Z455)/Z455 -> 0.007678359 | AC451: =(Z451-Z464)/Z464 -> 0.03006014 | AF451: 401093.2 | AG451: =(AF451-AF503)/AF503 -> #DIV/0! | AH451: =(AF451-AF455)/AF455 -> 0.02081612 | AI451: =(AF451-AF464)/AF464 -> #DIV/0!
B452: 42895 | C452: 179506.05 | D452: =(C452-C504)/C504 -> 0.19344174 | E452: =(C452-C456)/C456 -> 0.012288201 | F452: =(C452-C465)/C465 -> 0.057923016 | G452: =C452-C453 -> 637.77 | H452: =(C452-C477)/C477 -> 0.10585422 | J452: =C452-C453 -> 637.77 | L452: 6590.09 | M452: =(L452-L504)/L504 -> 0.034263635 | N452: =(L452-L456)/L456 -> 0.0076713477 | O452: =L452-L453 -> 24.98 | Q452: 178844.89 | R452: =(Q452-Q504)/Q504 -> 0.12946851 | S452: =(Q452-Q456)/Q456 -> 0.012005209 | T452: =Q452-Q453 -> 785.73 | V452: 38343.54 | W452: 44588.71 | X452: =(V452-V465)/V465 -> 0.013355554 | Y452: =(W452-W465)/W465 -> 0.030856778 | Z452: =V452+W452 -> 82932.25 | AA452: =(Z452-Z504)/Z504 -> 0.043209829 | AB452: =(Z452-Z456)/Z456 -> 0.0096811342 | AC452: =(Z452-Z465)/Z465 -> 0.022690586 | AF452: 398432.39 | AI452: =(AF452-AF465)/AF465 -> #DIV/0!
B453: 42888 | C453: 178868.28 | D453: =(C453-C505)/C505 -> 0.19441197 | E453: =(C453-C457)/C457 -> 0.012679421 | F453: =(C453-C466)/C466 -> 0.060324112 | G453: =C453-C454 -> 763.32 | H453: =(C453-C478)/C478 -> 0.10546314 | J453: =C453-C454 -> 763.32 | L453: 6565.11 | M453: =(L453-L505)/L505 -> 0.031192865 | N453: =(L453-L457)/L457 -> 0.0060160745 | O453: =L453-L454 -> 30.5 | Q453: 178059.16 | R453: =(Q453-Q505)/Q505 -> 0.12597469 | S453: =(Q453-Q457)/Q457 -> 0.01516402 | T453: =Q453-Q454 -> 718.71 | V453: 38446.96 | W453: 45266.57 | X453: =(V453-V466)/V466 -> 0.014877244 | Y453: =(W453-W466)/W466 -> 0.023064658 | Z453: =V453+W453 -> 83713.53 | AA453: =(Z453-Z505)/Z505 -> 0.049743926 | AB453: =(Z453-Z457)/Z457 -> 0.028376516 | AC453: =(Z453-Z466)/Z466 -> 0.019288097 | AF453: 398129.91 | AI453: =(AF453-AF466)/AF466 -> #DIV/0!
B454: 42881 | C454: 178104.96 | D454: =(C454-C506)/C506 -> 0.19176855 | E454: =(C454-C458)/C458 -> 0.010974415 | F454: =(C454-C467)/C467 -> 0.060815306 | G454: =C454-C455 -> 537.95 | H454: =(C454-C479)/C479 -> 0.1061763 | J454: =C454-C455 -> 537.95 | L454: 6534.61 | M454: =(L454-L506)/L506 -> 0.025424513 | N454: =(L454-L458)/L458 -> -0.00043900708 | O454: =L454-L455 -> 4.97 | Q454: 177340.45 | R454: =(Q454-Q506)/Q506 -> 0.122885 | S454: =(Q454-Q458)/Q458 -> 0.013493129 | T454: =Q454-Q455 -> 1039.37 | V454: 38174.16 | W454: 44385.91 | X454: =(V454-V467)/V467 -> -0.020662111 | Y454: =(W454-W467)/W467 -> 0.035560394 | Z454: =V454+W454 -> 82560.07 | AA454: =(Z454-Z506)/Z506 -> 0.050955381 | AB454: =(Z454-Z458)/Z458 -> 0.013012463 | AC454: =(Z454-Z467)/Z467 -> 0.0087826084 | AF454: 395305.35 | AI454: =(AF454-AF467)/AF467 -> #DIV/0!
B455: 42873 | C455: 177567.01 | D455: =(C455-C507)/C507 -> 0.19215528 | E455: =(C455-C459)/C459 -> 0.012532994 | F455: =(C455-C468)/C468 -> 0.062981884 | G455: =C455-C456 -> 239.99 | H455: =(C455-C480)/C480 -> 0.1088524 | J455: =C455-C456 -> 239.99 | L455: 6529.64 | M455: =(L455-L507)/L507 -> 0.030085519 | N455: =(L455-L459)/L459 -> 0.0011038814 | O455: =L455-L456 -> -10.28 | Q455: 176301.08 | R455: =(Q455-Q507)/Q507 -> 0.12120095 | S455: =(Q455-Q459)/Q459 -> 0.014220457 | T455: =Q455-Q456 -> -422.21 | V455: 38017.02 | W455: 43462.63 | X455: =(V455-V468)/V468 -> -0.022601729 | Y455: =(W455-W468)/W468 -> 0.0019921054 | Z455: =V455+W455 -> 81479.65 | AA455: =(Z455-Z507)/Z507 -> 0.049272492 | AB455: =(Z455-Z459)/Z459 -> 0.017137619 | AC455: =(Z455-Z468)/Z468 -> -0.0096351922 | AF455: 392914.25 | AI455: =(AF455-AF468)/AF468 -> #DIV/0!
B456: 42867 | C456: 177327.02 | D456: =(C456-C508)/C508 -> 0.18993462 | E456: =(C456-C460)/C460 -> 0.013691844 | F456: =(C456-C469)/C469 -> 0.064444228 | G456: =C456-C457 -> 698.29 | H456: =(C456-C481)/C481 -> 0.11332457 | J456: =C456-C457 -> 698.29 | L456: 6539.92 | M456: =(L456-L508)/L508 -> 0.029059485 | N456: =(L456-L460)/L460 -> -0.0015861845 | O456: =L456-L457 -> 14.07 | Q456: 176723.29 | R456: =(Q456-Q508)/Q508 -> 0.11735534 | S456: =(Q456-Q460)/Q460 -> 0.014118782 | T456: =Q456-Q457 -> 1323.89 | V456: 37753.55 | W456: 44383.52 | X456: =(V456-V469)/V469 -> -0.026247324 | Y456: =(W456-W469)/W469 -> -0.0034752112 | Z456: =V456+W456 -> 82137.07 | AA456: =(Z456-Z508)/Z508 -> 0.044549183 | AB456: =(Z456-Z460)/Z460 -> 0.0031473129 | AC456: =(Z456-Z469)/Z469 -> -0.014073067 | AF456: 389992.04 | AI456: =(AF456-AF469)/AF469 -> #DIV/0!
B457: 42860 | C457: 176628.73 | D457: =(C457-C509)/C509 -> 0.18930413 | E457: =(C457-C461)/C461 -> 0.01636098 | F457: =(C457-C470)/C470 -> 0.063836939 | G457: =C457-C458 -> 457.15 | H457: =(C457-C482)/C482 -> 0.112614 | J457: =C457-C458 -> 457.15 | L457: 6525.85 | M457: =(L457-L509)/L509 -> 0.028950339 | N457: =(L457-L461)/L461 -> -0.00088951354 | O457: =L457-L458 -> -11.63 | Q457: 175399.4 | R457: =(Q457-Q509)/Q509 -> 0.11521005 | S457: =(Q457-Q461)/Q461 -> 0.014434985 | T457: =Q457-Q458 -> 419.97 | V457: 37879.73 | W457: 43523.85 | X457: =(V457-V470)/V470 -> -0.03213251 | Y457: =(W457-W470)/W470 -> -0.0011811732 | Z457: =V457+W457 -> 81403.58 | AA457: =(Z457-Z509)/Z509 -> 0.043027743 | AB457: =(Z457-Z461)/Z461 -> 0.0036863507 | AC457: =(Z457-Z470)/Z470 -> -0.015826483 | AF457: 0 | AI457: =(AF457-AF470)/AF470 -> #DIV/0!
B458: 42853 | C458: 176171.58 | D458: =(C458-C510)/C510 -> 0.18925376 | E458: =(C458-C462)/C462 -> 0.020364537 | F458: =(C458-C471)/C471 -> 0.064797712 | G458: =C458-C459 -> 802.47 | H458: =(C458-C483)/C483 -> 0.11506124 | J458: =C458-C459 -> 802.47 | L458: 6537.48 | M458: =(L458-L510)/L510 -> 0.029996424 | N458: =(L458-L462)/L462 -> -0.00060842686 | O458: =L458-L459 -> 15.04 | Q458: 174979.43 | R458: =(Q458-Q510)/Q510 -> 0.11238649 | S458: =(Q458-Q462)/Q462 -> 0.013006976 | T458: =Q458-Q459 -> 1150.28 | V458: 37638.75 | W458: 43860.81 | X458: =(V458-V471)/V471 -> -0.025875208 | Y458: =(W458-W471)/W471 -> 0.025903707 | Z458: =V458+W458 -> 81499.56 | AA458: =(Z458-Z510)/Z510 -> 0.041437821 | AB458: =(Z458-Z462)/Z462 -> -0.0078783406 | AC458: =(Z458-Z471)/Z471 -> 0.0013231051 | AF458: 0 | AI458: =(AF458-AF471)/AF471 -> #DIV/0!
B459: 42846 | C459: 175369.11 | D459: =(C459-C511)/C511 -> 0.18720119 | E459: =(C459-C463)/C463 -> 0.022356414 | F459: =(C459-C472)/C472 -> 0.063728693 | G459: =C459-C460 -> 437.23 | H459: =(C459-C484)/C484 -> 0.11577257 | J459: =C459-C460 -> 437.23 | L459: 6522.44 | M459: =(L459-L511)/L511 -> 0.033300381 | N459: =(L459-L463)/L463 -> -0.0003264583 | O459: =L459-L460 -> -27.87 | Q459: 173829.15 | R459: =(Q459-Q511)/Q511 -> 0.10869761 | S459: =(Q459-Q463)/Q463 -> 0.012844006 | T459: =Q459-Q460 -> -433.76 | V459: 38197.73 | W459: 41909.08 | X459: =(V459-V472)/V472 -> -0.01137811 | Y459: =(W459-W472)/W472 -> 0.02124584 | Z459: =V459+W459 -> 80106.81 | AA459: =(Z459-Z511)/Z511 -> 0.041797092 | AB459: =(Z459-Z463)/Z463 -> -0.0054946406 | AC459: =(Z459-Z472)/Z472 -> 0.0054251947 | AF459: 0 | AI459: =(AF459-AF472)/AF472 -> #DIV/0!
B460: 42839 | C460: 174931.88 | D460: =(C460-C512)/C512 -> 0.18563409 | E460: =(C460-C464)/C464 -> 0.026038264 | F460: =(C460-C473)/C473 -> 0.061964633 | G460: =C460-C461 -> 1146.45 | H460: =(C460-C485)/C485 -> 0.11833276 | J460: =C460-C461 -> 1146.45 | L460: 6550.31 | M460: =(L460-L512)/L512 -> 0.0386947 | N460: =(L460-L464)/L464 -> 0.0043314536 | O460: =L460-L461 -> 18.65 | Q460: 174262.91 | R460: =(Q460-Q512)/Q512 -> 0.11486679 | S460: =(Q460-Q464)/Q464 -> 0.021916776 | T460: =Q460-Q461 -> 1359.37 | V460: 38005.03 | W460: 43874.34 | X460: =(V460-V473)/V473 -> -0.0099162005 | Y460: =(W460-W473)/W473 -> 0.027503552 | Z460: =V460+W460 -> 81879.37 | AA460: =(Z460-Z512)/Z512 -> 0.055312433 | AB460: =(Z460-Z464)/Z464 -> 0.027225963 | AC460: =(Z460-Z473)/Z473 -> 0.0097891599 | AF460: 0 | AI460: =(AF460-AF473)/AF473 -> #DIV/0!
B461: 42832 | C461: 173785.43 | D461: =(C461-C513)/C513 -> 0.17996978 | E461: =(C461-C465)/C465 -> 0.024208411 | F461: =(C461-C474)/C474 -> 0.057891546 | G461: =C461-C462 -> 1129.9 | H461: =(C461-C486)/C486 -> 0.11439049 | J461: =C461-C462 -> 1129.9 | L461: 6531.66 | M461: =(L461-L513)/L513 -> 0.0357127 | N461: =(L461-L465)/L465 -> -0.0018811211 | O461: =L461-L462 -> -9.8 | Q461: 172903.54 | R461: =(Q461-Q513)/Q513 -> 0.10245935 | S461: =(Q461-Q465)/Q465 -> 0.013768322 | T461: =Q461-Q462 -> 170.84 | V461: 37979.4 | W461: 43125.2 | X461: =(V461-V474)/V474 -> -0.02159355 | Y461: =(W461-W474)/W474 -> 0.019204922 | Z461: =V461+W461 -> 81104.6 | AA461: =(Z461-Z513)/Z513 -> 0.05165294 | AB461: =(Z461-Z465)/Z465 -> 0.00015266569 | AC461: =(Z461-Z474)/Z474 -> -0.00031554218 | AF461: 0 | AI461: =(AF461-AF474)/AF474 -> #DIV/0!
B462: 42825 | C462: 172655.53 | D462: =(C462-C514)/C514 -> 0.17510849 | E462: =(C462-C466)/C466 -> 0.023495175 | F462: =(C462-C475)/C475 -> 0.053286411 | G462: =C462-C463 -> 1121.31 | H462: =(C462-C487)/C487 -> 0.11353185 | J462: =C462-C463 -> 1121.31 | L462: 6541.46 | M462: =(L462-L514)/L514 -> 0.036556611 | N462: =(L462-L466)/L466 -> -0.00093317063 | O462: =L462-L463 -> 16.89 | Q462: 172732.7 | R462: =(Q462-Q514)/Q514 -> 0.10266554 | S462: =(Q462-Q466)/Q466 -> 0.018492367 | T462: =Q462-Q463 -> 1107.9 | V462: 38008.4 | W462: 44138.34 | X462: =(V462-V475)/V475 -> -0.019292447 | Y462: =(W462-W475)/W475 -> 0.020371439 | Z462: =V462+W462 -> 82146.74 | AA462: =(Z462-Z514)/Z514 -> 0.0569759 | AB462: =(Z462-Z466)/Z466 -> 0.00021100846 | AC462: =(Z462-Z475)/Z475 -> 0.0016279081 | AF462: 0 | AI462: =(AF462-AF475)/AF475 -> #DIV/0!
B463: 42818 | C463: 171534.22 | D463: =(C463-C515)/C515 -> 0.1714317 | E463: =(C463-C467)/C467 -> 0.021679161 | F463: =(C463-C476)/C476 -> 0.05269404 | G463: =C463-C464 -> 1041.67 | H463: =(C463-C488)/C488 -> 0.11195215 | J463: =C463-C464 -> 1041.67 | L463: 6524.57 | M463: =(L463-L515)/L515 -> 0.037805656 | N463: =(L463-L467)/L467 -> -0.0083577017 | O463: =L463-L464 -> 2.51 | Q463: 171624.8 | R463: =(Q463-Q515)/Q515 -> 0.097883962 | S463: =(Q463-Q467)/Q467 -> 0.011854497 | T463: =Q463-Q464 -> 1099.26 | V463: 38350.4 | W463: 42199 | X463: =(V463-V476)/V476 -> -0.013994448 | Y463: =(W463-W476)/W476 -> 0.014917232 | Z463: =V463+W463 -> 80549.4 | AA463: =(Z463-Z515)/Z515 -> 0.058635156 | AB463: =(Z463-Z467)/Z467 -> -0.015785308 | AC463: =(Z463-Z476)/Z476 -> 0.00094354077 | AF463: 0 | AI463: =(AF463-AF476)/AF476 -> #DIV/0!
... B515: 42454 | C515: 146431.26 | D515: =(C515-C567)/C567 -> 0.11607116 | E515: =(C515-C519)/C519 -> 0.0098527206 | F515: =(C515-C528)/C528 -> 0.023254075 | G515: =C515-C516 -> 398.36 | H515: =(C515-C540)/C540 -> 0.037146716 | J515: =C515-C516 -> 398.36 | L515: 6286.89 | M515: =(L515-L567)/L567 -> -0.026568171 | N515: =(L515-L519)/L519 -> -0.0035866437 | O515: =L515-L516 -> 4.06 | Q515: 156323.26 | R515: =(Q515-Q567)/Q567 -> 0.018101536 | S515: =(Q515-Q519)/Q519 -> 0.003249261 | T515: =Q515-Q516 -> 494.14 | V515: 34613.04 | W515: 41474.93 | X515: =(V515-V528)/V528 -> -0.016959021 | Y515: =(W515-W528)/W528 -> 0.0071754237 | Z515: =V515+W515 -> 76087.97 | AA515: =(Z515-Z567)/Z567 -> 0.059064794 | AB515: =(Z515-Z519)/Z519 -> -0.01196388 | AC515: =(Z515-Z528)/Z528 -> -0.0039488349 | AF515: 0 | AI515: =(AF515-AF528)/AF528 -> #DIV/0!
B516: 42447 | C516: 146032.9 | D516: =(C516-C568)/C568 -> 0.11850614 | E516: =(C516-C520)/C520 -> 0.0094284259 | G516: =C516-C517 -> 252.67 | H516: =(C516-C541)/C541 -> 0.035079959 | J516: =C516-C517 -> 252.67 | L516: 6282.83 | M516: =(L516-L568)/L568 -> -0.026575834 | N516: =(L516-L520)/L520 -> -0.0042064422 | O516: =L516-L517 -> -12.83 | Q516: 155829.12 | R516: =(Q516-Q568)/Q568 -> 0.019020072 | S516: =(Q516-Q520)/Q520 -> 0.0029771527 | T516: =Q516-Q517 -> -467.34 | V516: 34594.09 | W516: 41117.04 | X516: =(V516-V529)/V529 -> -0.01152993 | Y516: =(W516-W529)/W529 -> 0.014095762 | Z516: =V516+W516 -> 75711.13 | AA516: =(Z516-Z568)/Z568 -> 0.069842081 | AB516: =(Z516-Z520)/Z520 -> -0.012883947 | AC516: =(Z516-Z529)/Z529 -> 0.0022238951 | AF516: 0 | AI516: =(AF516-AF529)/AF529 -> #DIV/0!
B517: 42440 | C517: 145780.23 | D517: =(C517-C569)/C569 -> 0.12290965 | E517: =(C517-C521)/C521 -> 0.0083733313 | G517: =C517-C518 -> 413.68 | H517: =(C517-C542)/C542 -> 0.031654066 | J517: =C517-C518 -> 413.68 | L517: 6295.66 | M517: =(L517-L569)/L569 -> -0.030146272 | N517: =(L517-L521)/L521 -> -0.0050068433 | O517: =L517-L518 -> 1.85 | Q517: 156296.46 | R517: =(Q517-Q569)/Q569 -> 0.019687925 | S517: =(Q517-Q521)/Q521 -> 0.0014768755 | T517: =Q517-Q518 -> 549.72 | V517: 34595.57 | W517: 41995.88 | X517: =(V517-V530)/V530 -> -0.0062042627 | Y517: =(W517-W530)/W530 -> 0.012625545 | Z517: =V517+W517 -> 76591.45 | AA517: =(Z517-Z569)/Z569 -> 0.065412205 | AB517: =(Z517-Z521)/Z521 -> -0.016539517 | AC517: =(Z517-Z530)/Z530 -> 0.0040327031 | AF517: 0 | AI517: =(AF517-AF530)/AF530 -> #DIV/0!
